Workbook
Name apartmentcnt: 'MF Overview'!$W$30
Name inp_557ratio: 'MF Unit Material'!$AK$31
Name inp_boxlab: 'MF Unit Material'!$AJ$63
Name inp_caulkratio: 'MF Unit Material'!$AK$30
Name inp_condlen: 'MF Unit Material'!$AK$20
Name inp_cuwaste: 'MF Unit Material'!$AK$24
Name inp_dbtaperatio: 'MF Unit Material'!$AK$28
Name inp_dbwaste: 'MF Unit Material'!$AK$25
Name Inp_ductboardlab: 'MF Unit Material'!$AJ$61
Name inp_ductbrdsize: 'MF Unit Material'!$AK$26
Name inp_firecaulkratio: 'MF Unit Material'!$AK$29
Name inp_fittings: 'MF Unit Material'!$AK$21
Name inp_flexlabor: 'MF Unit Material'!$AJ$62
Name inp_flextaperatio: 'MF Unit Material'!$AK$35
Name inp_floors: 'MF Overview'!$O$35
Name inp_grillslab: 'MF Unit Material'!$AJ$64
Name inp_labdry: 'MF Unit Material'!$AJ$55
Name inp_labexh: 'MF Unit Material'!$AJ$54
Name inp_labpatio: 'MF Unit Material'!$AJ$56
Name inp_labpen: 'MF Unit Material'!$AJ$57
Name inp_labpipe: 'MF Pricing'!$AG$13
Name inp_labpipe: 'MF Unit Material'!$AJ$58
Name inp_loglabor: 'MF Unit Material'!$AJ$67
Name inp_metstrap: 'MF Unit Material'!$AK$23
Name inp_pookratio: 'MF Unit Material'!$AK$27
Name inp_statdist: 'MF Unit Material'!$AK$22
Name inp_statwire: 'MF Unit Material'!$AK$34
Name inp_unitlaborrough: 'MF Unit Material'!$AJ$50
Name inp_unitlabstart: 'MF Unit Material'!$AJ$51
Name inp_UVtaperatio: 'MF Unit Material'!$AK$32
Name inp_warrlab: 'MF Unit Material'!$AJ$68
Name Max_Width__Inch: [1]Data!$Q$34:$Q$38

Sheet Summary
C3: Job Sector | D3: Commercial | E3: Reduces the tax rate to 1/2%
C4: Margin | D4: M | E4: Selection of the margin rate (Low, Medium, High)
C5: Quick Turn | D5: n | E5: Reserved for public school jobs that must be completed in the summer months while school is in recession. Increases labor by 40%. Should be set to "n" in most cases
C6: Region | D6: Houston | E6: Region as identified in the proposal summary
D7: =INDEX($W$10:$W$18,MATCH($D$6,$V$10:$V$18,0),1) -> 1 | E7: Multiplier to increase/decrease labor rate for different regions. Basis of "1" is calibrated to Houston
C9: Schedule | D9: Materials Cost | E9: Labor Cost | F9: Mat. + Labor | G9: Cost/Ton (Mat) | H9: Cost/Ton (Labor) | I9: Cost/Ton (Mat+Labor) | J9: Split | K9: Updt | M9: Cooling Capacity | N9: ='Unit Sched'!D12 -> 0 | O9: tons | R9: Type | S9: Margin | T9: Quick Turn | V9: Area | W9: Labor Multiplier
C10: General | D10: =General!C14 -> 2592.5 | E10: =General!D14 -> 0 | F10: =SUM(D10:E10) -> 2592.5 | G10: =IFERROR(D10/$N$9,0) -> 0 | H10: =IFERROR(E10/$N$9,0) -> 0 | I10: =H10+G10 -> 0 | J10: =IFERROR(I10/$I$23,"") | R10: Commercial | S10: L | T10: y | V10: West | W10: 1.1
C11: Unit | D11: ='Unit Sched'!G12 -> 0 | E11: ='Unit Sched'!H12 -> 0 | F11: =SUM(D11:E11) -> 0 | G11: =IFERROR(D11/$N$9,0) -> 0 | H11: =IFERROR(E11/$N$9,0) -> 0 | I11: =H11+G11 -> 0 | J11: =IFERROR(I11/$I$23,"") | M11: Mercury Operations Cost Based Profit Calculator ( f(Labor) ) | R11: Public | S11: M | T11: n | V11: San Antonio | W11: 1
C12: CW Pipe | D12: ='CW Pipe Sched'!O413 -> 0 | E12: ='CW Pipe Sched'!R413 -> 0 | F12: =SUM(D12:E12) -> 0 | G12: =IFERROR(D12/$N$9,0) -> 0 | H12: =IFERROR(E12/$N$9,0) -> 0 | I12: =H12+G12 -> 0 | J12: =IFERROR(I12/$I$23,"") | M12: Boundaries | N12: Variable | O12: Pre- Tax | P12: Notes | R12: Multi Family | S12: H | V12: Austin | W12: 1.15
C13: VAV | D13: ='VAV Schedule'!L37 -> 0 | E13: ='VAV Schedule'!M37 -> 0 | F13: =SUM(D13:E13) -> 0 | G13: =IFERROR(D13/$N$9,0) -> 0 | H13: =IFERROR(E13/$N$9,0) -> 0 | I13: =H13+G13 -> 0 | J13: =IFERROR(I13/$I$23,"") | M13: Target EOY Net | N13: 0.1 | P13: Target end of year profitability | V13: DFW | W13: 1.1
C14: Heater | D14: ='Electric Heat Sched'!G24 -> 0 | E14: ='Electric Heat Sched'!H24 -> 0 | F14: =SUM(D14:E14) -> 0 | G14: =IFERROR(D14/$N$9,0) -> 0 | H14: =IFERROR(E14/$N$9,0) -> 0 | I14: =H14+G14 -> 0 | J14: =IFERROR(I14/$I$23,"") | M14: Overhead Variable | N14: 0.5 | P14: Overhead that functions based on project size | V14: Houston | W14: 1
C15: Fan | D15: ='Fan Schedule'!M30 -> 0 | E15: ='Fan Schedule'!P30 -> 0 | F15: =SUM(D15:E15) -> 0 | G15: =IFERROR(D15/$N$9,0) -> 0 | H15: =IFERROR(E15/$N$9,0) -> 0 | I15: =H15+G15 -> 0 | J15: =IFERROR(I15/$I$23,"") | M15: Overhead Fixed | N15: =INDEX($R$17:$R$43,MATCH($E$23,$T$17:$T$43,1)) -> 1000 | P15: Fixed overhead component ($2,900 per model) | V15: Panhandle | W15: 1.1
C16: Louver / Fire Damper | D16: ='Louvers & FD'!M30+'Louvers & FD'!M75 -> 0 | E16: ='Louvers & FD'!P30+'Louvers & FD'!P75 -> 0 | F16: =SUM(D16:E16) -> 0 | G16: =IFERROR(D16/$N$9,0) -> 0 | H16: =IFERROR(E16/$N$9,0) -> 0 | I16: =H16+G16 -> 0 | J16: =IFERROR(I16/$I$23,"") | M16: L | N16: -0.02 | R16: "Fixed" Overhead | S16: Gross Sale | T16: Labor Est | V16: South Texas | W16: 0.9
C17: Metal Duct | D17: ='Metal Duct'!W754+'Unit Sched'!J12 -> 0 | E17: ='Metal Duct'!X754+'Unit Sched'!K12 -> 0 | F17: =SUM(D17:E17) -> 0 | G17: =IFERROR(D17/$N$9,0) -> 0 | H17: =IFERROR(E17/$N$9,0) -> 0 | I17: =H17+G17 -> 0 | J17: =IFERROR(I17/$I$23,"") | M17: M | N17: 0 | R17: 1000 | S17: 0 | T17: 0 | V17: East Texas | W17: 1.1
C18: Diffusers | D18: ='Diffuser Schedule'!L24 -> 0 | E18: ='Diffuser Schedule'!M24 -> 0 | F18: =SUM(D18:E18) -> 0 | G18: =IFERROR(D18/$N$9,0) -> 0 | H18: =IFERROR(E18/$N$9,0) -> 0 | I18: =H18+G18 -> 0 | J18: =IFERROR(I18/$I$23,"") | M18: H | N18: 0.02 | R18: 1000 | S18: 10000 | T18: =S18*0.35 -> 3500 | V18: North Texas | W18: 1.1
C19: MF Living Units | F19: =SUM(D19:E19) -> 0 | G19: =IFERROR(D19/$N$9,0) -> 0 | H19: =IFERROR(E19/$N$9,0) -> 0 | I19: =H19+G19 -> 0 | J19: =IFERROR(I19/$I$23,"") | M19: Total Adj | N19: =INDEX($N$16:$N$18,MATCH($D$4,$M$16:$M$18,0),1)+N13 -> 0.1 | R19: 1100 | S19: 15000 | T19: =S19*0.35 -> 5250
C20: MF Common Area Duct Board / Flex | F20: =SUM(D20:E20) -> 0 | G20: =IFERROR(D20/$N$9,0) -> 0 | H20: =IFERROR(E20/$N$9,0) -> 0 | I20: =H20+G20 -> 0 | J20: =IFERROR(I20/$I$23,"") | M20: +Fixed | N20: =N15 -> 1000 | R20: 1200 | S20: 25000 | T20: =S20*0.35 -> 8750
C21: Labor Scalers | R21: 1300 | S21: 50000 | T21: =S21*0.3 -> 15000
C22: Quick Turn | M22: Base Profit Calculator | R22: 1350 | S22: 70000 | T22: =S22*0.3 -> 21000
C23: Base Schedule Total | D23: =SUM(D10:D20) -> 2592.5 | E23: =IF($D$5="y",1.4,1)*SUM(E10:E20)*$D$7 -> 0 | F23: =SUM(D23:E23) -> 2592.5 | G23: =SUM(G10:G20) -> 0 | H23: =SUM(H10:H20) -> 0 | I23: =SUM(I10:I20) -> 0 | M23: Boundaries | N23: Variable | O23: Pre- Tax | P23: Notes | R23: 1400 | S23: =S24-10000 -> 80000 | T23: =S23*0.3 -> 24000
M24: Min Labor Mult | N24: 0.8 | O24: =ROUND(D23+(1+N24)*E23,-2) -> 2600 | P24: Min allowable labor multiple in all scenarios | R24: =R23+100 -> 1500 | S24: =S25-10000 -> 90000 | T24: =S24*0.3 -> 27000
C25: Base Cost Breakout | D25: Materials | E25: Labor | M25: Max Labor Mult | N25: 2.5 | O25: =ROUND(D23+(1+N25)*E23,-2) -> 2600 | P25: Maximum labor multiplier for projects with mostly equipment | R25: =R24+100 -> 1600 | S25: =S26-10000 -> 100000 | T25: =S25*0.27 -> 27000
C26: Split | D26: =D23/$F$23 -> 1 | E26: =E23/$F$23 -> 0 | M26: L | N26: 0.18 | O26: =ROUND($F$23/(1-N26),-2) -> 3200 | P26: Preselected low profit margin | R26: =R25+100 -> 1700 | S26: =S27-10000 -> 110000 | T26: =S26*0.27 -> 29700
M27: M | N27: 0.2 | O27: =ROUND($F$23/(1-N27),-2) -> 3200 | P27: Preselected medium profit margin | R27: =R26+100 -> 1800 | S27: =S28-10000 -> 120000 | T27: =S27*0.27 -> 32400
C28: Mercury Operations Profit Calculator | E28: Price/Ton | G28: Tax Rates | M28: H | N28: 0.22 | O28: =ROUND($F$23/(1-N28),-2) -> 3300 | P28: Preselected high profit margin | R28: =R27+100 -> 1900 | S28: =S29-10000 -> 130000 | T28: =S28*0.27 -> 35100
C29: Bid | D29: =(($N$20+$E$23*$N$14)+$F$23)/(1-$N$19)+IF($D$3="Public",0.005*$D23,0) -> 3991.6667 | E29: =D29/$N$9 -> #DIV/0! | G29: Tax on Materials | H29: =IF(D3="Public",0,0.0825) -> 0.0825 | M29: 75000 | N29: =IF($F$23>M29,0,IF($F$23>=M30,1%,0)) -> 0 | R29: =R28+100 -> 2000 | S29: =S30-10000 -> 140000 | T29: =S29*0.27 -> 37800
C30: Gross Profit | D30: =D29-F23 -> 1399.1667 | E30: =D30/$N$9 -> #DIV/0! | G30: Tax on Labor | H30: 0 | M30: 50000 | N30: =IF(SUM(N$29:N29)>0,0,IF($F$23>M30,0,IF($F$23>=M31,2%,0))) -> 0 | R30: =R29+100 -> 2100 | S30: =S31-10000 -> 150000 | T30: =S30*0.25 -> 37500
C31: Margin | D31: =D30/D29 -> 0.35052192 | M31: 25000 | N31: =IF(SUM(N$29:N30)>0,0,IF($F$23>M31,0,IF($F$23>=M32,3%,0))) -> 0 | R31: =R30+100 -> 2200 | S31: =S32-10000 -> 160000 | T31: =S31*0.25 -> 40000
C32: Tax | D32: =ROUND(D23*($H$29)+E23*($H$30),-1) -> 210 | M32: 15000 | N32: =IF(SUM(N$29:N31)>0,0,IF($F$23>M32,0,IF($F$23>=M33,5%,0))) -> 0 | R32: =R31+100 -> 2300 | S32: =S33-10000 -> 170000 | T32: =S32*0.25 -> 42500
C33: Bid + Tax | D33: =D29+D32 -> 4201.6667 | M33: 10000 | N33: =IF(SUM(N$29:N32)>0,0,IF($F$23>M33,0,IF($F$23>=M34,9%,0))) -> 0 | R33: =R32+100 -> 2400 | S33: =S34-10000 -> 180000 | T33: =S33*0.25 -> 45000
C34: Note: 0.5% added for non-profit jobs to cover tax on materials | M34: 5000 | N34: =IF(SUM(N$29:N33)>0,0,IF($F$23>M34,0,IF($F$23>0,12%,0))) -> 0.12 | R34: =R33+100 -> 2500 | S34: =S35-10000 -> 190000 | T34: =S34*0.25 -> 47500
M35: Public Add | N35: =IF(D3="Public",5%,0) -> 0 | R35: =R34+100 -> 2600 | S35: =S36-10000 -> 200000 | T35: =S35*0.25 -> 50000
C36: Base Profit Calculator | E36: Price/Ton | M36: Labor Add | N36: =MAX(0,E26-0.25)*0.75 -> 0 | R36: =R35+100 -> 2700 | S36: =S37-10000 -> 210000 | T36: =S36*0.25 -> 52500
C37: Bid | D37: =O40+IF($D$3="Public",0.005*$D23,0) -> 2600 | E37: =D37/$N$9 -> #DIV/0! | M37: Total Add | N37: =SUM(N29:N36) -> 0.12 | R37: =R36+100 -> 2800 | S37: =S38-10000 -> 220000 | T37: =S37*0.25 -> 55000
C38: Gross Profit | D38: =D37-F23 -> 7.5 | E38: =D38/$N$9 -> #DIV/0! | M38: Base | N38: =INDEX($N$26:$N$28,MATCH($D$4,$M$26:$M$28,0),1) -> 0.2 | R38: =R37+100 -> 2900 | S38: =S39-10000 -> 230000 | T38: =S38*0.25 -> 57500
C39: Margin | D39: =D38/D37 -> 0.0028846154 | M39: Base + Add | N39: =SUM(N37:N38) -> 0.32 | O39: =ROUND($F$23/(1-N39),-2) -> 3800 | P39: Selected Margin | R39: =R38+100 -> 3000 | S39: =S40-10000 -> 240000 | T39: =S39*0.25 -> 60000
C40: Tax | D40: =ROUND(D23*($H$29)+E23*($H$30),-1) -> 210 | M40: Final w/ Boundaries | O40: =MIN(MAX(O39,O24),O25) -> 2600 | R40: =R39+100 -> 3100 | S40: 250000 | T40: =S40*0.25 -> 62500
C41: Bid + Tax | D41: =D37+D40 -> 2810 | R41: =R40+100 -> 3200 | S41: 2000000 | T41: =S41*0.25 -> 500000
C42: Note: 0.5% added for non-profit jobs to cover tax on materials | R42: 4000 | S42: 4000000 | T42: =S42*0.25 -> 1000000
R43: 6000 | S43: 6000000 | T43: =S43*0.25 -> 1500000
C46: Additions Needed For Next Model Version
C47: 1) Add travel per zipcode logic
C48: 2) Connect multifamily components
C49: 3) Update Electric Heat Schedule (similar to the fan schedule)
C50: 4) Add roof caps to the exhaust fan tab
C51: 5)
C52: 6) Build in duct model so that the weight is modified by dimension of the duct
C53: 7) Add access door option to unit schedule
C54: 8) Add option for multi head mini splits in unit section
C55: 9) Add stainless duct option
C56: 10) Add a complexity calculator for ducting installs
C57: 11) Add job size labor scaler
... C67: 21)

Sheet OverheadCalculator
B2: Commercial Construction Overhead Calculator Summary | J2: Commercial Construction Overhead Calculator Summary (Calculated to Labor instead of Sales) | R2: Testing
C3: Component | D3: Fixed | E3: Var. (H) | F3: Var. (L) | K3: Component | L3: Fixed | M3: Var. (H) | N3: Var. (L) | S3: 1000000 | T3: =S3+1000000 -> 2000000 | U3: =T3+1000000 -> 3000000 | V3: =U3+1000000 -> 4000000 | W3: =V3+1000000 -> 5000000 | X3: =W3+1000000 -> 6000000 | Y3: =X3+1000000 -> 7000000 | Z3: =Y3+1000000 -> 8000000 | AA3: =Z3+1000000 -> 9000000 | AB3: =AA3+1000000 -> 10000000 | AC3: <<<<Sales Rate
C4: President | E4: 0.01 | F4: 0.01 | K4: President | M4: =K17 -> 0.04 | N4: =K17 -> 0.04 | S4: =AVERAGE($M4:$N4)*(S$3/4) -> 10000 | T4: =AVERAGE($M4:$N4)*(T$3/4) -> 20000 | U4: =AVERAGE($M4:$N4)*(U$3/4) -> 30000 | V4: =AVERAGE($M4:$N4)*(V$3/4) -> 40000 | W4: =AVERAGE($M4:$N4)*(W$3/4) -> 50000 | X4: =AVERAGE($M4:$N4)*(X$3/4) -> 60000 | Y4: =AVERAGE($M4:$N4)*(Y$3/4) -> 70000 | Z4: =AVERAGE($M4:$N4)*(Z$3/4) -> 80000 | ... AB4: =AVERAGE($M4:$N4)*(AB$3/4) -> 100000
C5: Project Manager | D5: =C33 -> 2884 | E5: =C38 -> 0.02625 | F5: =52500/3000000 -> 0.0175 | K5: Project Manager | L5: =K33 -> 2884 | M5: =K38 -> 0.105 | N5: =M5*0.65 -> 0.06825 | S5: =AVERAGE($M5:$N5)*(S$3/4) -> 21656.25 | T5: =AVERAGE($M5:$N5)*(T$3/4) -> 43312.5 | U5: =AVERAGE($M5:$N5)*(U$3/4) -> 64968.75 | V5: =AVERAGE($M5:$N5)*(V$3/4) -> 86625 | W5: =AVERAGE($M5:$N5)*(W$3/4) -> 108281.25 | X5: =AVERAGE($M5:$N5)*(X$3/4) -> 129937.5 | Y5: =AVERAGE($M5:$N5)*(Y$3/4) -> 151593.75 | Z5: =AVERAGE($M5:$N5)*(Z$3/4) -> 173250 | ... AB5: =AVERAGE($M5:$N5)*(AB$3/4) -> 216562.5
C6: Field Supervisor | E6: =C47 -> 0.0325 | F6: =C45/3000000 -> 0.021666667 | K6: Field Supervisor | M6: =K47 -> 0.13 | N6: =M6*0.65 -> 0.0845 | S6: =AVERAGE($M6:$N6)*(S$3/4) -> 26812.5 | T6: =AVERAGE($M6:$N6)*(T$3/4) -> 53625 | U6: =AVERAGE($M6:$N6)*(U$3/4) -> 80437.5 | V6: =AVERAGE($M6:$N6)*(V$3/4) -> 107250 | W6: =AVERAGE($M6:$N6)*(W$3/4) -> 134062.5 | X6: =AVERAGE($M6:$N6)*(X$3/4) -> 160875 | Y6: =AVERAGE($M6:$N6)*(Y$3/4) -> 187687.5 | Z6: =AVERAGE($M6:$N6)*(Z$3/4) -> 214500 | ... AB6: =AVERAGE($M6:$N6)*(AB$3/4) -> 268125
C7: Human Resources | E7: =C58 -> 0.008 | F7: =48000/8000000 -> 0.006 | K7: Human Resources | M7: =K58 -> 0.024 | N7: =M7*0.65 -> 0.0156 | S7: =AVERAGE($M7:$N7)*(S$3/4) -> 4950 | T7: =AVERAGE($M7:$N7)*(T$3/4) -> 9900 | U7: =AVERAGE($M7:$N7)*(U$3/4) -> 14850 | V7: =AVERAGE($M7:$N7)*(V$3/4) -> 19800 | W7: =AVERAGE($M7:$N7)*(W$3/4) -> 24750 | X7: =AVERAGE($M7:$N7)*(X$3/4) -> 29700 | Y7: =AVERAGE($M7:$N7)*(Y$3/4) -> 34650 | Z7: =AVERAGE($M7:$N7)*(Z$3/4) -> 39600 | ... AB7: =AVERAGE($M7:$N7)*(AB$3/4) -> 49500
C8: Estimation | E8: =C69 -> 0.02 | F8: =20000/1500000 -> 0.013333333 | K8: Estimation | M8: =K69 -> 0.08 | N8: =M8*0.65 -> 0.052 | S8: =AVERAGE($M8:$N8)*(S$3/4) -> 16500 | T8: =AVERAGE($M8:$N8)*(T$3/4) -> 33000 | U8: =AVERAGE($M8:$N8)*(U$3/4) -> 49500 | V8: =AVERAGE($M8:$N8)*(V$3/4) -> 66000 | W8: =AVERAGE($M8:$N8)*(W$3/4) -> 82500 | X8: =AVERAGE($M8:$N8)*(X$3/4) -> 99000 | Y8: =AVERAGE($M8:$N8)*(Y$3/4) -> 115500 | Z8: =AVERAGE($M8:$N8)*(Z$3/4) -> 132000 | ... AB8: =AVERAGE($M8:$N8)*(AB$3/4) -> 165000
C9: Rent/Office | E9: =C81 -> 0.0186 | F9: =37200/3000000 -> 0.0124 | K9: Rent/Office | M9: =K81 -> 0.0744 | N9: =M9*0.65 -> 0.04836 | S9: =AVERAGE($M9:$N9)*(S$3/4) -> 15345 | T9: =AVERAGE($M9:$N9)*(T$3/4) -> 30690 | U9: =AVERAGE($M9:$N9)*(U$3/4) -> 46035 | V9: =AVERAGE($M9:$N9)*(V$3/4) -> 61380 | W9: =AVERAGE($M9:$N9)*(W$3/4) -> 76725 | X9: =AVERAGE($M9:$N9)*(X$3/4) -> 92070 | Y9: =AVERAGE($M9:$N9)*(Y$3/4) -> 107415 | Z9: =AVERAGE($M9:$N9)*(Z$3/4) -> 122760 | ... AB9: =AVERAGE($M9:$N9)*(AB$3/4) -> 153450
C10: Insurance & Services | E10: =C95 -> 0.015 | F10: =30000/3000000 -> 0.01 | K10: Insurance & Services | M10: =K95 -> 0.06 | N10: =M10*0.65 -> 0.039 | S10: =AVERAGE($M10:$N10)*(S$3/4) -> 12375 | T10: =AVERAGE($M10:$N10)*(T$3/4) -> 24750 | U10: =AVERAGE($M10:$N10)*(U$3/4) -> 37125 | V10: =AVERAGE($M10:$N10)*(V$3/4) -> 49500 | W10: =AVERAGE($M10:$N10)*(W$3/4) -> 61875 | X10: =AVERAGE($M10:$N10)*(X$3/4) -> 74250 | Y10: =AVERAGE($M10:$N10)*(Y$3/4) -> 86625 | Z10: =AVERAGE($M10:$N10)*(Z$3/4) -> 99000 | ... AB10: =AVERAGE($M10:$N10)*(AB$3/4) -> 123750
C11: Total | D11: =ROUND(SUM(D4:D10),-2) -> 2900 | E11: =SUM(E4:E10) -> 0.13035 | F11: =SUM(F4:F10) -> 0.0909 | K11: Total | L11: =ROUND(SUM(L4:L10),-2) -> 2900 | M11: =SUM(M4:M10) -> 0.5134 | N11: =SUM(N4:N10) -> 0.34771
S12: Project Managers
S13: 1 | T13: 1 | U13: 1 | V13: 1 | W13: 1 | X13: 1 | Y13: 1 | Z13: 1 | AA13: 1 | AB13: 1
S14: =S4/S13 -> 10000 | T14: =T4/T13 -> 20000 | U14: =U4/U13 -> 30000 | V14: =V4/V13 -> 40000 | W14: =W4/W13 -> 50000 | X14: =X4/X13 -> 60000 | Y14: =Y4/Y13 -> 70000 | Z14: =Z4/Z13 -> 80000 | ... AB14: =AB4/AB13 -> 100000 | AC14: <<<<Calc Avg Salary
B15: President Calculator | J15: President Calculator | S15: 70000 | T15: 70000 | U15: 70000 | V15: 70000 | W15: 70000 | X15: 70000 | Y15: 70000 | Z15: 70000 | AA15: 70000 | AB15: 70000 | AC15: <<<<Act Avg Salary
C16: Rate | D16: Notes | K16: Rate | L16: Notes | S16: =S15*S13-S14*S13 -> 60000 | T16: =T15*T13-T14*T13 -> 50000 | U16: =U15*U13-U14*U13 -> 40000 | V16: =V15*V13-V14*V13 -> 30000 | W16: =W15*W13-W14*W13 -> 20000 | X16: =X15*X13-X14*X13 -> 10000 | Y16: =Y15*Y13-Y14*Y13 -> 0 | Z16: =Z15*Z13-Z14*Z13 -> -10000 | ... AB16: =AB15*AB13-AB14*AB13 -> -30000 | AC16: Net Delta
C17: 0.01 | D17: Assumed pay rate relative to gross sales | K17: 0.04 | L17: Assumed pay rate relative to gross sales
B19: Project Manager Calculator | J19: Project Manager Calculator | S19: Project Managers
C20: Notes: | K20: Notes: | S20: 1 | T20: 1 | U20: 1 | V20: 2 | W20: 2 | X20: 2 | Y20: 3 | Z20: 3 | AA20: 3 | AB20: 4
D21: - It was determined that a PM can handle about $2MM of work across 8 projects | L21: - It was determined that a PM can handle about $500k of labor cost across 8 projects | S21: =S5/S20 -> 21656.25 | T21: =T5/T20 -> 43312.5 | U21: =U5/U20 -> 64968.75 | V21: =V5/V20 -> 43312.5 | W21: =W5/W20 -> 54140.625 | X21: =X5/X20 -> 64968.75 | Y21: =Y5/Y20 -> 50531.25 | Z21: =Z5/Z20 -> 57750 | ... AB21: =AB5/AB20 -> 54140.625 | AC21: <<<<Calc Avg Salary
D22: - Based on that it's estimated that there is a 1) fixed labor component independent of project size | L22: - Based on that it's estimated that there is a 1) fixed labor component independent of project size | S22: 65000 | T22: 65000 | U22: 65000 | V22: 65000 | W22: 65000 | X22: 65000 | Y22: 65000 | Z22: 65000 | AA22: 65000 | AB22: 65000 | AC22: <<<<Act Avg Salary
D23: - 2) variable for scheduling, sheet metal duct ordering, invoicing, and related | L23: - 2) variable for scheduling, sheet metal duct ordering, invoicing, and related | S23: =S22*S20-S21*S20 -> 43343.75 | T23: =T22*T20-T21*T20 -> 21687.5 | U23: =U22*U20-U21*U20 -> 31.25 | V23: =V22*V20-V21*V20 -> 43375 | W23: =W22*W20-W21*W20 -> 21718.75 | X23: =X22*X20-X21*X20 -> 62.5 | Y23: =Y22*Y20-Y21*Y20 -> 43406.25 | Z23: =Z22*Z20-Z21*Z20 -> 21750 | ... AB23: =AB22*AB20-AB21*AB20 -> 43437.5 | AC23: Net Delta
D24: - Calculations are based on an assumed income of $75,000/yr for a project manager | L24: - Calculations are based on an assumed income of $75,000/yr for a project manager
D25: - Weekly PM cost is assumed to be: $1,442 ($75k/yr) | L25: - Weekly PM cost is assumed to be: $1,442 ($75k/yr) | S25: Field Supervisor
D26: - Based on our experience and assumptions above, we believe ~30% relates to a fixed per project cost and ~70% is a function of project size (variable) | L26: - Based on our experience and assumptions above, we believe ~30% relates to a fixed per project cost and ~70% is a function of project size (variable) | S26: 1 | T26: 1 | U26: 1 | V26: 2 | W26: 2 | X26: 2 | Y26: 3 | Z26: 3 | AA26: 3 | AB26: 4
D27: - 70% of a PM's pay of $75k/yr = $52,500 | L27: - 70% of a PM's pay of $75k/yr = $52,500 | S27: =S6/S26 -> 26812.5 | T27: =T6/T26 -> 53625 | U27: =U6/U26 -> 80437.5 | V27: =V6/V26 -> 53625 | W27: =W6/W26 -> 67031.25 | X27: =X6/X26 -> 80437.5 | Y27: =Y6/Y26 -> 62562.5 | Z27: =Z6/Z26 -> 71500 | ... AB27: =AB6/AB26 -> 67031.25 | AC27: <<<<Calc Avg Salary
C28: Fixed Time Components | K28: Fixed Time Components | S28: 70000 | T28: 70000 | U28: 70000 | V28: 70000 | W28: 70000 | X28: 70000 | Y28: 70000 | Z28: 70000 | AA28: 70000 | AB28: 70000 | AC28: <<<<Act Avg Salary
C29: Weeks | D29: Description | K29: Weeks | L29: Description | S29: =S28*S26-S27*S26 -> 43187.5 | T29: =T28*T26-T27*T26 -> 16375 | U29: =U28*U26-U27*U26 -> -10437.5 | V29: =V28*V26-V27*V26 -> 32750 | W29: =W28*W26-W27*W26 -> 5937.5 | X29: =X28*X26-X27*X26 -> -20875 | Y29: =Y28*Y26-Y27*Y26 -> 22312.5 | Z29: =Z28*Z26-Z27*Z26 -> -4500 | ... AB29: =AB28*AB26-AB27*AB26 -> 11875 | AC29: Net Delta
C30: =8/5 -> 1.6 | D30: Private | G30: Fixed: Onboarding paperwork, Permits, Submittals, Equipment Orders, Rentals, & Closind Docs | K30: =8/5 -> 1.6 | L30: Private | O30: Fixed: Onboarding paperwork, Permits, Submittals, Equipment Orders, Rentals, & Closind Docs
C31: =12/5 -> 2.4 | D31: Public | G31: Fixed: Onboarding paperwork, Permits, Submittals, Equipment Orders, Rentals, & Closind Docs | K31: =12/5 -> 2.4 | L31: Public | O31: Fixed: Onboarding paperwork, Permits, Submittals, Equipment Orders, Rentals, & Closind Docs
C32: =(C31+C30)/2 -> 2 | D32: Average | G32: Predicted weeks of work associated with a project regardless of size | K32: =(K31+K30)/2 -> 2 | L32: Average | O32: Predicted weeks of work associated with a project regardless of size | S32: Human Resources
C33: =1442*C32 -> 2884 | D33: Fixed Project Cost based on weekly PM cost | K33: =1442*K32 -> 2884 | L33: Fixed Project Cost based on weekly PM cost | S33: 1 | T33: 1 | U33: 1 | V33: 1 | W33: 1 | X33: 1 | Y33: 1 | Z33: 1.5 | AA33: 1.5 | AB33: 1.5
C34: Variable Time Components | K34: Variable Time Components | S34: =S7/S33 -> 4950 | T34: =T7/T33 -> 9900 | U34: =U7/U33 -> 14850 | V34: =V7/V33 -> 19800 | W34: =W7/W33 -> 24750 | X34: =X7/X33 -> 29700 | Y34: =Y7/Y33 -> 34650 | Z34: =Z7/Z33 -> 26400 | ... AB34: =AB7/AB33 -> 33000 | AC34: <<<<Calc Avg Salary
C35: Metric | D35: Description | K35: Metric | L35: Description | S35: 45000 | T35: 45000 | U35: 45000 | V35: 45000 | W35: 45000 | X35: 45000 | Y35: 45000 | Z35: 45000 | AA35: 45000 | AB35: 45000 | AC35: <<<<Act Avg Salary
C36: 52500 | D36: Salary applicable to project size | K36: 52500 | L36: Salary applicable to project size | S36: =S35*S33-S34*S33 -> 40050 | T36: =T35*T33-T34*T33 -> 35100 | U36: =U35*U33-U34*U33 -> 30150 | V36: =V35*V33-V34*V33 -> 25200 | W36: =W35*W33-W34*W33 -> 20250 | X36: =X35*X33-X34*X33 -> 15300 | Y36: =Y35*Y33-Y34*Y33 -> 10350 | Z36: =Z35*Z33-Z34*Z33 -> 27900 | ... AB36: =AB35*AB33-AB34*AB33 -> 18000 | AC36: Net Delta
C37: 2000000 | D37: Assumed comfortable average limit for a project manager overseeing commercial projects (8 projects @ $250,000/project) | K37: 500000 | L37: Assumed comfortable average limit for a project manager overseeing commercial projects (8 projects @ $250,000/project)
C38: =C36/C37 -> 0.02625 | D38: Percentage of project related size (variable cost) | K38: =K36/K37 -> 0.105 | L38: Percentage of project related size (variable cost) | S38: Estimation Services
S39: 1 | T39: 1 | U39: 2 | V39: 2 | W39: 2 | X39: 3 | Y39: 3 | Z39: 3 | AA39: 4 | AB39: 4
B40: Field Supervisor Calculator | J40: Field Supervisor Calculator | S40: =S8/S39 -> 16500 | T40: =T8/T39 -> 33000 | U40: =U8/U39 -> 24750 | V40: =V8/V39 -> 33000 | W40: =W8/W39 -> 41250 | X40: =X8/X39 -> 33000 | Y40: =Y8/Y39 -> 38500 | Z40: =Z8/Z39 -> 44000 | ... AB40: =AB8/AB39 -> 41250 | AC40: <<<<Calc Avg Salary
C41: Notes: | D41: NOT SURE IF WE CAN HAVE A PURE FIELD SUPERVISOR. THIS COST NEEDS TO BE FOLDED INTO JOB LABOR CALCULATOR | K41: Notes: | L41: NOT SURE IF WE CAN HAVE A PURE FIELD SUPERVISOR. THIS COST NEEDS TO BE FOLDED INTO JOB LABOR CALCULATOR | S41: 12000 | T41: 12000 | U41: 12000 | V41: 12000 | W41: 12000 | X41: 12000 | Y41: 12000 | Z41: 12000 | AA41: 12000 | AB41: 12000 | AC41: <<<<Act Avg Salary
D42: - It is assumed that 1 field supervisor team member can handle $2,000,000 employees | L42: - It is assumed that 1 field supervisor team member can handle $2,000,000 employees | S42: =S41*S39-S40*S39 -> -4500 | T42: =T41*T39-T40*T39 -> -21000 | U42: =U41*U39-U40*U39 -> -25500 | V42: =V41*V39-V40*V39 -> -42000 | W42: =W41*W39-W40*W39 -> -58500 | X42: =X41*X39-X40*X39 -> -63000 | Y42: =Y41*Y39-Y40*Y39 -> -79500 | Z42: =Z41*Z39-Z40*Z39 -> -96000 | ... AB42: =AB41*AB39-AB40*AB39 -> -117000 | AC42: Net Delta
D43: - Assumed salary of $65,000 | L43: - Assumed salary of $65,000
C44: Metric | D44: Description | K44: Metric | L44: Description | S44: Rent/Office
C45: 65000 | D45: Salary applicable to project size | K45: 65000 | L45: Salary applicable to project size | S45: 1 | T45: 1 | U45: 1 | V45: 1 | W45: 1 | X45: 1.5 | Y45: 1.5 | Z45: 1.5 | AA45: 1.5 | AB45: 1.5
C46: 2000000 | D46: Gross sales supported per HR team member | K46: 500000 | L46: Gross sales supported per Field Supervisor team member | S46: =S9/S45 -> 15345 | T46: =T9/T45 -> 30690 | U46: =U9/U45 -> 46035 | V46: =V9/V45 -> 61380 | W46: =W9/W45 -> 76725 | X46: =X9/X45 -> 61380 | Y46: =Y9/Y45 -> 71610 | Z46: =Z9/Z45 -> 81840 | ... AB46: =AB9/AB45 -> 102300 | AC46: <<<<Calc Avg Salary
C47: =C45/C46 -> 0.0325 | D47: Percentage of project related HR services | K47: =K45/K46 -> 0.13 | L47: Percentage of project related to Field supervision services | S47: 35000 | T47: 35000 | U47: 35000 | V47: 35000 | W47: 35000 | X47: 35000 | Y47: 35000 | Z47: 35000 | AA47: 35000 | AB47: 35000 | AC47: <<<<Act Avg Salary
S48: =S47*S45-S46*S45 -> 19655 | T48: =T47*T45-T46*T45 -> 4310 | U48: =U47*U45-U46*U45 -> -11035 | V48: =V47*V45-V46*V45 -> -26380 | W48: =W47*W45-W46*W45 -> -41725 | X48: =X47*X45-X46*X45 -> -39570 | Y48: =Y47*Y45-Y46*Y45 -> -54915 | Z48: =Z47*Z45-Z46*Z45 -> -70260 | ... AB48: =AB47*AB45-AB46*AB45 -> -100950 | AC48: Net Delta
B49: Human Resource Calculator | J49: Human Resource Calculator
C50: Notes: | K50: Notes: | S50: Unsurance & Services
D51: - It is assumed that 1 human resource team member can handle 100 employees | L51: - It is assumed that 1 human resource team member can handle 100 employees | S51: 1 | T51: 1 | U51: 1 | V51: 1 | W51: 1 | X51: 1.5 | Y51: 1.5 | Z51: 1.5 | AA51: 1.5 | AB51: 1.5
D52: - To take a slightly more conservative approach, we will assume 40 employees can be managed per HR manager | L52: - To take a slightly more conservative approach, we will assume 40 employees can be managed per HR manager | S52: =S10/S51 -> 12375 | T52: =T10/T51 -> 24750 | U52: =U10/U51 -> 37125 | V52: =V10/V51 -> 49500 | W52: =W10/W51 -> 61875 | X52: =X10/X51 -> 49500 | Y52: =Y10/Y51 -> 57750 | Z52: =Z10/Z51 -> 66000 | ... AB52: =AB10/AB51 -> 82500 | AC52: <<<<Calc Avg Salary
D53: - 40 employees at an average rate of $23/hr = $1,800,000/yr in payroll | L53: - 40 employees at an average rate of $23/hr = $1,800,000/yr in payroll | S53: 15000 | T53: 15000 | U53: 15000 | V53: 22000 | W53: 22000 | X53: 22000 | Y53: 22000 | Z53: 30000 | AA53: 30000 | AB53: 30000 | AC53: <<<<Act Avg Salary
D54: - Assuming total payroll is ~30% of total gross sales or ~ $6,000,000 | L54: - Assuming total payroll is ~30% of total gross sales or ~ $6,000,000 | S54: =S53*S51-S52*S51 -> 2625 | T54: =T53*T51-T52*T51 -> -9750 | U54: =U53*U51-U52*U51 -> -22125 | V54: =V53*V51-V52*V51 -> -27500 | W54: =W53*W51-W52*W51 -> -39875 | X54: =X53*X51-X52*X51 -> -41250 | Y54: =Y53*Y51-Y52*Y51 -> -53625 | Z54: =Z53*Z51-Z52*Z51 -> -54000 | ... AB54: =AB53*AB51-AB52*AB51 -> -78750 | AC54: Net Delta
C55: Metric | D55: Description | K55: Metric | L55: Description
C56: 48000 | D56: Salary applicable to project size | K56: 48000 | L56: Salary applicable to project size | S56: Total Nets
C57: 6000000 | D57: Gross sales supported per HR team member | K57: 2000000 | L57: Gross sales labor supported per HR team member | S57: =S16+S23+S29+S36+S42+S48+S54 -> 204361.25 | T57: =T16+T23+T29+T36+T42+T48+T54 -> 96722.5 | U57: =U16+U23+U29+U36+U42+U48+U54 -> 1083.75 | V57: =V16+V23+V29+V36+V42+V48+V54 -> 35445 | W57: =W16+W23+W29+W36+W42+W48+W54 -> -72193.75 | X57: =X16+X23+X29+X36+X42+X48+X54 -> -139332.5 | Y57: =Y16+Y23+Y29+Y36+Y42+Y48+Y54 -> -111971.25 | Z57: =Z16+Z23+Z29+Z36+Z42+Z48+Z54 -> -185110 | ... AB57: =AB16+AB23+AB29+AB36+AB42+AB48+AB54 -> -253387.5
C58: =C56/C57 -> 0.008 | D58: Percentage of project related HR services | K58: =K56/K57 -> 0.024 | L58: Percentage of project related HR services | S58: Percent of Sales
S59: =S57/S3 -> 0.20436125 | T59: =T57/T3 -> 0.04836125 | U59: =U57/U3 -> 0.00036125 | V59: =V57/V3 -> 0.00886125 | W59: =W57/W3 -> -0.01443875 | X59: =X57/X3 -> -0.023222083 | Y59: =Y57/Y3 -> -0.015995893 | Z59: =Z57/Z3 -> -0.02313875 | ... AB59: =AB57/AB3 -> -0.02533875
B60: Estimating Resource Calculator | J60: Estimating Resource Calculator
C61: Notes: | K61: Notes:
D62: - It is assumed that 1 estimating team member generate $40,000,000 in quotes/yr | L62: - It is assumed that 1 estimating team member generate $40,000,000 in quotes/yr
D63: - It is determined that we are awarded about 3% of the work we quote | L63: - It is determined that we are awarded about 3% of the work we quote
D64: - The implied win rate is $1.2MM/year. To be conservative, we will assume $1MM/yr in gross sales per full time estimator | L64: - The implied win rate is $1.2MM/year. To be conservative, we will assume $1MM/yr in gross sales per full time estimator
D65: - Assumed estimator pay rate of $20,000 inc. incentives | L65: - Assumed estimator pay rate of $20,000 inc. incentives
C66: Metric | D66: Description | K66: Metric | L66: Description
C67: 20000 | D67: Salary applicable to project size | K67: 20000 | L67: Salary applicable to project size
C68: 1000000 | D68: Gross sales supported per HR team member | K68: 250000 | L68: Gross sales labor supported per HR team member
C69: =C67/C68 -> 0.02 | D69: Percentage of project related HR services | K69: =K67/K68 -> 0.08 | L69: Percentage of project related HR services
B71: Rent/Office Calculator | J71: Rent/Office Calculator
C72: Notes: | K72: Notes:
D73: - It is assumed that rent for the company supporting about $2,000,000 of business is $25,000/yr | L73: - It is assumed that rent for the company supporting about $2,000,000 of business is $25,000/yr
D74: - it is assumed that utilities is $2,700 for that facility | L74: - it is assumed that utilities is $2,700 for that facility
D75: - it is assumed that utilities is $7,500 in facility maintenance per year | L75: - it is assumed that utilities is $7,500 in facility maintenance per year
D76: - it is assumed that internet is $2,000 for that facility | L76: - it is assumed that internet is $2,000 for that facility
D77: - Total facility cost is: $37,200 | L77: - Total facility cost is: $37,200
C78: Metric | D78: Description | K78: Metric | L78: Description
C79: 37200 | D79: Salary applicable to project size | K79: 37200 | L79: Office space cost applicable to project size
C80: 2000000 | D80: Gross sales supported per office | K80: 500000 | L80: Gross sales labor supported per office
C81: =C79/C80 -> 0.0186 | D81: Percentage of project related HR services | K81: =K79/K80 -> 0.0744 | L81: Percentage of project related rent/office space
B83: Marketing & Subscription Services | J83: Marketing & Subscription Services
C84: Notes: | K84: Notes:
D85: - It is assumed that rent for the company supporting about $2,000,000/yr of business | L85: - It is assumed that rent for the company supporting about $2,000,000/yr of business
D86: - Project subcription/marketing services: $10,000 | L86: - Project subcription/marketing services: $10,000
D87: - Company insurance: Workmens comp & GL: $12,000 | L87: - Company insurance: Workmens comp & GL: $12,000
D88: - Software subscriptions: | L88: - Software subscriptions:
G89: 1) Quickbooks: $3,500/yr | O89: 1) Quickbooks: $3,500/yr
G90: 2) Tee sheets: $3,500/yr | O90: 2) Tee sheets: $3,500/yr
G91: 2) Misc: $1,000/yr | O91: 2) Misc: $1,000/yr
C92: Metric | D92: Description | K92: Metric | L92: Description
C93: =10000+12000+3500+3500+1000 -> 30000 | D93: Salary applicable to project size | K93: =10000+12000+3500+3500+1000 -> 30000 | L93: Salary applicable to project size
C94: 2000000 | D94: Gross sales supported related to services | K94: 500000 | L94: Gross sales labor supported related to services
C95: =C93/C94 -> 0.015 | D95: Percentage of project related HR services | K95: =K93/K94 -> 0.06 | L95: Percentage of project related maketing services

Sheet General
B1: =IF(Summary!$C$1="","",Summary!$C$1)
B2: General Items | G2: Defined Ranges (Don't erase)
B3: Item | C3: Materials Cost | D3: Labor Cost | E3: Notes | G3: Binary
B4: Permitting | C4: =C23 -> 192.5 | G4: Yes
B5: Field Logistics | D5: =D33 -> 0 | G5: No
B6: Crane Service | C6: =C48 -> 0
B7: Demolition | D7: =D68 -> 0
B8: Rentals | C8: =C82 -> 2400
B9: Air Balance | C9: =C94 -> 0
B10: Warranty | D10: =D104 -> 0
B11: Team Travel | C11: =C115 -> 0
B12: NA | C12: 0 | D12: 0
B13: NA | C13: 0 | D13: 0
B14: Totals | C14: =SUM(C4:C13) -> 2592.5 | D14: =SUM(D4:D13) -> 0
B16: Permitting
B17: Item | C17: Selection | E17: Description
B18: Required | C18: Yes | E18: Permit required aside from AC system changeouts or service
B19: Direct Job Cost | C19: =Summary!F18+Summary!F17+Summary!F15+Summary!F14+Summary!F13+Summary!F11+Summary!F12 -> 0 | E19: Total of direct field level labor and materials cost
B20: Base Cost ($) | C20: {=IF(C18="",_xludf.ISERROR,IF($C$18="yes",MAX(175,C19*0.005),0))} -> 175 | E20: Modeled as the maximum of 0.5% of project cost or $175
B21: Inc. Rate | C21: 0.1
B22: Inc ($) | C22: =C20*C21 -> 17.5
B23: Total Cost | C23: =C22+C20 -> 192.5
B25: Field Logistics | G25: Logisitics Calculator
B26: Item | D26: Selection | E26: Description | G26: Component | H26: Value
B27: Required | D27: Yes | E27: Required for all jobs currently | G27: Rate | H27: 45000 | I27: 70000
B28: Labor Total | D28: =Summary!$E$18+Summary!$E$17+Summary!$E$15+Summary!$E$14+Summary!$E$13+Summary!$E$11++Summary!$E$12 -> 0 | E28: Labor total from 'Summary' tab | G28: Job Gross | H28: 3000000 | I28: 2000000
B29: Field Logistics | D29: =H30 -> 0.06 | E29: Logistical rate for field support relative to direct labor. Assumed 5% in all cases | G29: Labor Est. | H29: =H28*0.25 -> 750000 | I29: =I28*0.25 -> 500000
B30: Base Cost ($) | D30: =IF(D27="Yes",D28*D29,0) -> 0 | E30: Modeled relative to field labor requirements | G30: Logistics Component | H30: =H27/H29 -> 0.06 | I30: =I27/I29 -> 0.14
B31: Inc. Rate | D31: 0 | E31: No incidental rate currently assumed
B32: Inc ($) | D32: =D30*D31 -> 0
B33: Total Cost | D33: =D32+D30 -> 0
B35: Crane Service (New Units) | G35: Crane Perameters (Don't erase)
B36: Item | C36: Selection | E36: Description | G36: Unit Category | H36: Desc | I36: Crane Size | J36: Price/Day
B37: Required | C37: No | E37: Required for all jobs currently | G37: Small | H37: <= 5 ton | I37: 19 | J37: 750
B38: Lifted Unit Count | C38: 5 | E38: Total number of units that will be lifted/unloaded by crane (1 for each new unit and 1 for each removed unit) | G38: Med | H38: <= 10 ton | I38: 40 | J38: 1500
B39: Extra Lift Days | C39: 0 | E39: Extra days required for logistics (1 for each additional day based on planned logistical schedule) | G39: Large | H39: <= 25 ton | I39: 80 | J39: 3500
B40: Largest Unit Category | C40: Max | G40: Max | H40: > 25 ton/chiller | I40: 120 | J40: 4500
B41: Largest Unit Desc | C41: =INDEX($H$37:$H$40,MATCH(C40,$G$37:$G$40,0),1) -> > 25 ton/chiller | E41: Unit size associated with "Largest Unit Category"
B42: Crane Size (tons) | C42: =INDEX($I$37:$I$40,MATCH(C40,$G$37:$G$40,0),1) -> 120 | E42: Crane size specified by "Largest Unit Category"
B43: Crane Cost/Day | C43: =INDEX($J$37:$J$40,MATCH(C40,$G$37:$G$40,0),1) -> 4500
B44: Days Required | C44: =ROUNDUP(C38/8,0)+C39 -> 1 | E44: Max of 8 units/day. Automatically populates based on unit count and extra days
B45: Base Cost ($) | C45: =IF($C$37="yes",C43*C44,0) -> 0 | E45: Modeled relative to field labor requirements
B46: Inc. Rate | C46: 0 | E46: No incidental rate currently assumed for logistics
B47: Inc ($) | C47: =C45*C46 -> 0
B48: Total Cost | C48: =C47+C45 -> 0
B50: Demolition (+ Crane Service for Demo of Old Units) | G50: Crane Perameters (Don't erase)
B51: Item | D51: Selection | E51: Description | G51: Unit Category | H51: Desc | I51: Price/Unit
B52: Required | D52: No | E52: Required for all jobs currently | G52: XL Duct | H52: > 25 ton | I52: 1200
B53: Split Systems to Demo | E53: Number of split systems to demo (doesn't include boilers, chillers, or towers) | G53: L Duct | H53: 10 -25 ton | I53: 800
B54: RTUs to Demo | E54: Number of package unitsto demo (doesn't include boilers, chillers, or towers) | G54: M Duct | H54: 5 - 10 ton | I54: 600
B55: VAV's to Demo | D55: not used yet | E55: Number of VAV units to demo (doesn't include boilers, chillers, or towers) | G55: S Duct | H55: < 5 ton | I55: 400
B56: Craned Unit Count | E56: Number of demoed units that require a crane
B57: XL Duct Runs to Demo | E57: Number of units of ducting requiring demo for equipment with cooling tonnage > 25 tons
B58: L Duct Runs to Demo | E58: Number of units of ducting requiring demo for equipment with cooling tonnage 10 to 25 tons | G58: Add VAV line
B59: M Duct Runs to Demo | E59: Number of units of ducting requiring demo for equipment with cooling tonnage 5 to 10 tons
B60: S Duct Runs to Demo | E60: Number of units of ducting requiring demo for equipment with cooling tonnage <=5 tons
B61: Unit Demo Cost | D61: =D54*400+D53*600+IF(D56=0,0,IF(D56>5,1500,800)) -> 0 | E61: Logistical rate for field support relative to direct labor. Assumed 5% in all cases. Includes crane service
B62: Duct Demo Cost | D62: =SUMPRODUCT($D$57:$D$60,$I$52:$I$55) -> 0 | E62: Logistical rate for field support relative to direct labor. Assumed 5% in all cases
B63: Partial Duct Discount | D63: 0 | E63: Discount the duct demo due to partial demo instead of complete removal of all ductwork (estimated)
B64: Duct Demo Net Disc | D64: =D62*(1-D63) -> 0 | E64: Final duct demo cost after discounting for only doing partial demo
B65: Base Cost ($) | D65: =IF(D52="No",0,D64+D61) -> 0 | E65: Modeled relative to field labor requirements
B66: Inc. Rate | D66: 0 | E66: No incidental rate currently assumed. Assume incidental cost for other miscellaneous items to demo and chillers and boilers
B67: Inc ($) | D67: =D65*D66 -> 0
B68: Total Cost | D68: =D67+D65 -> 0
B70: Rentals | G70: Rental Calculator (Don't erase)
B71: Item | C71: Selection | E71: Description | H71: Counts | K71: Cost
B72: Required | C72: Yes | E72: Required for all jobs unless no ductwork or units will be suspended or job is exceptionally small and doesn't appear to require one | G72: Labor | H72: Staff | I72: Scissor Lifts | J72: Mat. Lift | K72: Scissor Lifts | L72: Mat. Lift
B73: Labor Cost | C73: =Summary!E23 -> 0 | E73: Total labor cost for the job | G73: 0 | H73: 2 | I73: 1 | J73: 1 | K73: =2*500+500 -> 1500 | L73: =2*350+200 -> 900
B74: Estimated Staff | C74: =INDEX($H$73:$H$78,MATCH(C73,$G$73:$G$78,1),1) -> 2 | E74: Estimated team size for the project | G74: 18000 | H74: 3 | I74: 1 | J74: 1 | K74: =3*500+500 -> 2000 | L74: =3*350+200 -> 1250
B75: Scissor Lift Cnt | C75: =INDEX($I$73:$I$78,MATCH(C73,$G$73:$G$78,1),1) -> 1 | E75: Project scissor lift need | G75: =36000*2 -> 72000 | H75: 3 | I75: 1 | J75: 1 | K75: =6*500+500 -> 3500 | L75: =6*350+200 -> 2300
B76: Material Lift Cnt | C76: =INDEX($J$73:$J$78,MATCH(C73,$G$73:$G$78,1),1) -> 1 | E76: Logistical rate for field support relative to direct labor | G76: =36000*4 -> 144000 | H76: 6 | I76: 2 | J76: 2 | K76: =(6*500+500)*I76 -> 7000 | L76: =(6*350+200)*J76 -> 4600
B77: Scissor Lift ($) | C77: =INDEX($K$73:$K$78,MATCH(C73,$G$73:$G$78,1),1) -> 1500 | E77: Values pulled from table to the right | G77: =36000*8 -> 288000 | H77: 9 | I77: 3 | J77: 3 | K77: =(6*500+500)*I77 -> 10500 | L77: =(6*350+200)*J77 -> 6900
B78: Material Lift ($) | C78: =INDEX($L$73:$L$78,MATCH(C73,$G$73:$G$78,1),1) -> 900 | E78: Values pulled from table to the right | G78: =36000*12 -> 432000 | H78: 12 | I78: 4 | J78: 4 | K78: =(9*500+500)*I78 -> 20000 | L78: =(9*350+200)*J78 -> 13400
B79: Base Cost ($) | C79: =IF(C72="Yes",SUM(C77,C78),0) -> 2400 | E79: Total of scissor lift and material lift
B80: Inc. Rate | C80: 0 | E80: No incidental rate currently assumed rentals
B81: Inc ($) | C81: =C79*C80 -> 0 | E81: Incremental due to special consideration
B82: Total Cost | C82: =C81+C79 -> 2400
B84: Air Balancing
B85: Item | C85: Selection | E85: Description
B86: Required | C86: Yes | E86: Required for all jobs unless no ductwork is done or a small addition of a few small duct runs
B87: Mercury Provided | C87: Yes
B88: TP Certifiied | C88: {=IF(C87="Yes","No",IF(C87="No","Yes",_xludf.ISERROR))} -> No
B89: Systems to Balance | E89: Count the number of systems with ductwork that will require air balancing due to new unit, replacement, or the addition/modification of ductwork
B90: Grills | C90: ='Diffuser Schedule'!K24 -> 0 | E90: Logistical rate for field support relative to direct labor
B91: Base Cost ($) | C91: {=IF(C86="No",0,IF(C87="",_xludf.ISERROR,(C89*450+C90*45)/(IF(C87="Yes",3,1))))} -> 0 | E91: Cost calculated based on $450 per system plus $45 per grill for third part. Divide by 1/3r for Mercury air balance
B92: Inc. Rate | C92: 0 | E92: No incidental rate currently assumed for air balancing
B93: Inc ($) | C93: =C91*C92 -> 0
B94: Total Cost | C94: =C93+C91 -> 0
B96: Warranty
B97: Item | D97: Selection | E97: Description
B98: Required | D98: Yes | E98: Required for all jobs unless no ductwork is done or a small addition of a few small duct runs
B99: Installed Cooling Capacity | D99: =SUM('Unit Sched'!D5:D8) -> 0 | E99: Count the number of systems with ductwork that will require air balancing due to new unit, replacement, or the addition/modification of ductwork
B100: Installed Units | D100: ='Unit Sched'!D13 -> 0 | E100: Count the number of systems with ductwork that will require air balancing due to new unit, replacement, or the addition/modification of ductwork
B101: Base Cost ($) | D101: =D99*10+D100*50 -> 0 | E101: Estimated warranty cost of $10/ton+50/unit
B102: Inc. Rate | D102: 0 | E102: No incidental rate currently assumed for air balancing
B103: Inc ($) | D103: =D101*D102 -> 0
B104: Total Cost | D104: =D103+D101 -> 0
B106: Team Travel
B107: Item | C107: Selection | E107: Description
B108: Required | C108: No | E108: Required for all jobs beyond 30 min from Houston area suburbs
...

Sheet Unit Sched
B1: =IF(Summary!$C$1="","",Summary!$C$1)
B2: Unit Summary | J2: Near Unit Duct Summary (Do not include this on Duct schedule)
C3: Type | D3: Cooling (Tons) | E3: Equip + Accessories ($) | F3: Misc. ($) | G3: Total Materials ($) | H3: Labor ($) | I3: Materials + Labor | J3: Materials | K3: Labor | L3: Materials + Labor | N3: Note: Need to add a selection for knockdown units (requires dissasembly to get into the building)
B4: 1 | C4: Service of Existing | D4: =D43 -> 0 | E4: 0 | F4: =F43 -> 0 | G4: =E4+F4 -> 0 | H4: =G43 -> 0 | I4: =G4+H4 -> 0 | J4: 0 | K4: 0 | L4: =SUM(J4:K4) -> 0
B5: 2 | C5: Package | D5: =D82 -> 0 | E5: =AD82+AE82 -> 0 | F5: =AF82 -> 0 | G5: =E5+F5 -> 0 | H5: =AW82 -> 0 | I5: =G5+H5 -> 0 | J5: =AH82 -> 0 | K5: =AZ82 -> 0 | L5: =SUM(J5:K5) -> 0
B6: 3 | C6: Standard Split | D6: =D111 -> 0 | E6: =AL111+AM111 -> 0 | F6: =AN111 -> 0 | G6: =E6+F6 -> 0 | H6: =BD111 -> 0 | I6: =G6+H6 -> 0 | J6: =AP111 -> 0 | K6: =BE111 -> 0 | L6: =SUM(J6:K6) -> 0
B7: 4 | C7: Wall Mounted Split | D7: =D140 -> 0 | E7: =Y140+Z140 -> 0 | F7: =AA140 -> 0 | G7: =E7+F7 -> 0 | H7: =AL140 -> 0 | I7: =G7+H7 -> 0 | J7: 0 | K7: 0 | L7: 0
B8: 5 | C8: VRF | D8: =D169 -> 0 | E8: =AD169+AE169 -> 0 | F8: =AF169 -> 0 | G8: =E8+F8 -> 0 | H8: =AS169 -> 0 | I8: =G8+H8 -> 0 | J8: 0 | K8: 0 | L8: 0
B9: 6 | C9: [FPB/VAV] | G9: =E9+F9 -> 0 | I9: =G9+H9 -> 0
B10: 7 | C10: [Chiller] | G10: =E10+F10 -> 0 | I10: =G10+H10 -> 0
B11: 8 | C11: Boilers | G11: =E11+F11 -> 0 | I11: =G11+H11 -> 0
D12: =SUM(D4:D11) -> 0 | E12: =SUM(E4:E11) -> 0 | F12: =SUM(F4:F11) -> 0 | G12: =SUM(G4:G11) -> 0 | H12: =SUM(H4:H11) -> 0 | I12: =SUM(I4:I11) -> 0 | J12: =SUM(J4:J11) -> 0 | K12: =SUM(K4:K11) -> 0 | L12: =SUM(L4:L11) -> 0
C13: Unit Count (Warranty) | D13: =COUNT($D$57:$D$81)+COUNT($D$86:$D$110)+COUNT($D$115:$D$139)+COUNT($D$144:$D$168) -> 0
C14: Unit Count (Air Balance) | D14: =COUNT($D$57:$D$81)+COUNT($D$86:$D$110)+COUNT($D$115:$D$139)+COUNT($D$144:$D$168)+COUNT($D$18:$D$42) -> 0
B16: Servicing of Existing Units | I16: Materials Cost | Q16: Labor | Z16: Unit Type
B17: Unit | C17: Name | D17: Cool (Tons) | E17: System Type | F17: PM Materials | G17: PM Labor | I17: System Type | J17: Packaged Unit | K17: Standard Split | L17: Wall Mount Split | M17: VRF | N17: VAV/FBP | O17: Chiller | P17: Boiler | Q17: System Type | R17: Packaged Unit | S17: Standard Split | T17: Wall Mount Split | U17: VRF | V17: VAV/FBP | W17: Chiller | X17: Boiler | Z17: Packaged Unit
B18: 1 | F18: =IF($D18="",0,IF($E18="",0,INDEX($J$19:$P$24,MATCH($D18,$I$19:$I$24,1),MATCH($E18,$J$17:$P$17,0)))) -> 0 | G18: =IF($D18="",0,IF($E18="",0,INDEX($R$19:$X$24,MATCH($D18,$I$19:$I$24,1),MATCH($E18,$R$17:$X$17,0)))) -> 0 | I18: Size | J18: Cost | K18: Cost | L18: Cost | M18: Cost | N18: Cost | O18: Cost | P18: Cost | Q18: Size | R18: Cost | S18: Cost | T18: Cost | U18: Cost | V18: Cost | W18: Cost | X18: Cost | Z18: Standard Split
B19: =B18+1 -> 2 | F19: =IF($D19="",0,IF($E19="",0,INDEX($J$19:$P$24,MATCH($D19,$I$19:$I$24,1),MATCH($E19,$J$17:$P$17,0)))) -> 0 | G19: =IF($D19="",0,IF($E19="",0,INDEX($R$19:$X$24,MATCH($D19,$I$19:$I$24,1),MATCH($E19,$R$17:$X$17,0)))) -> 0 | I19: 0 | J19: 150 | K19: 150 | L19: =K19*0.65 -> 97.5 | M19: 300 | N19: =M19*0.65 -> 195 | O19: 650 | P19: 300 | Q19: 0 | R19: 100 | S19: 100 | T19: 75 | U19: 400 | V19: 50 | W19: =400 -> 400 | X19: 400 | Z19: Wall Mount Split
B20: =B19+1 -> 3 | F20: =IF($D20="",0,IF($E20="",0,INDEX($J$19:$P$24,MATCH($D20,$I$19:$I$24,1),MATCH($E20,$J$17:$P$17,0)))) -> 0 | G20: =IF($D20="",0,IF($E20="",0,INDEX($R$19:$X$24,MATCH($D20,$I$19:$I$24,1),MATCH($E20,$R$17:$X$17,0)))) -> 0 | I20: 5 | J20: 150 | K20: 150 | L20: =K20*0.65 -> 97.5 | M20: 300 | N20: =M20*0.65 -> 195 | O20: 650 | P20: 300 | Q20: 5 | R20: 100 | S20: 100 | T20: 75 | U20: 400 | V20: 50 | W20: 400 | X20: 400 | Z20: VRF
B21: =B20+1 -> 4 | F21: =IF($D21="",0,IF($E21="",0,INDEX($J$19:$P$24,MATCH($D21,$I$19:$I$24,1),MATCH($E21,$J$17:$P$17,0)))) -> 0 | G21: =IF($D21="",0,IF($E21="",0,INDEX($R$19:$X$24,MATCH($D21,$I$19:$I$24,1),MATCH($E21,$R$17:$X$17,0)))) -> 0 | I21: 10 | J21: 175 | K21: 175 | L21: =K21*0.65 -> 113.75 | M21: 350 | N21: =M21*0.65 -> 227.5 | O21: 750 | P21: 350 | Q21: 10 | R21: 125 | S21: 125 | T21: 100 | U21: 500 | V21: 75 | W21: 600 | X21: 450 | Z21: VAV/FBP
B22: =B21+1 -> 5 | F22: =IF($D22="",0,IF($E22="",0,INDEX($J$19:$P$24,MATCH($D22,$I$19:$I$24,1),MATCH($E22,$J$17:$P$17,0)))) -> 0 | G22: =IF($D22="",0,IF($E22="",0,INDEX($R$19:$X$24,MATCH($D22,$I$19:$I$24,1),MATCH($E22,$R$17:$X$17,0)))) -> 0 | I22: 20 | J22: 175 | K22: 175 | L22: =K22*0.65 -> 113.75 | M22: 400 | N22: =M22*0.65 -> 260 | O22: 1200 | P22: 400 | Q22: 20 | R22: 200 | S22: 200 | T22: 150 | U22: 800 | V22: 125 | W22: 800 | X22: 600 | Z22: Chiller
B23: =B22+1 -> 6 | F23: =IF($D23="",0,IF($E23="",0,INDEX($J$19:$P$24,MATCH($D23,$I$19:$I$24,1),MATCH($E23,$J$17:$P$17,0)))) -> 0 | G23: =IF($D23="",0,IF($E23="",0,INDEX($R$19:$X$24,MATCH($D23,$I$19:$I$24,1),MATCH($E23,$R$17:$X$17,0)))) -> 0 | I23: 50 | J23: 250 | K23: 250 | L23: =K23*0.65 -> 162.5 | M23: 800 | N23: =M23*0.65 -> 520 | O23: 1500 | P23: 600 | Q23: 50 | R23: 400 | S23: 400 | T23: 250 | U23: 1000 | V23: 200 | W23: 1200 | X23: 800 | Z23: Boiler
B24: =B23+1 -> 7 | F24: =IF($D24="",0,IF($E24="",0,INDEX($J$19:$P$24,MATCH($D24,$I$19:$I$24,1),MATCH($E24,$J$17:$P$17,0)))) -> 0 | G24: =IF($D24="",0,IF($E24="",0,INDEX($R$19:$X$24,MATCH($D24,$I$19:$I$24,1),MATCH($E24,$R$17:$X$17,0)))) -> 0 | I24: 75 | J24: 350 | K24: 350 | L24: =K24*0.65 -> 227.5 | M24: 1500 | N24: =M24*0.65 -> 975 | O24: 2000 | P24: 800 | Q24: 75 | R24: 800 | S24: 800 | T24: 300 | U24: 1500 | V24: 300 | W24: 1600 | X24: 1200
B25: =B24+1 -> 8 | F25: =IF($D25="",0,IF($E25="",0,INDEX($J$19:$P$24,MATCH($D25,$I$19:$I$24,1),MATCH($E25,$J$17:$P$17,0)))) -> 0 | G25: =IF($D25="",0,IF($E25="",0,INDEX($R$19:$X$24,MATCH($D25,$I$19:$I$24,1),MATCH($E25,$R$17:$X$17,0)))) -> 0
B26: =B25+1 -> 9 | F26: =IF($D26="",0,IF($E26="",0,INDEX($J$19:$P$24,MATCH($D26,$I$19:$I$24,1),MATCH($E26,$J$17:$P$17,0)))) -> 0 | G26: =IF($D26="",0,IF($E26="",0,INDEX($R$19:$X$24,MATCH($D26,$I$19:$I$24,1),MATCH($E26,$R$17:$X$17,0)))) -> 0
B27: =B26+1 -> 10 | F27: =IF($D27="",0,IF($E27="",0,INDEX($J$19:$P$24,MATCH($D27,$I$19:$I$24,1),MATCH($E27,$J$17:$P$17,0)))) -> 0 | G27: =IF($D27="",0,IF($E27="",0,INDEX($R$19:$X$24,MATCH($D27,$I$19:$I$24,1),MATCH($E27,$R$17:$X$17,0)))) -> 0
B28: =B27+1 -> 11 | F28: =IF($D28="",0,IF($E28="",0,INDEX($J$19:$P$24,MATCH($D28,$I$19:$I$24,1),MATCH($E28,$J$17:$P$17,0)))) -> 0 | G28: =IF($D28="",0,IF($E28="",0,INDEX($R$19:$X$24,MATCH($D28,$I$19:$I$24,1),MATCH($E28,$R$17:$X$17,0)))) -> 0
B29: =B28+1 -> 12 | F29: =IF($D29="",0,IF($E29="",0,INDEX($J$19:$P$24,MATCH($D29,$I$19:$I$24,1),MATCH($E29,$J$17:$P$17,0)))) -> 0 | G29: =IF($D29="",0,IF($E29="",0,INDEX($R$19:$X$24,MATCH($D29,$I$19:$I$24,1),MATCH($E29,$R$17:$X$17,0)))) -> 0
B30: =B29+1 -> 13 | F30: =IF($D30="",0,IF($E30="",0,INDEX($J$19:$P$24,MATCH($D30,$I$19:$I$24,1),MATCH($E30,$J$17:$P$17,0)))) -> 0 | G30: =IF($D30="",0,IF($E30="",0,INDEX($R$19:$X$24,MATCH($D30,$I$19:$I$24,1),MATCH($E30,$R$17:$X$17,0)))) -> 0
B31: =B30+1 -> 14 | F31: =IF($D31="",0,IF($E31="",0,INDEX($J$19:$P$24,MATCH($D31,$I$19:$I$24,1),MATCH($E31,$J$17:$P$17,0)))) -> 0 | G31: =IF($D31="",0,IF($E31="",0,INDEX($R$19:$X$24,MATCH($D31,$I$19:$I$24,1),MATCH($E31,$R$17:$X$17,0)))) -> 0
B32: =B31+1 -> 15 | F32: =IF($D32="",0,IF($E32="",0,INDEX($J$19:$P$24,MATCH($D32,$I$19:$I$24,1),MATCH($E32,$J$17:$P$17,0)))) -> 0 | G32: =IF($D32="",0,IF($E32="",0,INDEX($R$19:$X$24,MATCH($D32,$I$19:$I$24,1),MATCH($E32,$R$17:$X$17,0)))) -> 0
B33: =B32+1 -> 16 | F33: =IF($D33="",0,IF($E33="",0,INDEX($J$19:$P$24,MATCH($D33,$I$19:$I$24,1),MATCH($E33,$J$17:$P$17,0)))) -> 0 | G33: =IF($D33="",0,IF($E33="",0,INDEX($R$19:$X$24,MATCH($D33,$I$19:$I$24,1),MATCH($E33,$R$17:$X$17,0)))) -> 0
B34: =B33+1 -> 17 | F34: =IF($D34="",0,IF($E34="",0,INDEX($J$19:$P$24,MATCH($D34,$I$19:$I$24,1),MATCH($E34,$J$17:$P$17,0)))) -> 0 | G34: =IF($D34="",0,IF($E34="",0,INDEX($R$19:$X$24,MATCH($D34,$I$19:$I$24,1),MATCH($E34,$R$17:$X$17,0)))) -> 0
B35: =B34+1 -> 18 | F35: =IF($D35="",0,IF($E35="",0,INDEX($J$19:$P$24,MATCH($D35,$I$19:$I$24,1),MATCH($E35,$J$17:$P$17,0)))) -> 0 | G35: =IF($D35="",0,IF($E35="",0,INDEX($R$19:$X$24,MATCH($D35,$I$19:$I$24,1),MATCH($E35,$R$17:$X$17,0)))) -> 0
B36: =B35+1 -> 19 | F36: =IF($D36="",0,IF($E36="",0,INDEX($J$19:$P$24,MATCH($D36,$I$19:$I$24,1),MATCH($E36,$J$17:$P$17,0)))) -> 0 | G36: =IF($D36="",0,IF($E36="",0,INDEX($R$19:$X$24,MATCH($D36,$I$19:$I$24,1),MATCH($E36,$R$17:$X$17,0)))) -> 0
... B42: =B41+1 -> 25 | F42: =IF($D42="",0,IF($E42="",0,INDEX($J$19:$P$24,MATCH($D42,$I$19:$I$24,1),MATCH($E42,$J$17:$P$17,0)))) -> 0 | G42: =IF($D42="",0,IF($E42="",0,INDEX($R$19:$X$24,MATCH($D42,$I$19:$I$24,1),MATCH($E42,$R$17:$X$17,0)))) -> 0
B43: Totals | D43: =SUM(D18:D42) -> 0 | F43: =SUM(F18:F42) -> 0 | G43: =SUM(G18:G42) -> 0
E54: vvvvvvvvvv Notes: Selecting "xx" means the owner is providing the equipment | I54: Notes: "x" implies that we need to include an estimate for this item. If the equipment provider has included the item in their package proporsal select "xx". Also use "xx" if the owner is providing but we have to install
B55: New Packaged Units | F55: Cost Calculator (Option) | H55: Supplier Quote (Option) | R55: DUCT | S55: DUCT | T55: Equipment Materials ------------------------------------------------------------------------------------------------------------------------------------------------------------------------------------------------------------------------------------------------------------------------------------------------------------------------------------------------------------------------------------------------------------------ | AE55: Misc: | AF55: 0.025 | AH55: Duct Materials-------------------------------------------- | AK55: Equipment Labor-------------------------------------------------------------------------------------------------------------------------------------------------------------------------------------------------------------------------------------------------------------------------------------------------------------------------------------------------------------------------------------------------------------------- | AX55: Duct Labor----------------------------------------------------------------------------- | BC55: Materials Cost | BR55: Equipment Labor Cost | CQ55: Duct Labor
B56: Unit | C56: Name | D56: Cool (Tons) | E56: Owner Provided ("xx") | F56: Base Cost ($/ton) | G56: Est. Equipment Cost ($) | H56: Equipment Cost ($) | I56: Standard Curb ("x/xx") | J56: Metal Roof Curb ("x/xx") | K56: Curb Adapter ("x/xx") | L56: Economizer ("x/xx") | M56: PVC Condensate ("x/xx") | N56: CU Condensate ("x/xx") | O56: Thermostat ("x/xx") | P56: Smoke Detectors ("x/xx") | Q56: Sensors (CO/Temp) (Qty) | R56: New Drops ("x/xx") | S56: Drum Louvers ("x/xx") | T56: Economizer ($) | U56: Standard Curb ($) | V56: Metal Roof Curb ($) | W56: Curb Adapter ($) | X56: PVC Cond. ($) | Y56: CU Cond. ($) | Z56: Thermostat ($) | AA56: Smoke Detectors ($) | AB56: Sensors (CO/Temp) ($) | AC56: Stat Wire (CO/Temp) ($) | AD56: Base + Quoted Price ($) | AE56: Accessories ($) | AF56: Misc/Consumables | AG56: Total Materials | AH56: New Drops ($) | AI56: Drum Louvers ($) | AJ56: Total Materials ($) | AK56: Base Equipment ($) | AL56: Standard Curb ($) | AM56: Metal Roof Curb ($) | AN56: Curb Adapter ($) | AO56: Economizer ($) | AP56: PVC Cond. ($) | AQ56: CU Cond. ($) | AR56: Thermostat ($) | AS56: Smoke Detectors ($) | AT56: Sensors (CO/Temp) ($) | AU56: Stat Wire (CO/Temp) ($) | AV56: Startup & Testing | AW56: Labor Total ($) | AX56: New Drops ($) | AY56: Drum Louvers ($) | AZ56: Labor Total ($) | BA56: Notes | BD56: Economizer | BF56: Standard Curb | BH56: Metal Roof Curb | BJ56: Curb Adapter | BN56: New Drops | BP56: Drum Louvers (Supply + Return) | BS56: Base Unit | BU56: Standard Curb | BW56: Metal Curb | BY56: Curb Adapter | CA56: Economizer | CC56: PVC Cond | CE56: CU Cond | CG56: Thermostat | CI56: Smoke Detectors | CK56: Sensors | CM56: Stat Wire | CO56: Start Up | CQ56: New Drops | CS56: Drum Louvers (+ Returns)
B57: 1 | G57: =F57*D57 -> 0 | T57: =IF($L57="x",IF($D57="",0,INDEX($BE$58:$BE$63,MATCH($D57,$BD$58:$BD$63,1))),0) -> 0 | U57: =IF($I57="x",IF($D57="",0,INDEX($BG$58:$BG$63,MATCH($D57,$BF$58:$BF$63,1))),0) -> 0 | V57: =IF($J57="x",IF($D57="",0,INDEX($BI$58:$BI$63,MATCH($D57,$BH$58:$BH$63,1))),0) -> 0 | W57: =IF($K57="x",IF($D57="",0,INDEX($BK$58:$BK$63,MATCH($D57,$BJ$58:$BJ$63,1))),0) -> 0 | X57: =IF($D57="",0,IF(M57="x",$BM$60,0)) -> 0 | Y57: =IF($D57="",0,IF(N57="x",$BM$62,0)) -> 0 | Z57: =IF($O57="x",IF($D57="",0,$BL$58),0) -> 0 | AA57: =IF($P57="x",IF($D57="",0,IF($D57>4,$BL$60,0)),0) -> 0 | AB57: =IF($D57="",0,$Q57*$BL$62) -> 0 | AC57: =IF($D57="",0,(Q57+IF(OR(O57="x",44="xx"),1,0))*$BM$58) -> 0 | AD57: =G57+H57 -> 0 | AE57: =SUM(T57:AC57) -> 0 | AF57: =IF($E57="xx",(1600*$D57+$AE57),SUM(AD57:AE57))*$AF$55 -> 0 | AG57: =SUM(AD57:AF57) -> 0 | AH57: =IF($R57="x",IF($D57="",0,INDEX($BO$58:$BO$63,MATCH($D57,$BN$58:$BN$63,1))),0) -> 0 | AI57: =IF($S57="x",IF($D57="",0,INDEX($BQ$58:$BQ$63,MATCH($D57,$BP$58:$BP$63,1))),0) -> 0 | AJ57: =SUM(AH57:AI57) -> 0 | AK57: =IF($D57="",0,INDEX($BT$58:$BT$63,MATCH($D57,$BS$58:$BS$63))*$BR$58) -> 0 | AL57: =IF($D57="",0,IF(OR($I57="x",$I57="xx"),INDEX($BV$58:$BV$63,MATCH($D57,$BU$58:$BU$63))*$BR$58,0)) -> 0 | AM57: =IF($D57="",0,IF(OR($J57="x",$J57="xx"),INDEX($BX$58:$BX$63,MATCH($D57,$BW$58:$BW$63))*$BR$58,0)) -> 0 | AN57: =IF($D57="",0,IF(OR($K57="x",$K57="xx"),INDEX($BZ$58:$BZ$63,MATCH($D57,$BY$58:$BY$63))*$BR$58,0)) -> 0 | AO57: =IF($D57="",0,IF(OR($L57="x",$L57="xx"),INDEX($CB$58:$CB$63,MATCH($D57,$CA$58:$CA$63))*$BR$58,0)) -> 0 | AP57: =IF($D57="",0,IF(OR($M57="x",$M57="xx"),INDEX($CD$58:$CD$63,MATCH($D57,$CC$58:$CC$63))*$BR$58,0)) -> 0 | AQ57: =IF($D57="",0,IF(OR($N57="x",$N57="xx"),INDEX($CF$58:$CF$63,MATCH($D57,$CE$58:$CE$63))*$BR$58,0)) -> 0 | AR57: =IF($D57="",0,IF(OR($O57="x",$O57="xx"),INDEX($CH$58:$CH$63,MATCH($D57,$CG$58:$CG$63))*$BR$58,0)) -> 0 | AS57: =IF($D57="",0,IF(OR($P57="x",$P57="xx"),IF($D57>4,INDEX($CJ$58:$CJ$63,MATCH($D57,$CI$58:$CI$63))*$BR$58,0),0)) -> 0 | AT57: =IF($D57="",0,($Q57*INDEX($CL$58:$CL$63,MATCH($D57,$CK$58:$CK$63))*$BR$58)) -> 0 | AU57: =IF($D57="",0,(($Q57+IF(OR($O57="x",$O57="xx"),1,0))*INDEX($CN$58:$CN$63,MATCH($D57,$CM$58:$CM$63))*$BR$58)) -> 0 | AV57: =IF($D57="",0,INDEX($CP$58:$CP$63,MATCH($D57,$CO$58:$CO$63))*$BR$58) -> 0 | AW57: =SUM(AK57:AV57) -> 0 | AX57: =IF($D57="",0,((IF(OR($R57="x",$R57="xx"),1,0))*INDEX($CR$58:$CR$63,MATCH($D57,$CQ$58:$CQ$63))*$BR$58)) -> 0 | AY57: =IF($D57="",0,((IF(OR($S57="x",$S57="xx"),1,0))*INDEX($CT$58:$CT$63,MATCH($D57,$CS$58:$CS$63))*$BR$58)) -> 0 | AZ57: =SUM(AX57:AY57) -> 0 | BC57: Selection Options | BD57: Size | BE57: Cost | BF57: Size | BG57: Cost | BH57: Size | BI57: Cost | BJ57: Size | BK57: Cost | BL57: Thermostat | BM57: Stat Wire/Unit | BN57: Size | BO57: Cost | BP57: Size | BQ57: Cost | BR57: Tech Rate ($/hr) | BS57: Size | BT57: Hours | BU57: Size | BV57: Hours | BW57: Size | BX57: Hours | BY57: Size | BZ57: Hours | CA57: Size | CB57: Hours | CC57: Size | CD57: Hours | CE57: Size | CF57: Hours | CG57: Size | CH57: Hours | CI57: Size | CJ57: Hours | CK57: Size | CL57: Hours | CM57: Size | CN57: Hours | CO57: Size | CP57: Hours | CQ57: Size | CR57: Hours | CS57: Size | CT57: Cost
B58: =B57+1 -> 2 | G58: =F58*D58 -> 0 | T58: =IF($L58="x",IF($D58="",0,INDEX($BE$58:$BE$63,MATCH($D58,$BD$58:$BD$63,1))),0) -> 0 | U58: =IF($I58="x",IF($D58="",0,INDEX($BG$58:$BG$63,MATCH($D58,$BF$58:$BF$63,1))),0) -> 0 | V58: =IF($J58="x",IF($D58="",0,INDEX($BI$58:$BI$63,MATCH($D58,$BH$58:$BH$63,1))),0) -> 0 | W58: =IF($K58="x",IF($D58="",0,INDEX($BK$58:$BK$63,MATCH($D58,$BJ$58:$BJ$63,1))),0) -> 0 | X58: =IF($D58="",0,IF(M58="x",$BM$60,0)) -> 0 | Y58: =IF($D58="",0,IF(N58="x",$BM$62,0)) -> 0 | Z58: =IF($O58="x",IF($D58="",0,$BL$58),0) -> 0 | AA58: =IF($P58="x",IF($D58="",0,IF($D58>4,$BL$60,0)),0) -> 0 | AB58: =IF($D58="",0,$Q58*$BL$62) -> 0 | AC58: =IF($D58="",0,(Q58+IF(OR(O58="x",44="xx"),1,0))*$BM$58) -> 0 | AD58: =G58+H58 -> 0 | AE58: =SUM(T58:AC58) -> 0 | AF58: =IF($E58="xx",(1600*$D58+$AE58),SUM(AD58:AE58))*$AF$55 -> 0 | AG58: =SUM(AD58:AF58) -> 0 | AH58: =IF($R58="x",IF($D58="",0,INDEX($BO$58:$BO$63,MATCH($D58,$BN$58:$BN$63,1))),0) -> 0 | AI58: =IF($S58="x",IF($D58="",0,INDEX($BQ$58:$BQ$63,MATCH($D58,$BP$58:$BP$63,1))),0) -> 0 | AJ58: =SUM(AH58:AI58) -> 0 | AK58: =IF($D58="",0,INDEX($BT$58:$BT$63,MATCH($D58,$BS$58:$BS$63))*$BR$58) -> 0 | AL58: =IF($D58="",0,IF(OR($I58="x",$I58="xx"),INDEX($BV$58:$BV$63,MATCH($D58,$BU$58:$BU$63))*$BR$58,0)) -> 0 | AM58: =IF($D58="",0,IF(OR($J58="x",$J58="xx"),INDEX($BX$58:$BX$63,MATCH($D58,$BW$58:$BW$63))*$BR$58,0)) -> 0 | AN58: =IF($D58="",0,IF(OR($K58="x",$K58="xx"),INDEX($BZ$58:$BZ$63,MATCH($D58,$BY$58:$BY$63))*$BR$58,0)) -> 0 | AO58: =IF($D58="",0,IF(OR($L58="x",$L58="xx"),INDEX($CB$58:$CB$63,MATCH($D58,$CA$58:$CA$63))*$BR$58,0)) -> 0 | AP58: =IF($D58="",0,IF(OR($M58="x",$M58="xx"),INDEX($CD$58:$CD$63,MATCH($D58,$CC$58:$CC$63))*$BR$58,0)) -> 0 | AQ58: =IF($D58="",0,IF(OR($N58="x",$N58="xx"),INDEX($CF$58:$CF$63,MATCH($D58,$CE$58:$CE$63))*$BR$58,0)) -> 0 | AR58: =IF($D58="",0,IF(OR($O58="x",$O58="xx"),INDEX($CH$58:$CH$63,MATCH($D58,$CG$58:$CG$63))*$BR$58,0)) -> 0 | AS58: =IF($D58="",0,IF(OR($P58="x",$P58="xx"),IF($D58>4,INDEX($CJ$58:$CJ$63,MATCH($D58,$CI$58:$CI$63))*$BR$58,0),0)) -> 0 | AT58: =IF($D58="",0,($Q58*INDEX($CL$58:$CL$63,MATCH($D58,$CK$58:$CK$63))*$BR$58)) -> 0 | AU58: =IF($D58="",0,(($Q58+IF(OR($O58="x",$O58="xx"),1,0))*INDEX($CN$58:$CN$63,MATCH($D58,$CM$58:$CM$63))*$BR$58)) -> 0 | AV58: =IF($D58="",0,INDEX($CP$58:$CP$63,MATCH($D58,$CO$58:$CO$63))*$BR$58) -> 0 | AW58: =SUM(AK58:AV58) -> 0 | AX58: =IF($D58="",0,((IF(OR($R58="x",$R58="xx"),1,0))*INDEX($CR$58:$CR$63,MATCH($D58,$CQ$58:$CQ$63))*$BR$58)) -> 0 | AY58: =IF($D58="",0,((IF(OR($S58="x",$S58="xx"),1,0))*INDEX($CT$58:$CT$63,MATCH($D58,$CS$58:$CS$63))*$BR$58)) -> 0 | AZ58: =SUM(AX58:AY58) -> 0 | BC58: x | BD58: 0 | BE58: 1200 | BF58: 0 | BG58: 450 | BH58: 0 | BI58: 3500 | BJ58: 0 | BK58: 1300 | BL58: 160 | BM58: =90/2 -> 45 | BN58: 0 | BO58: 400 | BP58: 0 | BQ58: 2400 | BR58: 25 | BS58: 0 | BT58: 4 | BU58: 0 | BV58: 8 | BW58: 0 | BX58: 11 | BY58: 0 | BZ58: 3 | CA58: 0 | CB58: 5 | CC58: 0 | CD58: 4 | CE58: 0 | CF58: 12 | CG58: 0 | CH58: 1 | CI58: 0 | CJ58: 2 | CK58: 0 | CL58: 2 | CM58: 0 | CN58: 3 | CO58: 0 | CP58: 4 | CQ58: 0 | CR58: 16 | CS58: 0 | CT58: 16
B59: =B58+1 -> 3 | G59: =F59*D59 -> 0 | T59: =IF($L59="x",IF($D59="",0,INDEX($BE$58:$BE$63,MATCH($D59,$BD$58:$BD$63,1))),0) -> 0 | U59: =IF($I59="x",IF($D59="",0,INDEX($BG$58:$BG$63,MATCH($D59,$BF$58:$BF$63,1))),0) -> 0 | V59: =IF($J59="x",IF($D59="",0,INDEX($BI$58:$BI$63,MATCH($D59,$BH$58:$BH$63,1))),0) -> 0 | W59: =IF($K59="x",IF($D59="",0,INDEX($BK$58:$BK$63,MATCH($D59,$BJ$58:$BJ$63,1))),0) -> 0 | X59: =IF($D59="",0,IF(M59="x",$BM$60,0)) -> 0 | Y59: =IF($D59="",0,IF(N59="x",$BM$62,0)) -> 0 | Z59: =IF($O59="x",IF($D59="",0,$BL$58),0) -> 0 | AA59: =IF($P59="x",IF($D59="",0,IF($D59>4,$BL$60,0)),0) -> 0 | AB59: =IF($D59="",0,$Q59*$BL$62) -> 0 | AC59: =IF($D59="",0,(Q59+IF(OR(O59="x",44="xx"),1,0))*$BM$58) -> 0 | AD59: =G59+H59 -> 0 | AE59: =SUM(T59:AC59) -> 0 | AF59: =IF($E59="xx",(1600*$D59+$AE59),SUM(AD59:AE59))*$AF$55 -> 0 | AG59: =SUM(AD59:AF59) -> 0 | AH59: =IF($R59="x",IF($D59="",0,INDEX($BO$58:$BO$63,MATCH($D59,$BN$58:$BN$63,1))),0) -> 0 | AI59: =IF($S59="x",IF($D59="",0,INDEX($BQ$58:$BQ$63,MATCH($D59,$BP$58:$BP$63,1))),0) -> 0 | AJ59: =SUM(AH59:AI59) -> 0 | AK59: =IF($D59="",0,INDEX($BT$58:$BT$63,MATCH($D59,$BS$58:$BS$63))*$BR$58) -> 0 | AL59: =IF($D59="",0,IF(OR($I59="x",$I59="xx"),INDEX($BV$58:$BV$63,MATCH($D59,$BU$58:$BU$63))*$BR$58,0)) -> 0 | AM59: =IF($D59="",0,IF(OR($J59="x",$J59="xx"),INDEX($BX$58:$BX$63,MATCH($D59,$BW$58:$BW$63))*$BR$58,0)) -> 0 | AN59: =IF($D59="",0,IF(OR($K59="x",$K59="xx"),INDEX($BZ$58:$BZ$63,MATCH($D59,$BY$58:$BY$63))*$BR$58,0)) -> 0 | AO59: =IF($D59="",0,IF(OR($L59="x",$L59="xx"),INDEX($CB$58:$CB$63,MATCH($D59,$CA$58:$CA$63))*$BR$58,0)) -> 0 | AP59: =IF($D59="",0,IF(OR($M59="x",$M59="xx"),INDEX($CD$58:$CD$63,MATCH($D59,$CC$58:$CC$63))*$BR$58,0)) -> 0 | AQ59: =IF($D59="",0,IF(OR($N59="x",$N59="xx"),INDEX($CF$58:$CF$63,MATCH($D59,$CE$58:$CE$63))*$BR$58,0)) -> 0 | AR59: =IF($D59="",0,IF(OR($O59="x",$O59="xx"),INDEX($CH$58:$CH$63,MATCH($D59,$CG$58:$CG$63))*$BR$58,0)) -> 0 | AS59: =IF($D59="",0,IF(OR($P59="x",$P59="xx"),IF($D59>4,INDEX($CJ$58:$CJ$63,MATCH($D59,$CI$58:$CI$63))*$BR$58,0),0)) -> 0 | AT59: =IF($D59="",0,($Q59*INDEX($CL$58:$CL$63,MATCH($D59,$CK$58:$CK$63))*$BR$58)) -> 0 | AU59: =IF($D59="",0,(($Q59+IF(OR($O59="x",$O59="xx"),1,0))*INDEX($CN$58:$CN$63,MATCH($D59,$CM$58:$CM$63))*$BR$58)) -> 0 | AV59: =IF($D59="",0,INDEX($CP$58:$CP$63,MATCH($D59,$CO$58:$CO$63))*$BR$58) -> 0 | AW59: =SUM(AK59:AV59) -> 0 | AX59: =IF($D59="",0,((IF(OR($R59="x",$R59="xx"),1,0))*INDEX($CR$58:$CR$63,MATCH($D59,$CQ$58:$CQ$63))*$BR$58)) -> 0 | AY59: =IF($D59="",0,((IF(OR($S59="x",$S59="xx"),1,0))*INDEX($CT$58:$CT$63,MATCH($D59,$CS$58:$CS$63))*$BR$58)) -> 0 | AZ59: =SUM(AX59:AY59) -> 0 | BC59: xx | BD59: 5 | BE59: 1300 | BF59: 5 | BG59: 500 | BH59: 5 | BI59: 4000 | BJ59: 5 | BK59: 1600 | BL59: Smoke Detector | BM59: PVC Cond | BN59: 5 | BO59: 450 | BP59: 5 | BQ59: 2400 | BS59: 5 | BT59: 5 | BU59: 5 | BV59: 8 | BW59: 5 | BX59: 11 | BY59: 5 | BZ59: 3 | CA59: 5 | CB59: 5 | CC59: 5 | CD59: 4 | CE59: 5 | CF59: 12 | CG59: 5 | CH59: 1 | CI59: 5 | CJ59: 2 | CK59: 5 | CL59: 2 | CM59: 5 | CN59: 3 | CO59: 5 | CP59: 4 | CQ59: 5 | CR59: 16 | CS59: 5 | CT59: 16
B60: =B59+1 -> 4 | G60: =F60*D60 -> 0 | T60: =IF($L60="x",IF($D60="",0,INDEX($BE$58:$BE$63,MATCH($D60,$BD$58:$BD$63,1))),0) -> 0 | U60: =IF($I60="x",IF($D60="",0,INDEX($BG$58:$BG$63,MATCH($D60,$BF$58:$BF$63,1))),0) -> 0 | V60: =IF($J60="x",IF($D60="",0,INDEX($BI$58:$BI$63,MATCH($D60,$BH$58:$BH$63,1))),0) -> 0 | W60: =IF($K60="x",IF($D60="",0,INDEX($BK$58:$BK$63,MATCH($D60,$BJ$58:$BJ$63,1))),0) -> 0 | X60: =IF($D60="",0,IF(M60="x",$BM$60,0)) -> 0 | Y60: =IF($D60="",0,IF(N60="x",$BM$62,0)) -> 0 | Z60: =IF($O60="x",IF($D60="",0,$BL$58),0) -> 0 | AA60: =IF($P60="x",IF($D60="",0,IF($D60>4,$BL$60,0)),0) -> 0 | AB60: =IF($D60="",0,$Q60*$BL$62) -> 0 | AC60: =IF($D60="",0,(Q60+IF(OR(O60="x",44="xx"),1,0))*$BM$58) -> 0 | AD60: =G60+H60 -> 0 | AE60: =SUM(T60:AC60) -> 0 | AF60: =IF($E60="xx",(1600*$D60+$AE60),SUM(AD60:AE60))*$AF$55 -> 0 | AG60: =SUM(AD60:AF60) -> 0 | AH60: =IF($R60="x",IF($D60="",0,INDEX($BO$58:$BO$63,MATCH($D60,$BN$58:$BN$63,1))),0) -> 0 | AI60: =IF($S60="x",IF($D60="",0,INDEX($BQ$58:$BQ$63,MATCH($D60,$BP$58:$BP$63,1))),0) -> 0 | AJ60: =SUM(AH60:AI60) -> 0 | AK60: =IF($D60="",0,INDEX($BT$58:$BT$63,MATCH($D60,$BS$58:$BS$63))*$BR$58) -> 0 | AL60: =IF($D60="",0,IF(OR($I60="x",$I60="xx"),INDEX($BV$58:$BV$63,MATCH($D60,$BU$58:$BU$63))*$BR$58,0)) -> 0 | AM60: =IF($D60="",0,IF(OR($J60="x",$J60="xx"),INDEX($BX$58:$BX$63,MATCH($D60,$BW$58:$BW$63))*$BR$58,0)) -> 0 | AN60: =IF($D60="",0,IF(OR($K60="x",$K60="xx"),INDEX($BZ$58:$BZ$63,MATCH($D60,$BY$58:$BY$63))*$BR$58,0)) -> 0 | AO60: =IF($D60="",0,IF(OR($L60="x",$L60="xx"),INDEX($CB$58:$CB$63,MATCH($D60,$CA$58:$CA$63))*$BR$58,0)) -> 0 | AP60: =IF($D60="",0,IF(OR($M60="x",$M60="xx"),INDEX($CD$58:$CD$63,MATCH($D60,$CC$58:$CC$63))*$BR$58,0)) -> 0 | AQ60: =IF($D60="",0,IF(OR($N60="x",$N60="xx"),INDEX($CF$58:$CF$63,MATCH($D60,$CE$58:$CE$63))*$BR$58,0)) -> 0 | AR60: =IF($D60="",0,IF(OR($O60="x",$O60="xx"),INDEX($CH$58:$CH$63,MATCH($D60,$CG$58:$CG$63))*$BR$58,0)) -> 0 | AS60: =IF($D60="",0,IF(OR($P60="x",$P60="xx"),IF($D60>4,INDEX($CJ$58:$CJ$63,MATCH($D60,$CI$58:$CI$63))*$BR$58,0),0)) -> 0 | AT60: =IF($D60="",0,($Q60*INDEX($CL$58:$CL$63,MATCH($D60,$CK$58:$CK$63))*$BR$58)) -> 0 | AU60: =IF($D60="",0,(($Q60+IF(OR($O60="x",$O60="xx"),1,0))*INDEX($CN$58:$CN$63,MATCH($D60,$CM$58:$CM$63))*$BR$58)) -> 0 | AV60: =IF($D60="",0,INDEX($CP$58:$CP$63,MATCH($D60,$CO$58:$CO$63))*$BR$58) -> 0 | AW60: =SUM(AK60:AV60) -> 0 | AX60: =IF($D60="",0,((IF(OR($R60="x",$R60="xx"),1,0))*INDEX($CR$58:$CR$63,MATCH($D60,$CQ$58:$CQ$63))*$BR$58)) -> 0 | AY60: =IF($D60="",0,((IF(OR($S60="x",$S60="xx"),1,0))*INDEX($CT$58:$CT$63,MATCH($D60,$CS$58:$CS$63))*$BR$58)) -> 0 | AZ60: =SUM(AX60:AY60) -> 0 | BD60: 10 | BE60: 1800 | BF60: 10 | BG60: 600 | BH60: 10 | BI60: 4800 | BJ60: 10 | BK60: 1900 | BL60: 170 | BM60: =30+6+50 -> 86 | BN60: 10 | BO60: 500 | BP60: 10 | BQ60: 2600 | BS60: 10 | BT60: 6 | BU60: 10 | BV60: 9 | BW60: 10 | BX60: 12 | BY60: 10 | BZ60: 3 | CA60: 10 | CB60: 5 | CC60: 10 | CD60: 4 | CE60: 10 | CF60: 12 | CG60: 10 | CH60: 1 | CI60: 10 | CJ60: 2 | CK60: 10 | CL60: 2 | CM60: 10 | CN60: 3 | CO60: 10 | CP60: 4 | CQ60: 10 | CR60: 24 | CS60: 10 | CT60: 20
B61: =B60+1 -> 5 | G61: =F61*D61 -> 0 | T61: =IF($L61="x",IF($D61="",0,INDEX($BE$58:$BE$63,MATCH($D61,$BD$58:$BD$63,1))),0) -> 0 | U61: =IF($I61="x",IF($D61="",0,INDEX($BG$58:$BG$63,MATCH($D61,$BF$58:$BF$63,1))),0) -> 0 | V61: =IF($J61="x",IF($D61="",0,INDEX($BI$58:$BI$63,MATCH($D61,$BH$58:$BH$63,1))),0) -> 0 | W61: =IF($K61="x",IF($D61="",0,INDEX($BK$58:$BK$63,MATCH($D61,$BJ$58:$BJ$63,1))),0) -> 0 | X61: =IF($D61="",0,IF(M61="x",$BM$60,0)) -> 0 | Y61: =IF($D61="",0,IF(N61="x",$BM$62,0)) -> 0 | Z61: =IF($O61="x",IF($D61="",0,$BL$58),0) -> 0 | AA61: =IF($P61="x",IF($D61="",0,IF($D61>4,$BL$60,0)),0) -> 0 | AB61: =IF($D61="",0,$Q61*$BL$62) -> 0 | AC61: =IF($D61="",0,(Q61+IF(OR(O61="x",44="xx"),1,0))*$BM$58) -> 0 | AD61: =G61+H61 -> 0 | AE61: =SUM(T61:AC61) -> 0 | AF61: =IF($E61="xx",(1600*$D61+$AE61),SUM(AD61:AE61))*$AF$55 -> 0 | AG61: =SUM(AD61:AF61) -> 0 | AH61: =IF($R61="x",IF($D61="",0,INDEX($BO$58:$BO$63,MATCH($D61,$BN$58:$BN$63,1))),0) -> 0 | AI61: =IF($S61="x",IF($D61="",0,INDEX($BQ$58:$BQ$63,MATCH($D61,$BP$58:$BP$63,1))),0) -> 0 | AJ61: =SUM(AH61:AI61) -> 0 | AK61: =IF($D61="",0,INDEX($BT$58:$BT$63,MATCH($D61,$BS$58:$BS$63))*$BR$58) -> 0 | AL61: =IF($D61="",0,IF(OR($I61="x",$I61="xx"),INDEX($BV$58:$BV$63,MATCH($D61,$BU$58:$BU$63))*$BR$58,0)) -> 0 | AM61: =IF($D61="",0,IF(OR($J61="x",$J61="xx"),INDEX($BX$58:$BX$63,MATCH($D61,$BW$58:$BW$63))*$BR$58,0)) -> 0 | AN61: =IF($D61="",0,IF(OR($K61="x",$K61="xx"),INDEX($BZ$58:$BZ$63,MATCH($D61,$BY$58:$BY$63))*$BR$58,0)) -> 0 | AO61: =IF($D61="",0,IF(OR($L61="x",$L61="xx"),INDEX($CB$58:$CB$63,MATCH($D61,$CA$58:$CA$63))*$BR$58,0)) -> 0 | AP61: =IF($D61="",0,IF(OR($M61="x",$M61="xx"),INDEX($CD$58:$CD$63,MATCH($D61,$CC$58:$CC$63))*$BR$58,0)) -> 0 | AQ61: =IF($D61="",0,IF(OR($N61="x",$N61="xx"),INDEX($CF$58:$CF$63,MATCH($D61,$CE$58:$CE$63))*$BR$58,0)) -> 0 | AR61: =IF($D61="",0,IF(OR($O61="x",$O61="xx"),INDEX($CH$58:$CH$63,MATCH($D61,$CG$58:$CG$63))*$BR$58,0)) -> 0 | AS61: =IF($D61="",0,IF(OR($P61="x",$P61="xx"),IF($D61>4,INDEX($CJ$58:$CJ$63,MATCH($D61,$CI$58:$CI$63))*$BR$58,0),0)) -> 0 | AT61: =IF($D61="",0,($Q61*INDEX($CL$58:$CL$63,MATCH($D61,$CK$58:$CK$63))*$BR$58)) -> 0 | AU61: =IF($D61="",0,(($Q61+IF(OR($O61="x",$O61="xx"),1,0))*INDEX($CN$58:$CN$63,MATCH($D61,$CM$58:$CM$63))*$BR$58)) -> 0 | AV61: =IF($D61="",0,INDEX($CP$58:$CP$63,MATCH($D61,$CO$58:$CO$63))*$BR$58) -> 0 | AW61: =SUM(AK61:AV61) -> 0 | AX61: =IF($D61="",0,((IF(OR($R61="x",$R61="xx"),1,0))*INDEX($CR$58:$CR$63,MATCH($D61,$CQ$58:$CQ$63))*$BR$58)) -> 0 | AY61: =IF($D61="",0,((IF(OR($S61="x",$S61="xx"),1,0))*INDEX($CT$58:$CT$63,MATCH($D61,$CS$58:$CS$63))*$BR$58)) -> 0 | AZ61: =SUM(AX61:AY61) -> 0 | BC61: Selection Owner Provided | BD61: 20 | BE61: 2500 | BF61: 20 | BG61: 1000 | BH61: 20 | BI61: 5500 | BJ61: 20 | BK61: 3500 | BL61: Sensors | BM61: CU Cond | BN61: 20 | BO61: 750 | BP61: 20 | BQ61: 3100 | BS61: 20 | BT61: 7 | BU61: 20 | BV61: 10 | BW61: 20 | BX61: 14 | BY61: 20 | BZ61: 4 | CA61: 20 | CB61: 6 | CC61: 20 | CD61: 5 | CE61: 20 | CF61: 14 | CG61: 20 | CH61: 1 | CI61: 20 | CJ61: 2 | CK61: 20 | CL61: 2 | CM61: 20 | CN61: 3 | CO61: 20 | CP61: 5 | CQ61: 20 | CR61: 32 | CS61: 20 | CT61: 24
B62: =B61+1 -> 6 | G62: =F62*D62 -> 0 | T62: =IF($L62="x",IF($D62="",0,INDEX($BE$58:$BE$63,MATCH($D62,$BD$58:$BD$63,1))),0) -> 0 | U62: =IF($I62="x",IF($D62="",0,INDEX($BG$58:$BG$63,MATCH($D62,$BF$58:$BF$63,1))),0) -> 0 | V62: =IF($J62="x",IF($D62="",0,INDEX($BI$58:$BI$63,MATCH($D62,$BH$58:$BH$63,1))),0) -> 0 | W62: =IF($K62="x",IF($D62="",0,INDEX($BK$58:$BK$63,MATCH($D62,$BJ$58:$BJ$63,1))),0) -> 0 | X62: =IF($D62="",0,IF(M62="x",$BM$60,0)) -> 0 | Y62: =IF($D62="",0,IF(N62="x",$BM$62,0)) -> 0 | Z62: =IF($O62="x",IF($D62="",0,$BL$58),0) -> 0 | AA62: =IF($P62="x",IF($D62="",0,IF($D62>4,$BL$60,0)),0) -> 0 | AB62: =IF($D62="",0,$Q62*$BL$62) -> 0 | AC62: =IF($D62="",0,(Q62+IF(OR(O62="x",44="xx"),1,0))*$BM$58) -> 0 | AD62: =G62+H62 -> 0 | AE62: =SUM(T62:AC62) -> 0 | AF62: =IF($E62="xx",(1600*$D62+$AE62),SUM(AD62:AE62))*$AF$55 -> 0 | AG62: =SUM(AD62:AF62) -> 0 | AH62: =IF($R62="x",IF($D62="",0,INDEX($BO$58:$BO$63,MATCH($D62,$BN$58:$BN$63,1))),0) -> 0 | AI62: =IF($S62="x",IF($D62="",0,INDEX($BQ$58:$BQ$63,MATCH($D62,$BP$58:$BP$63,1))),0) -> 0 | AJ62: =SUM(AH62:AI62) -> 0 | AK62: =IF($D62="",0,INDEX($BT$58:$BT$63,MATCH($D62,$BS$58:$BS$63))*$BR$58) -> 0 | AL62: =IF($D62="",0,IF(OR($I62="x",$I62="xx"),INDEX($BV$58:$BV$63,MATCH($D62,$BU$58:$BU$63))*$BR$58,0)) -> 0 | AM62: =IF($D62="",0,IF(OR($J62="x",$J62="xx"),INDEX($BX$58:$BX$63,MATCH($D62,$BW$58:$BW$63))*$BR$58,0)) -> 0 | AN62: =IF($D62="",0,IF(OR($K62="x",$K62="xx"),INDEX($BZ$58:$BZ$63,MATCH($D62,$BY$58:$BY$63))*$BR$58,0)) -> 0 | AO62: =IF($D62="",0,IF(OR($L62="x",$L62="xx"),INDEX($CB$58:$CB$63,MATCH($D62,$CA$58:$CA$63))*$BR$58,0)) -> 0 | AP62: =IF($D62="",0,IF(OR($M62="x",$M62="xx"),INDEX($CD$58:$CD$63,MATCH($D62,$CC$58:$CC$63))*$BR$58,0)) -> 0 | AQ62: =IF($D62="",0,IF(OR($N62="x",$N62="xx"),INDEX($CF$58:$CF$63,MATCH($D62,$CE$58:$CE$63))*$BR$58,0)) -> 0 | AR62: =IF($D62="",0,IF(OR($O62="x",$O62="xx"),INDEX($CH$58:$CH$63,MATCH($D62,$CG$58:$CG$63))*$BR$58,0)) -> 0 | AS62: =IF($D62="",0,IF(OR($P62="x",$P62="xx"),IF($D62>4,INDEX($CJ$58:$CJ$63,MATCH($D62,$CI$58:$CI$63))*$BR$58,0),0)) -> 0 | AT62: =IF($D62="",0,($Q62*INDEX($CL$58:$CL$63,MATCH($D62,$CK$58:$CK$63))*$BR$58)) -> 0 | AU62: =IF($D62="",0,(($Q62+IF(OR($O62="x",$O62="xx"),1,0))*INDEX($CN$58:$CN$63,MATCH($D62,$CM$58:$CM$63))*$BR$58)) -> 0 | AV62: =IF($D62="",0,INDEX($CP$58:$CP$63,MATCH($D62,$CO$58:$CO$63))*$BR$58) -> 0 | AW62: =SUM(AK62:AV62) -> 0 | AX62: =IF($D62="",0,((IF(OR($R62="x",$R62="xx"),1,0))*INDEX($CR$58:$CR$63,MATCH($D62,$CQ$58:$CQ$63))*$BR$58)) -> 0 | AY62: =IF($D62="",0,((IF(OR($S62="x",$S62="xx"),1,0))*INDEX($CT$58:$CT$63,MATCH($D62,$CS$58:$CS$63))*$BR$58)) -> 0 | AZ62: =SUM(AX62:AY62) -> 0 | BC62: xx | BD62: 50 | BE62: 6000 | BF62: 50 | BG62: 6000 | BH62: 50 | BI62: 10000 | BJ62: 50 | BK62: 8000 | BL62: 125 | BM62: =50*4+15+50 -> 265 | BN62: 50 | BO62: 1000 | BP62: 50 | BQ62: 6000 | BS62: 50 | BT62: 14 | BU62: 50 | BV62: 15 | BW62: 50 | BX62: 20 | BY62: 50 | BZ62: 8 | CA62: 50 | CB62: 8 | CC62: 50 | CD62: 6 | CE62: 50 | CF62: 18 | CG62: 50 | CH62: 2 | CI62: 50 | CJ62: 3 | CK62: 50 | CL62: 2 | CM62: 50 | CN62: 3 | CO62: 50 | CP62: 7 | CQ62: 50 | CR62: 48 | CS62: 50 | CT62: 32
B63: =B62+1 -> 7 | G63: =F63*D63 -> 0 | T63: =IF($L63="x",IF($D63="",0,INDEX($BE$58:$BE$63,MATCH($D63,$BD$58:$BD$63,1))),0) -> 0 | U63: =IF($I63="x",IF($D63="",0,INDEX($BG$58:$BG$63,MATCH($D63,$BF$58:$BF$63,1))),0) -> 0 | V63: =IF($J63="x",IF($D63="",0,INDEX($BI$58:$BI$63,MATCH($D63,$BH$58:$BH$63,1))),0) -> 0 | W63: =IF($K63="x",IF($D63="",0,INDEX($BK$58:$BK$63,MATCH($D63,$BJ$58:$BJ$63,1))),0) -> 0 | X63: =IF($D63="",0,IF(M63="x",$BM$60,0)) -> 0 | Y63: =IF($D63="",0,IF(N63="x",$BM$62,0)) -> 0 | Z63: =IF($O63="x",IF($D63="",0,$BL$58),0) -> 0 | AA63: =IF($P63="x",IF($D63="",0,IF($D63>4,$BL$60,0)),0) -> 0 | AB63: =IF($D63="",0,$Q63*$BL$62) -> 0 | AC63: =IF($D63="",0,(Q63+IF(OR(O63="x",44="xx"),1,0))*$BM$58) -> 0 | AD63: =G63+H63 -> 0 | AE63: =SUM(T63:AC63) -> 0 | AF63: =IF($E63="xx",(1600*$D63+$AE63),SUM(AD63:AE63))*$AF$55 -> 0 | AG63: =SUM(AD63:AF63) -> 0 | AH63: =IF($R63="x",IF($D63="",0,INDEX($BO$58:$BO$63,MATCH($D63,$BN$58:$BN$63,1))),0) -> 0 | AI63: =IF($S63="x",IF($D63="",0,INDEX($BQ$58:$BQ$63,MATCH($D63,$BP$58:$BP$63,1))),0) -> 0 | AJ63: =SUM(AH63:AI63) -> 0 | AK63: =IF($D63="",0,INDEX($BT$58:$BT$63,MATCH($D63,$BS$58:$BS$63))*$BR$58) -> 0 | AL63: =IF($D63="",0,IF(OR($I63="x",$I63="xx"),INDEX($BV$58:$BV$63,MATCH($D63,$BU$58:$BU$63))*$BR$58,0)) -> 0 | AM63: =IF($D63="",0,IF(OR($J63="x",$J63="xx"),INDEX($BX$58:$BX$63,MATCH($D63,$BW$58:$BW$63))*$BR$58,0)) -> 0 | AN63: =IF($D63="",0,IF(OR($K63="x",$K63="xx"),INDEX($BZ$58:$BZ$63,MATCH($D63,$BY$58:$BY$63))*$BR$58,0)) -> 0 | AO63: =IF($D63="",0,IF(OR($L63="x",$L63="xx"),INDEX($CB$58:$CB$63,MATCH($D63,$CA$58:$CA$63))*$BR$58,0)) -> 0 | AP63: =IF($D63="",0,IF(OR($M63="x",$M63="xx"),INDEX($CD$58:$CD$63,MATCH($D63,$CC$58:$CC$63))*$BR$58,0)) -> 0 | AQ63: =IF($D63="",0,IF(OR($N63="x",$N63="xx"),INDEX($CF$58:$CF$63,MATCH($D63,$CE$58:$CE$63))*$BR$58,0)) -> 0 | AR63: =IF($D63="",0,IF(OR($O63="x",$O63="xx"),INDEX($CH$58:$CH$63,MATCH($D63,$CG$58:$CG$63))*$BR$58,0)) -> 0 | AS63: =IF($D63="",0,IF(OR($P63="x",$P63="xx"),IF($D63>4,INDEX($CJ$58:$CJ$63,MATCH($D63,$CI$58:$CI$63))*$BR$58,0),0)) -> 0 | AT63: =IF($D63="",0,($Q63*INDEX($CL$58:$CL$63,MATCH($D63,$CK$58:$CK$63))*$BR$58)) -> 0 | AU63: =IF($D63="",0,(($Q63+IF(OR($O63="x",$O63="xx"),1,0))*INDEX($CN$58:$CN$63,MATCH($D63,$CM$58:$CM$63))*$BR$58)) -> 0 | AV63: =IF($D63="",0,INDEX($CP$58:$CP$63,MATCH($D63,$CO$58:$CO$63))*$BR$58) -> 0 | AW63: =SUM(AK63:AV63) -> 0 | AX63: =IF($D63="",0,((IF(OR($R63="x",$R63="xx"),1,0))*INDEX($CR$58:$CR$63,MATCH($D63,$CQ$58:$CQ$63))*$BR$58)) -> 0 | AY63: =IF($D63="",0,((IF(OR($S63="x",$S63="xx"),1,0))*INDEX($CT$58:$CT$63,MATCH($D63,$CS$58:$CS$63))*$BR$58)) -> 0 | AZ63: =SUM(AX63:AY63) -> 0 | BD63: 75 | BE63: 15000 | BF63: 75 | BG63: 15000 | BH63: 75 | BI63: 15000 | BJ63: 75 | BK63: 13000 | BN63: 75 | BO63: 1500 | BP63: 75 | BQ63: 9000 | BS63: 75 | BT63: 28 | BU63: 75 | BV63: 30 | BW63: 75 | BX63: 40 | BY63: 75 | BZ63: 16 | CA63: 75 | CB63: 12 | CC63: 75 | CD63: 8 | CE63: 75 | CF63: 22 | CG63: 75 | CH63: 3 | CI63: 75 | CJ63: 3 | CK63: 75 | CL63: 2 | CM63: 75 | CN63: 3 | CO63: 75 | CP63: 12 | CQ63: 75 | CR63: 56 | CS63: 75 | CT63: 40
B64: =B63+1 -> 8 | G64: =F64*D64 -> 0 | T64: =IF($L64="x",IF($D64="",0,INDEX($BE$58:$BE$63,MATCH($D64,$BD$58:$BD$63,1))),0) -> 0 | U64: =IF($I64="x",IF($D64="",0,INDEX($BG$58:$BG$63,MATCH($D64,$BF$58:$BF$63,1))),0) -> 0 | V64: =IF($J64="x",IF($D64="",0,INDEX($BI$58:$BI$63,MATCH($D64,$BH$58:$BH$63,1))),0) -> 0 | W64: =IF($K64="x",IF($D64="",0,INDEX($BK$58:$BK$63,MATCH($D64,$BJ$58:$BJ$63,1))),0) -> 0 | X64: =IF($D64="",0,IF(M64="x",$BM$60,0)) -> 0 | Y64: =IF($D64="",0,IF(N64="x",$BM$62,0)) -> 0 | Z64: =IF($O64="x",IF($D64="",0,$BL$58),0) -> 0 | AA64: =IF($P64="x",IF($D64="",0,IF($D64>4,$BL$60,0)),0) -> 0 | AB64: =IF($D64="",0,$Q64*$BL$62) -> 0 | AC64: =IF($D64="",0,(Q64+IF(OR(O64="x",44="xx"),1,0))*$BM$58) -> 0 | AD64: =G64+H64 -> 0 | AE64: =SUM(T64:AC64) -> 0 | AF64: =IF($E64="xx",(1600*$D64+$AE64),SUM(AD64:AE64))*$AF$55 -> 0 | AG64: =SUM(AD64:AF64) -> 0 | AH64: =IF($R64="x",IF($D64="",0,INDEX($BO$58:$BO$63,MATCH($D64,$BN$58:$BN$63,1))),0) -> 0 | AI64: =IF($S64="x",IF($D64="",0,INDEX($BQ$58:$BQ$63,MATCH($D64,$BP$58:$BP$63,1))),0) -> 0 | AJ64: =SUM(AH64:AI64) -> 0 | AK64: =IF($D64="",0,INDEX($BT$58:$BT$63,MATCH($D64,$BS$58:$BS$63))*$BR$58) -> 0 | AL64: =IF($D64="",0,IF(OR($I64="x",$I64="xx"),INDEX($BV$58:$BV$63,MATCH($D64,$BU$58:$BU$63))*$BR$58,0)) -> 0 | AM64: =IF($D64="",0,IF(OR($J64="x",$J64="xx"),INDEX($BX$58:$BX$63,MATCH($D64,$BW$58:$BW$63))*$BR$58,0)) -> 0 | AN64: =IF($D64="",0,IF(OR($K64="x",$K64="xx"),INDEX($BZ$58:$BZ$63,MATCH($D64,$BY$58:$BY$63))*$BR$58,0)) -> 0 | AO64: =IF($D64="",0,IF(OR($L64="x",$L64="xx"),INDEX($CB$58:$CB$63,MATCH($D64,$CA$58:$CA$63))*$BR$58,0)) -> 0 | AP64: =IF($D64="",0,IF(OR($M64="x",$M64="xx"),INDEX($CD$58:$CD$63,MATCH($D64,$CC$58:$CC$63))*$BR$58,0)) -> 0 | AQ64: =IF($D64="",0,IF(OR($N64="x",$N64="xx"),INDEX($CF$58:$CF$63,MATCH($D64,$CE$58:$CE$63))*$BR$58,0)) -> 0 | AR64: =IF($D64="",0,IF(OR($O64="x",$O64="xx"),INDEX($CH$58:$CH$63,MATCH($D64,$CG$58:$CG$63))*$BR$58,0)) -> 0 | AS64: =IF($D64="",0,IF(OR($P64="x",$P64="xx"),IF($D64>4,INDEX($CJ$58:$CJ$63,MATCH($D64,$CI$58:$CI$63))*$BR$58,0),0)) -> 0 | AT64: =IF($D64="",0,($Q64*INDEX($CL$58:$CL$63,MATCH($D64,$CK$58:$CK$63))*$BR$58)) -> 0 | AU64: =IF($D64="",0,(($Q64+IF(OR($O64="x",$O64="xx"),1,0))*INDEX($CN$58:$CN$63,MATCH($D64,$CM$58:$CM$63))*$BR$58)) -> 0 | AV64: =IF($D64="",0,INDEX($CP$58:$CP$63,MATCH($D64,$CO$58:$CO$63))*$BR$58) -> 0 | AW64: =SUM(AK64:AV64) -> 0 | AX64: =IF($D64="",0,((IF(OR($R64="x",$R64="xx"),1,0))*INDEX($CR$58:$CR$63,MATCH($D64,$CQ$58:$CQ$63))*$BR$58)) -> 0 | AY64: =IF($D64="",0,((IF(OR($S64="x",$S64="xx"),1,0))*INDEX($CT$58:$CT$63,MATCH($D64,$CS$58:$CS$63))*$BR$58)) -> 0 | AZ64: =SUM(AX64:AY64) -> 0
B65: =B64+1 -> 9 | G65: =F65*D65 -> 0 | T65: =IF($L65="x",IF($D65="",0,INDEX($BE$58:$BE$63,MATCH($D65,$BD$58:$BD$63,1))),0) -> 0 | U65: =IF($I65="x",IF($D65="",0,INDEX($BG$58:$BG$63,MATCH($D65,$BF$58:$BF$63,1))),0) -> 0 | V65: =IF($J65="x",IF($D65="",0,INDEX($BI$58:$BI$63,MATCH($D65,$BH$58:$BH$63,1))),0) -> 0 | W65: =IF($K65="x",IF($D65="",0,INDEX($BK$58:$BK$63,MATCH($D65,$BJ$58:$BJ$63,1))),0) -> 0 | X65: =IF($D65="",0,IF(M65="x",$BM$60,0)) -> 0 | Y65: =IF($D65="",0,IF(N65="x",$BM$62,0)) -> 0 | Z65: =IF($O65="x",IF($D65="",0,$BL$58),0) -> 0 | AA65: =IF($P65="x",IF($D65="",0,IF($D65>4,$BL$60,0)),0) -> 0 | AB65: =IF($D65="",0,$Q65*$BL$62) -> 0 | AC65: =IF($D65="",0,(Q65+IF(OR(O65="x",44="xx"),1,0))*$BM$58) -> 0 | AD65: =G65+H65 -> 0 | AE65: =SUM(T65:AC65) -> 0 | AF65: =IF($E65="xx",(1600*$D65+$AE65),SUM(AD65:AE65))*$AF$55 -> 0 | AG65: =SUM(AD65:AF65) -> 0 | AH65: =IF($R65="x",IF($D65="",0,INDEX($BO$58:$BO$63,MATCH($D65,$BN$58:$BN$63,1))),0) -> 0 | AI65: =IF($S65="x",IF($D65="",0,INDEX($BQ$58:$BQ$63,MATCH($D65,$BP$58:$BP$63,1))),0) -> 0 | AJ65: =SUM(AH65:AI65) -> 0 | AK65: =IF($D65="",0,INDEX($BT$58:$BT$63,MATCH($D65,$BS$58:$BS$63))*$BR$58) -> 0 | AL65: =IF($D65="",0,IF(OR($I65="x",$I65="xx"),INDEX($BV$58:$BV$63,MATCH($D65,$BU$58:$BU$63))*$BR$58,0)) -> 0 | AM65: =IF($D65="",0,IF(OR($J65="x",$J65="xx"),INDEX($BX$58:$BX$63,MATCH($D65,$BW$58:$BW$63))*$BR$58,0)) -> 0 | AN65: =IF($D65="",0,IF(OR($K65="x",$K65="xx"),INDEX($BZ$58:$BZ$63,MATCH($D65,$BY$58:$BY$63))*$BR$58,0)) -> 0 | AO65: =IF($D65="",0,IF(OR($L65="x",$L65="xx"),INDEX($CB$58:$CB$63,MATCH($D65,$CA$58:$CA$63))*$BR$58,0)) -> 0 | AP65: =IF($D65="",0,IF(OR($M65="x",$M65="xx"),INDEX($CD$58:$CD$63,MATCH($D65,$CC$58:$CC$63))*$BR$58,0)) -> 0 | AQ65: =IF($D65="",0,IF(OR($N65="x",$N65="xx"),INDEX($CF$58:$CF$63,MATCH($D65,$CE$58:$CE$63))*$BR$58,0)) -> 0 | AR65: =IF($D65="",0,IF(OR($O65="x",$O65="xx"),INDEX($CH$58:$CH$63,MATCH($D65,$CG$58:$CG$63))*$BR$58,0)) -> 0 | AS65: =IF($D65="",0,IF(OR($P65="x",$P65="xx"),IF($D65>4,INDEX($CJ$58:$CJ$63,MATCH($D65,$CI$58:$CI$63))*$BR$58,0),0)) -> 0 | AT65: =IF($D65="",0,($Q65*INDEX($CL$58:$CL$63,MATCH($D65,$CK$58:$CK$63))*$BR$58)) -> 0 | AU65: =IF($D65="",0,(($Q65+IF(OR($O65="x",$O65="xx"),1,0))*INDEX($CN$58:$CN$63,MATCH($D65,$CM$58:$CM$63))*$BR$58)) -> 0 | AV65: =IF($D65="",0,INDEX($CP$58:$CP$63,MATCH($D65,$CO$58:$CO$63))*$BR$58) -> 0 | AW65: =SUM(AK65:AV65) -> 0 | AX65: =IF($D65="",0,((IF(OR($R65="x",$R65="xx"),1,0))*INDEX($CR$58:$CR$63,MATCH($D65,$CQ$58:$CQ$63))*$BR$58)) -> 0 | AY65: =IF($D65="",0,((IF(OR($S65="x",$S65="xx"),1,0))*INDEX($CT$58:$CT$63,MATCH($D65,$CS$58:$CS$63))*$BR$58)) -> 0 | AZ65: =SUM(AX65:AY65) -> 0
B66: =B65+1 -> 10 | G66: =F66*D66 -> 0 | T66: =IF($L66="x",IF($D66="",0,INDEX($BE$58:$BE$63,MATCH($D66,$BD$58:$BD$63,1))),0) -> 0 | U66: =IF($I66="x",IF($D66="",0,INDEX($BG$58:$BG$63,MATCH($D66,$BF$58:$BF$63,1))),0) -> 0 | V66: =IF($J66="x",IF($D66="",0,INDEX($BI$58:$BI$63,MATCH($D66,$BH$58:$BH$63,1))),0) -> 0 | W66: =IF($K66="x",IF($D66="",0,INDEX($BK$58:$BK$63,MATCH($D66,$BJ$58:$BJ$63,1))),0) -> 0 | X66: =IF($D66="",0,IF(M66="x",$BM$60,0)) -> 0 | Y66: =IF($D66="",0,IF(N66="x",$BM$62,0)) -> 0 | Z66: =IF($O66="x",IF($D66="",0,$BL$58),0) -> 0 | AA66: =IF($P66="x",IF($D66="",0,IF($D66>4,$BL$60,0)),0) -> 0 | AB66: =IF($D66="",0,$Q66*$BL$62) -> 0 | AC66: =IF($D66="",0,(Q66+IF(OR(O66="x",44="xx"),1,0))*$BM$58) -> 0 | AD66: =G66+H66 -> 0 | AE66: =SUM(T66:AC66) -> 0 | AF66: =IF($E66="xx",(1600*$D66+$AE66),SUM(AD66:AE66))*$AF$55 -> 0 | AG66: =SUM(AD66:AF66) -> 0 | AH66: =IF($R66="x",IF($D66="",0,INDEX($BO$58:$BO$63,MATCH($D66,$BN$58:$BN$63,1))),0) -> 0 | AI66: =IF($S66="x",IF($D66="",0,INDEX($BQ$58:$BQ$63,MATCH($D66,$BP$58:$BP$63,1))),0) -> 0 | AJ66: =SUM(AH66:AI66) -> 0 | AK66: =IF($D66="",0,INDEX($BT$58:$BT$63,MATCH($D66,$BS$58:$BS$63))*$BR$58) -> 0 | AL66: =IF($D66="",0,IF(OR($I66="x",$I66="xx"),INDEX($BV$58:$BV$63,MATCH($D66,$BU$58:$BU$63))*$BR$58,0)) -> 0 | AM66: =IF($D66="",0,IF(OR($J66="x",$J66="xx"),INDEX($BX$58:$BX$63,MATCH($D66,$BW$58:$BW$63))*$BR$58,0)) -> 0 | AN66: =IF($D66="",0,IF(OR($K66="x",$K66="xx"),INDEX($BZ$58:$BZ$63,MATCH($D66,$BY$58:$BY$63))*$BR$58,0)) -> 0 | AO66: =IF($D66="",0,IF(OR($L66="x",$L66="xx"),INDEX($CB$58:$CB$63,MATCH($D66,$CA$58:$CA$63))*$BR$58,0)) -> 0 | AP66: =IF($D66="",0,IF(OR($M66="x",$M66="xx"),INDEX($CD$58:$CD$63,MATCH($D66,$CC$58:$CC$63))*$BR$58,0)) -> 0 | AQ66: =IF($D66="",0,IF(OR($N66="x",$N66="xx"),INDEX($CF$58:$CF$63,MATCH($D66,$CE$58:$CE$63))*$BR$58,0)) -> 0 | AR66: =IF($D66="",0,IF(OR($O66="x",$O66="xx"),INDEX($CH$58:$CH$63,MATCH($D66,$CG$58:$CG$63))*$BR$58,0)) -> 0 | AS66: =IF($D66="",0,IF(OR($P66="x",$P66="xx"),IF($D66>4,INDEX($CJ$58:$CJ$63,MATCH($D66,$CI$58:$CI$63))*$BR$58,0),0)) -> 0 | AT66: =IF($D66="",0,($Q66*INDEX($CL$58:$CL$63,MATCH($D66,$CK$58:$CK$63))*$BR$58)) -> 0 | AU66: =IF($D66="",0,(($Q66+IF(OR($O66="x",$O66="xx"),1,0))*INDEX($CN$58:$CN$63,MATCH($D66,$CM$58:$CM$63))*$BR$58)) -> 0 | AV66: =IF($D66="",0,INDEX($CP$58:$CP$63,MATCH($D66,$CO$58:$CO$63))*$BR$58) -> 0 | AW66: =SUM(AK66:AV66) -> 0 | AX66: =IF($D66="",0,((IF(OR($R66="x",$R66="xx"),1,0))*INDEX($CR$58:$CR$63,MATCH($D66,$CQ$58:$CQ$63))*$BR$58)) -> 0 | AY66: =IF($D66="",0,((IF(OR($S66="x",$S66="xx"),1,0))*INDEX($CT$58:$CT$63,MATCH($D66,$CS$58:$CS$63))*$BR$58)) -> 0 | AZ66: =SUM(AX66:AY66) -> 0
B67: =B66+1 -> 11 | G67: =F67*D67 -> 0 | T67: =IF($L67="x",IF($D67="",0,INDEX($BE$58:$BE$63,MATCH($D67,$BD$58:$BD$63,1))),0) -> 0 | U67: =IF($I67="x",IF($D67="",0,INDEX($BG$58:$BG$63,MATCH($D67,$BF$58:$BF$63,1))),0) -> 0 | V67: =IF($J67="x",IF($D67="",0,INDEX($BI$58:$BI$63,MATCH($D67,$BH$58:$BH$63,1))),0) -> 0 | W67: =IF($K67="x",IF($D67="",0,INDEX($BK$58:$BK$63,MATCH($D67,$BJ$58:$BJ$63,1))),0) -> 0 | X67: =IF($D67="",0,IF(M67="x",$BM$60,0)) -> 0 | Y67: =IF($D67="",0,IF(N67="x",$BM$62,0)) -> 0 | Z67: =IF($O67="x",IF($D67="",0,$BL$58),0) -> 0 | AA67: =IF($P67="x",IF($D67="",0,IF($D67>4,$BL$60,0)),0) -> 0 | AB67: =IF($D67="",0,$Q67*$BL$62) -> 0 | AC67: =IF($D67="",0,(Q67+IF(OR(O67="x",44="xx"),1,0))*$BM$58) -> 0 | AD67: =G67+H67 -> 0 | AE67: =SUM(T67:AC67) -> 0 | AF67: =IF($E67="xx",(1600*$D67+$AE67),SUM(AD67:AE67))*$AF$55 -> 0 | AG67: =SUM(AD67:AF67) -> 0 | AH67: =IF($R67="x",IF($D67="",0,INDEX($BO$58:$BO$63,MATCH($D67,$BN$58:$BN$63,1))),0) -> 0 | AI67: =IF($S67="x",IF($D67="",0,INDEX($BQ$58:$BQ$63,MATCH($D67,$BP$58:$BP$63,1))),0) -> 0 | AJ67: =SUM(AH67:AI67) -> 0 | AK67: =IF($D67="",0,INDEX($BT$58:$BT$63,MATCH($D67,$BS$58:$BS$63))*$BR$58) -> 0 | AL67: =IF($D67="",0,IF(OR($I67="x",$I67="xx"),INDEX($BV$58:$BV$63,MATCH($D67,$BU$58:$BU$63))*$BR$58,0)) -> 0 | AM67: =IF($D67="",0,IF(OR($J67="x",$J67="xx"),INDEX($BX$58:$BX$63,MATCH($D67,$BW$58:$BW$63))*$BR$58,0)) -> 0 | AN67: =IF($D67="",0,IF(OR($K67="x",$K67="xx"),INDEX($BZ$58:$BZ$63,MATCH($D67,$BY$58:$BY$63))*$BR$58,0)) -> 0 | AO67: =IF($D67="",0,IF(OR($L67="x",$L67="xx"),INDEX($CB$58:$CB$63,MATCH($D67,$CA$58:$CA$63))*$BR$58,0)) -> 0 | AP67: =IF($D67="",0,IF(OR($M67="x",$M67="xx"),INDEX($CD$58:$CD$63,MATCH($D67,$CC$58:$CC$63))*$BR$58,0)) -> 0 | AQ67: =IF($D67="",0,IF(OR($N67="x",$N67="xx"),INDEX($CF$58:$CF$63,MATCH($D67,$CE$58:$CE$63))*$BR$58,0)) -> 0 | AR67: =IF($D67="",0,IF(OR($O67="x",$O67="xx"),INDEX($CH$58:$CH$63,MATCH($D67,$CG$58:$CG$63))*$BR$58,0)) -> 0 | AS67: =IF($D67="",0,IF(OR($P67="x",$P67="xx"),IF($D67>4,INDEX($CJ$58:$CJ$63,MATCH($D67,$CI$58:$CI$63))*$BR$58,0),0)) -> 0 | AT67: =IF($D67="",0,($Q67*INDEX($CL$58:$CL$63,MATCH($D67,$CK$58:$CK$63))*$BR$58)) -> 0 | AU67: =IF($D67="",0,(($Q67+IF(OR($O67="x",$O67="xx"),1,0))*INDEX($CN$58:$CN$63,MATCH($D67,$CM$58:$CM$63))*$BR$58)) -> 0 | AV67: =IF($D67="",0,INDEX($CP$58:$CP$63,MATCH($D67,$CO$58:$CO$63))*$BR$58) -> 0 | AW67: =SUM(AK67:AV67) -> 0 | AX67: =IF($D67="",0,((IF(OR($R67="x",$R67="xx"),1,0))*INDEX($CR$58:$CR$63,MATCH($D67,$CQ$58:$CQ$63))*$BR$58)) -> 0 | AY67: =IF($D67="",0,((IF(OR($S67="x",$S67="xx"),1,0))*INDEX($CT$58:$CT$63,MATCH($D67,$CS$58:$CS$63))*$BR$58)) -> 0 | AZ67: =SUM(AX67:AY67) -> 0
B68: =B67+1 -> 12 | G68: =F68*D68 -> 0 | T68: =IF($L68="x",IF($D68="",0,INDEX($BE$58:$BE$63,MATCH($D68,$BD$58:$BD$63,1))),0) -> 0 | U68: =IF($I68="x",IF($D68="",0,INDEX($BG$58:$BG$63,MATCH($D68,$BF$58:$BF$63,1))),0) -> 0 | V68: =IF($J68="x",IF($D68="",0,INDEX($BI$58:$BI$63,MATCH($D68,$BH$58:$BH$63,1))),0) -> 0 | W68: =IF($K68="x",IF($D68="",0,INDEX($BK$58:$BK$63,MATCH($D68,$BJ$58:$BJ$63,1))),0) -> 0 | X68: =IF($D68="",0,IF(M68="x",$BM$60,0)) -> 0 | Y68: =IF($D68="",0,IF(N68="x",$BM$62,0)) -> 0 | Z68: =IF($O68="x",IF($D68="",0,$BL$58),0) -> 0 | AA68: =IF($P68="x",IF($D68="",0,IF($D68>4,$BL$60,0)),0) -> 0 | AB68: =IF($D68="",0,$Q68*$BL$62) -> 0 | AC68: =IF($D68="",0,(Q68+IF(OR(O68="x",44="xx"),1,0))*$BM$58) -> 0 | AD68: =G68+H68 -> 0 | AE68: =SUM(T68:AC68) -> 0 | AF68: =IF($E68="xx",(1600*$D68+$AE68),SUM(AD68:AE68))*$AF$55 -> 0 | AG68: =SUM(AD68:AF68) -> 0 | AH68: =IF($R68="x",IF($D68="",0,INDEX($BO$58:$BO$63,MATCH($D68,$BN$58:$BN$63,1))),0) -> 0 | AI68: =IF($S68="x",IF($D68="",0,INDEX($BQ$58:$BQ$63,MATCH($D68,$BP$58:$BP$63,1))),0) -> 0 | AJ68: =SUM(AH68:AI68) -> 0 | AK68: =IF($D68="",0,INDEX($BT$58:$BT$63,MATCH($D68,$BS$58:$BS$63))*$BR$58) -> 0 | AL68: =IF($D68="",0,IF(OR($I68="x",$I68="xx"),INDEX($BV$58:$BV$63,MATCH($D68,$BU$58:$BU$63))*$BR$58,0)) -> 0 | AM68: =IF($D68="",0,IF(OR($J68="x",$J68="xx"),INDEX($BX$58:$BX$63,MATCH($D68,$BW$58:$BW$63))*$BR$58,0)) -> 0 | AN68: =IF($D68="",0,IF(OR($K68="x",$K68="xx"),INDEX($BZ$58:$BZ$63,MATCH($D68,$BY$58:$BY$63))*$BR$58,0)) -> 0 | AO68: =IF($D68="",0,IF(OR($L68="x",$L68="xx"),INDEX($CB$58:$CB$63,MATCH($D68,$CA$58:$CA$63))*$BR$58,0)) -> 0 | AP68: =IF($D68="",0,IF(OR($M68="x",$M68="xx"),INDEX($CD$58:$CD$63,MATCH($D68,$CC$58:$CC$63))*$BR$58,0)) -> 0 | AQ68: =IF($D68="",0,IF(OR($N68="x",$N68="xx"),INDEX($CF$58:$CF$63,MATCH($D68,$CE$58:$CE$63))*$BR$58,0)) -> 0 | AR68: =IF($D68="",0,IF(OR($O68="x",$O68="xx"),INDEX($CH$58:$CH$63,MATCH($D68,$CG$58:$CG$63))*$BR$58,0)) -> 0 | AS68: =IF($D68="",0,IF(OR($P68="x",$P68="xx"),IF($D68>4,INDEX($CJ$58:$CJ$63,MATCH($D68,$CI$58:$CI$63))*$BR$58,0),0)) -> 0 | AT68: =IF($D68="",0,($Q68*INDEX($CL$58:$CL$63,MATCH($D68,$CK$58:$CK$63))*$BR$58)) -> 0 | AU68: =IF($D68="",0,(($Q68+IF(OR($O68="x",$O68="xx"),1,0))*INDEX($CN$58:$CN$63,MATCH($D68,$CM$58:$CM$63))*$BR$58)) -> 0 | AV68: =IF($D68="",0,INDEX($CP$58:$CP$63,MATCH($D68,$CO$58:$CO$63))*$BR$58) -> 0 | AW68: =SUM(AK68:AV68) -> 0 | AX68: =IF($D68="",0,((IF(OR($R68="x",$R68="xx"),1,0))*INDEX($CR$58:$CR$63,MATCH($D68,$CQ$58:$CQ$63))*$BR$58)) -> 0 | AY68: =IF($D68="",0,((IF(OR($S68="x",$S68="xx"),1,0))*INDEX($CT$58:$CT$63,MATCH($D68,$CS$58:$CS$63))*$BR$58)) -> 0 | AZ68: =SUM(AX68:AY68) -> 0
B69: =B68+1 -> 13 | G69: =F69*D69 -> 0 | T69: =IF($L69="x",IF($D69="",0,INDEX($BE$58:$BE$63,MATCH($D69,$BD$58:$BD$63,1))),0) -> 0 | U69: =IF($I69="x",IF($D69="",0,INDEX($BG$58:$BG$63,MATCH($D69,$BF$58:$BF$63,1))),0) -> 0 | V69: =IF($J69="x",IF($D69="",0,INDEX($BI$58:$BI$63,MATCH($D69,$BH$58:$BH$63,1))),0) -> 0 | W69: =IF($K69="x",IF($D69="",0,INDEX($BK$58:$BK$63,MATCH($D69,$BJ$58:$BJ$63,1))),0) -> 0 | X69: =IF($D69="",0,IF(M69="x",$BM$60,0)) -> 0 | Y69: =IF($D69="",0,IF(N69="x",$BM$62,0)) -> 0 | Z69: =IF($O69="x",IF($D69="",0,$BL$58),0) -> 0 | AA69: =IF($P69="x",IF($D69="",0,IF($D69>4,$BL$60,0)),0) -> 0 | AB69: =IF($D69="",0,$Q69*$BL$62) -> 0 | AC69: =IF($D69="",0,(Q69+IF(OR(O69="x",44="xx"),1,0))*$BM$58) -> 0 | AD69: =G69+H69 -> 0 | AE69: =SUM(T69:AC69) -> 0 | AF69: =IF($E69="xx",(1600*$D69+$AE69),SUM(AD69:AE69))*$AF$55 -> 0 | AG69: =SUM(AD69:AF69) -> 0 | AH69: =IF($R69="x",IF($D69="",0,INDEX($BO$58:$BO$63,MATCH($D69,$BN$58:$BN$63,1))),0) -> 0 | AI69: =IF($S69="x",IF($D69="",0,INDEX($BQ$58:$BQ$63,MATCH($D69,$BP$58:$BP$63,1))),0) -> 0 | AJ69: =SUM(AH69:AI69) -> 0 | AK69: =IF($D69="",0,INDEX($BT$58:$BT$63,MATCH($D69,$BS$58:$BS$63))*$BR$58) -> 0 | AL69: =IF($D69="",0,IF(OR($I69="x",$I69="xx"),INDEX($BV$58:$BV$63,MATCH($D69,$BU$58:$BU$63))*$BR$58,0)) -> 0 | AM69: =IF($D69="",0,IF(OR($J69="x",$J69="xx"),INDEX($BX$58:$BX$63,MATCH($D69,$BW$58:$BW$63))*$BR$58,0)) -> 0 | AN69: =IF($D69="",0,IF(OR($K69="x",$K69="xx"),INDEX($BZ$58:$BZ$63,MATCH($D69,$BY$58:$BY$63))*$BR$58,0)) -> 0 | AO69: =IF($D69="",0,IF(OR($L69="x",$L69="xx"),INDEX($CB$58:$CB$63,MATCH($D69,$CA$58:$CA$63))*$BR$58,0)) -> 0 | AP69: =IF($D69="",0,IF(OR($M69="x",$M69="xx"),INDEX($CD$58:$CD$63,MATCH($D69,$CC$58:$CC$63))*$BR$58,0)) -> 0 | AQ69: =IF($D69="",0,IF(OR($N69="x",$N69="xx"),INDEX($CF$58:$CF$63,MATCH($D69,$CE$58:$CE$63))*$BR$58,0)) -> 0 | AR69: =IF($D69="",0,IF(OR($O69="x",$O69="xx"),INDEX($CH$58:$CH$63,MATCH($D69,$CG$58:$CG$63))*$BR$58,0)) -> 0 | AS69: =IF($D69="",0,IF(OR($P69="x",$P69="xx"),IF($D69>4,INDEX($CJ$58:$CJ$63,MATCH($D69,$CI$58:$CI$63))*$BR$58,0),0)) -> 0 | AT69: =IF($D69="",0,($Q69*INDEX($CL$58:$CL$63,MATCH($D69,$CK$58:$CK$63))*$BR$58)) -> 0 | AU69: =IF($D69="",0,(($Q69+IF(OR($O69="x",$O69="xx"),1,0))*INDEX($CN$58:$CN$63,MATCH($D69,$CM$58:$CM$63))*$BR$58)) -> 0 | AV69: =IF($D69="",0,INDEX($CP$58:$CP$63,MATCH($D69,$CO$58:$CO$63))*$BR$58) -> 0 | AW69: =SUM(AK69:AV69) -> 0 | AX69: =IF($D69="",0,((IF(OR($R69="x",$R69="xx"),1,0))*INDEX($CR$58:$CR$63,MATCH($D69,$CQ$58:$CQ$63))*$BR$58)) -> 0 | AY69: =IF($D69="",0,((IF(OR($S69="x",$S69="xx"),1,0))*INDEX($CT$58:$CT$63,MATCH($D69,$CS$58:$CS$63))*$BR$58)) -> 0 | AZ69: =SUM(AX69:AY69) -> 0
B70: =B69+1 -> 14 | G70: =F70*D70 -> 0 | T70: =IF($L70="x",IF($D70="",0,INDEX($BE$58:$BE$63,MATCH($D70,$BD$58:$BD$63,1))),0) -> 0 | U70: =IF($I70="x",IF($D70="",0,INDEX($BG$58:$BG$63,MATCH($D70,$BF$58:$BF$63,1))),0) -> 0 | V70: =IF($J70="x",IF($D70="",0,INDEX($BI$58:$BI$63,MATCH($D70,$BH$58:$BH$63,1))),0) -> 0 | W70: =IF($K70="x",IF($D70="",0,INDEX($BK$58:$BK$63,MATCH($D70,$BJ$58:$BJ$63,1))),0) -> 0 | X70: =IF($D70="",0,IF(M70="x",$BM$60,0)) -> 0 | Y70: =IF($D70="",0,IF(N70="x",$BM$62,0)) -> 0 | Z70: =IF($O70="x",IF($D70="",0,$BL$58),0) -> 0 | AA70: =IF($P70="x",IF($D70="",0,IF($D70>4,$BL$60,0)),0) -> 0 | AB70: =IF($D70="",0,$Q70*$BL$62) -> 0 | AC70: =IF($D70="",0,(Q70+IF(OR(O70="x",44="xx"),1,0))*$BM$58) -> 0 | AD70: =G70+H70 -> 0 | AE70: =SUM(T70:AC70) -> 0 | AF70: =IF($E70="xx",(1600*$D70+$AE70),SUM(AD70:AE70))*$AF$55 -> 0 | AG70: =SUM(AD70:AF70) -> 0 | AH70: =IF($R70="x",IF($D70="",0,INDEX($BO$58:$BO$63,MATCH($D70,$BN$58:$BN$63,1))),0) -> 0 | AI70: =IF($S70="x",IF($D70="",0,INDEX($BQ$58:$BQ$63,MATCH($D70,$BP$58:$BP$63,1))),0) -> 0 | AJ70: =SUM(AH70:AI70) -> 0 | AK70: =IF($D70="",0,INDEX($BT$58:$BT$63,MATCH($D70,$BS$58:$BS$63))*$BR$58) -> 0 | AL70: =IF($D70="",0,IF(OR($I70="x",$I70="xx"),INDEX($BV$58:$BV$63,MATCH($D70,$BU$58:$BU$63))*$BR$58,0)) -> 0 | AM70: =IF($D70="",0,IF(OR($J70="x",$J70="xx"),INDEX($BX$58:$BX$63,MATCH($D70,$BW$58:$BW$63))*$BR$58,0)) -> 0 | AN70: =IF($D70="",0,IF(OR($K70="x",$K70="xx"),INDEX($BZ$58:$BZ$63,MATCH($D70,$BY$58:$BY$63))*$BR$58,0)) -> 0 | AO70: =IF($D70="",0,IF(OR($L70="x",$L70="xx"),INDEX($CB$58:$CB$63,MATCH($D70,$CA$58:$CA$63))*$BR$58,0)) -> 0 | AP70: =IF($D70="",0,IF(OR($M70="x",$M70="xx"),INDEX($CD$58:$CD$63,MATCH($D70,$CC$58:$CC$63))*$BR$58,0)) -> 0 | AQ70: =IF($D70="",0,IF(OR($N70="x",$N70="xx"),INDEX($CF$58:$CF$63,MATCH($D70,$CE$58:$CE$63))*$BR$58,0)) -> 0 | AR70: =IF($D70="",0,IF(OR($O70="x",$O70="xx"),INDEX($CH$58:$CH$63,MATCH($D70,$CG$58:$CG$63))*$BR$58,0)) -> 0 | AS70: =IF($D70="",0,IF(OR($P70="x",$P70="xx"),IF($D70>4,INDEX($CJ$58:$CJ$63,MATCH($D70,$CI$58:$CI$63))*$BR$58,0),0)) -> 0 | AT70: =IF($D70="",0,($Q70*INDEX($CL$58:$CL$63,MATCH($D70,$CK$58:$CK$63))*$BR$58)) -> 0 | AU70: =IF($D70="",0,(($Q70+IF(OR($O70="x",$O70="xx"),1,0))*INDEX($CN$58:$CN$63,MATCH($D70,$CM$58:$CM$63))*$BR$58)) -> 0 | AV70: =IF($D70="",0,INDEX($CP$58:$CP$63,MATCH($D70,$CO$58:$CO$63))*$BR$58) -> 0 | AW70: =SUM(AK70:AV70) -> 0 | AX70: =IF($D70="",0,((IF(OR($R70="x",$R70="xx"),1,0))*INDEX($CR$58:$CR$63,MATCH($D70,$CQ$58:$CQ$63))*$BR$58)) -> 0 | AY70: =IF($D70="",0,((IF(OR($S70="x",$S70="xx"),1,0))*INDEX($CT$58:$CT$63,MATCH($D70,$CS$58:$CS$63))*$BR$58)) -> 0 | AZ70: =SUM(AX70:AY70) -> 0
B71: =B70+1 -> 15 | G71: =F71*D71 -> 0 | T71: =IF($L71="x",IF($D71="",0,INDEX($BE$58:$BE$63,MATCH($D71,$BD$58:$BD$63,1))),0) -> 0 | U71: =IF($I71="x",IF($D71="",0,INDEX($BG$58:$BG$63,MATCH($D71,$BF$58:$BF$63,1))),0) -> 0 | V71: =IF($J71="x",IF($D71="",0,INDEX($BI$58:$BI$63,MATCH($D71,$BH$58:$BH$63,1))),0) -> 0 | W71: =IF($K71="x",IF($D71="",0,INDEX($BK$58:$BK$63,MATCH($D71,$BJ$58:$BJ$63,1))),0) -> 0 | X71: =IF($D71="",0,IF(M71="x",$BM$60,0)) -> 0 | Y71: =IF($D71="",0,IF(N71="x",$BM$62,0)) -> 0 | Z71: =IF($O71="x",IF($D71="",0,$BL$58),0) -> 0 | AA71: =IF($P71="x",IF($D71="",0,IF($D71>4,$BL$60,0)),0) -> 0 | AB71: =IF($D71="",0,$Q71*$BL$62) -> 0 | AC71: =IF($D71="",0,(Q71+IF(OR(O71="x",44="xx"),1,0))*$BM$58) -> 0 | AD71: =G71+H71 -> 0 | AE71: =SUM(T71:AC71) -> 0 | AF71: =IF($E71="xx",(1600*$D71+$AE71),SUM(AD71:AE71))*$AF$55 -> 0 | AG71: =SUM(AD71:AF71) -> 0 | AH71: =IF($R71="x",IF($D71="",0,INDEX($BO$58:$BO$63,MATCH($D71,$BN$58:$BN$63,1))),0) -> 0 | AI71: =IF($S71="x",IF($D71="",0,INDEX($BQ$58:$BQ$63,MATCH($D71,$BP$58:$BP$63,1))),0) -> 0 | AJ71: =SUM(AH71:AI71) -> 0 | AK71: =IF($D71="",0,INDEX($BT$58:$BT$63,MATCH($D71,$BS$58:$BS$63))*$BR$58) -> 0 | AL71: =IF($D71="",0,IF(OR($I71="x",$I71="xx"),INDEX($BV$58:$BV$63,MATCH($D71,$BU$58:$BU$63))*$BR$58,0)) -> 0 | AM71: =IF($D71="",0,IF(OR($J71="x",$J71="xx"),INDEX($BX$58:$BX$63,MATCH($D71,$BW$58:$BW$63))*$BR$58,0)) -> 0 | AN71: =IF($D71="",0,IF(OR($K71="x",$K71="xx"),INDEX($BZ$58:$BZ$63,MATCH($D71,$BY$58:$BY$63))*$BR$58,0)) -> 0 | AO71: =IF($D71="",0,IF(OR($L71="x",$L71="xx"),INDEX($CB$58:$CB$63,MATCH($D71,$CA$58:$CA$63))*$BR$58,0)) -> 0 | AP71: =IF($D71="",0,IF(OR($M71="x",$M71="xx"),INDEX($CD$58:$CD$63,MATCH($D71,$CC$58:$CC$63))*$BR$58,0)) -> 0 | AQ71: =IF($D71="",0,IF(OR($N71="x",$N71="xx"),INDEX($CF$58:$CF$63,MATCH($D71,$CE$58:$CE$63))*$BR$58,0)) -> 0 | AR71: =IF($D71="",0,IF(OR($O71="x",$O71="xx"),INDEX($CH$58:$CH$63,MATCH($D71,$CG$58:$CG$63))*$BR$58,0)) -> 0 | AS71: =IF($D71="",0,IF(OR($P71="x",$P71="xx"),IF($D71>4,INDEX($CJ$58:$CJ$63,MATCH($D71,$CI$58:$CI$63))*$BR$58,0),0)) -> 0 | AT71: =IF($D71="",0,($Q71*INDEX($CL$58:$CL$63,MATCH($D71,$CK$58:$CK$63))*$BR$58)) -> 0 | AU71: =IF($D71="",0,(($Q71+IF(OR($O71="x",$O71="xx"),1,0))*INDEX($CN$58:$CN$63,MATCH($D71,$CM$58:$CM$63))*$BR$58)) -> 0 | AV71: =IF($D71="",0,INDEX($CP$58:$CP$63,MATCH($D71,$CO$58:$CO$63))*$BR$58) -> 0 | AW71: =SUM(AK71:AV71) -> 0 | AX71: =IF($D71="",0,((IF(OR($R71="x",$R71="xx"),1,0))*INDEX($CR$58:$CR$63,MATCH($D71,$CQ$58:$CQ$63))*$BR$58)) -> 0 | AY71: =IF($D71="",0,((IF(OR($S71="x",$S71="xx"),1,0))*INDEX($CT$58:$CT$63,MATCH($D71,$CS$58:$CS$63))*$BR$58)) -> 0 | AZ71: =SUM(AX71:AY71) -> 0
B72: =B71+1 -> 16 | G72: =F72*D72 -> 0 | T72: =IF($L72="x",IF($D72="",0,INDEX($BE$58:$BE$63,MATCH($D72,$BD$58:$BD$63,1))),0) -> 0 | U72: =IF($I72="x",IF($D72="",0,INDEX($BG$58:$BG$63,MATCH($D72,$BF$58:$BF$63,1))),0) -> 0 | V72: =IF($J72="x",IF($D72="",0,INDEX($BI$58:$BI$63,MATCH($D72,$BH$58:$BH$63,1))),0) -> 0 | W72: =IF($K72="x",IF($D72="",0,INDEX($BK$58:$BK$63,MATCH($D72,$BJ$58:$BJ$63,1))),0) -> 0 | X72: =IF($D72="",0,IF(M72="x",$BM$60,0)) -> 0 | Y72: =IF($D72="",0,IF(N72="x",$BM$62,0)) -> 0 | Z72: =IF($O72="x",IF($D72="",0,$BL$58),0) -> 0 | AA72: =IF($P72="x",IF($D72="",0,IF($D72>4,$BL$60,0)),0) -> 0 | AB72: =IF($D72="",0,$Q72*$BL$62) -> 0 | AC72: =IF($D72="",0,(Q72+IF(OR(O72="x",44="xx"),1,0))*$BM$58) -> 0 | AD72: =G72+H72 -> 0 | AE72: =SUM(T72:AC72) -> 0 | AF72: =IF($E72="xx",(1600*$D72+$AE72),SUM(AD72:AE72))*$AF$55 -> 0 | AG72: =SUM(AD72:AF72) -> 0 | AH72: =IF($R72="x",IF($D72="",0,INDEX($BO$58:$BO$63,MATCH($D72,$BN$58:$BN$63,1))),0) -> 0 | AI72: =IF($S72="x",IF($D72="",0,INDEX($BQ$58:$BQ$63,MATCH($D72,$BP$58:$BP$63,1))),0) -> 0 | AJ72: =SUM(AH72:AI72) -> 0 | AK72: =IF($D72="",0,INDEX($BT$58:$BT$63,MATCH($D72,$BS$58:$BS$63))*$BR$58) -> 0 | AL72: =IF($D72="",0,IF(OR($I72="x",$I72="xx"),INDEX($BV$58:$BV$63,MATCH($D72,$BU$58:$BU$63))*$BR$58,0)) -> 0 | AM72: =IF($D72="",0,IF(OR($J72="x",$J72="xx"),INDEX($BX$58:$BX$63,MATCH($D72,$BW$58:$BW$63))*$BR$58,0)) -> 0 | AN72: =IF($D72="",0,IF(OR($K72="x",$K72="xx"),INDEX($BZ$58:$BZ$63,MATCH($D72,$BY$58:$BY$63))*$BR$58,0)) -> 0 | AO72: =IF($D72="",0,IF(OR($L72="x",$L72="xx"),INDEX($CB$58:$CB$63,MATCH($D72,$CA$58:$CA$63))*$BR$58,0)) -> 0 | AP72: =IF($D72="",0,IF(OR($M72="x",$M72="xx"),INDEX($CD$58:$CD$63,MATCH($D72,$CC$58:$CC$63))*$BR$58,0)) -> 0 | AQ72: =IF($D72="",0,IF(OR($N72="x",$N72="xx"),INDEX($CF$58:$CF$63,MATCH($D72,$CE$58:$CE$63))*$BR$58,0)) -> 0 | AR72: =IF($D72="",0,IF(OR($O72="x",$O72="xx"),INDEX($CH$58:$CH$63,MATCH($D72,$CG$58:$CG$63))*$BR$58,0)) -> 0 | AS72: =IF($D72="",0,IF(OR($P72="x",$P72="xx"),IF($D72>4,INDEX($CJ$58:$CJ$63,MATCH($D72,$CI$58:$CI$63))*$BR$58,0),0)) -> 0 | AT72: =IF($D72="",0,($Q72*INDEX($CL$58:$CL$63,MATCH($D72,$CK$58:$CK$63))*$BR$58)) -> 0 | AU72: =IF($D72="",0,(($Q72+IF(OR($O72="x",$O72="xx"),1,0))*INDEX($CN$58:$CN$63,MATCH($D72,$CM$58:$CM$63))*$BR$58)) -> 0 | AV72: =IF($D72="",0,INDEX($CP$58:$CP$63,MATCH($D72,$CO$58:$CO$63))*$BR$58) -> 0 | AW72: =SUM(AK72:AV72) -> 0 | AX72: =IF($D72="",0,((IF(OR($R72="x",$R72="xx"),1,0))*INDEX($CR$58:$CR$63,MATCH($D72,$CQ$58:$CQ$63))*$BR$58)) -> 0 | AY72: =IF($D72="",0,((IF(OR($S72="x",$S72="xx"),1,0))*INDEX($CT$58:$CT$63,MATCH($D72,$CS$58:$CS$63))*$BR$58)) -> 0 | AZ72: =SUM(AX72:AY72) -> 0
B73: =B72+1 -> 17 | G73: =F73*D73 -> 0 | T73: =IF($L73="x",IF($D73="",0,INDEX($BE$58:$BE$63,MATCH($D73,$BD$58:$BD$63,1))),0) -> 0 | U73: =IF($I73="x",IF($D73="",0,INDEX($BG$58:$BG$63,MATCH($D73,$BF$58:$BF$63,1))),0) -> 0 | V73: =IF($J73="x",IF($D73="",0,INDEX($BI$58:$BI$63,MATCH($D73,$BH$58:$BH$63,1))),0) -> 0 | W73: =IF($K73="x",IF($D73="",0,INDEX($BK$58:$BK$63,MATCH($D73,$BJ$58:$BJ$63,1))),0) -> 0 | X73: =IF($D73="",0,IF(M73="x",$BM$60,0)) -> 0 | Y73: =IF($D73="",0,IF(N73="x",$BM$62,0)) -> 0 | Z73: =IF($O73="x",IF($D73="",0,$BL$58),0) -> 0 | AA73: =IF($P73="x",IF($D73="",0,IF($D73>4,$BL$60,0)),0) -> 0 | AB73: =IF($D73="",0,$Q73*$BL$62) -> 0 | AC73: =IF($D73="",0,(Q73+IF(OR(O73="x",44="xx"),1,0))*$BM$58) -> 0 | AD73: =G73+H73 -> 0 | AE73: =SUM(T73:AC73) -> 0 | AF73: =IF($E73="xx",(1600*$D73+$AE73),SUM(AD73:AE73))*$AF$55 -> 0 | AG73: =SUM(AD73:AF73) -> 0 | AH73: =IF($R73="x",IF($D73="",0,INDEX($BO$58:$BO$63,MATCH($D73,$BN$58:$BN$63,1))),0) -> 0 | AI73: =IF($S73="x",IF($D73="",0,INDEX($BQ$58:$BQ$63,MATCH($D73,$BP$58:$BP$63,1))),0) -> 0 | AJ73: =SUM(AH73:AI73) -> 0 | AK73: =IF($D73="",0,INDEX($BT$58:$BT$63,MATCH($D73,$BS$58:$BS$63))*$BR$58) -> 0 | AL73: =IF($D73="",0,IF(OR($I73="x",$I73="xx"),INDEX($BV$58:$BV$63,MATCH($D73,$BU$58:$BU$63))*$BR$58,0)) -> 0 | AM73: =IF($D73="",0,IF(OR($J73="x",$J73="xx"),INDEX($BX$58:$BX$63,MATCH($D73,$BW$58:$BW$63))*$BR$58,0)) -> 0 | AN73: =IF($D73="",0,IF(OR($K73="x",$K73="xx"),INDEX($BZ$58:$BZ$63,MATCH($D73,$BY$58:$BY$63))*$BR$58,0)) -> 0 | AO73: =IF($D73="",0,IF(OR($L73="x",$L73="xx"),INDEX($CB$58:$CB$63,MATCH($D73,$CA$58:$CA$63))*$BR$58,0)) -> 0 | AP73: =IF($D73="",0,IF(OR($M73="x",$M73="xx"),INDEX($CD$58:$CD$63,MATCH($D73,$CC$58:$CC$63))*$BR$58,0)) -> 0 | AQ73: =IF($D73="",0,IF(OR($N73="x",$N73="xx"),INDEX($CF$58:$CF$63,MATCH($D73,$CE$58:$CE$63))*$BR$58,0)) -> 0 | AR73: =IF($D73="",0,IF(OR($O73="x",$O73="xx"),INDEX($CH$58:$CH$63,MATCH($D73,$CG$58:$CG$63))*$BR$58,0)) -> 0 | AS73: =IF($D73="",0,IF(OR($P73="x",$P73="xx"),IF($D73>4,INDEX($CJ$58:$CJ$63,MATCH($D73,$CI$58:$CI$63))*$BR$58,0),0)) -> 0 | AT73: =IF($D73="",0,($Q73*INDEX($CL$58:$CL$63,MATCH($D73,$CK$58:$CK$63))*$BR$58)) -> 0 | AU73: =IF($D73="",0,(($Q73+IF(OR($O73="x",$O73="xx"),1,0))*INDEX($CN$58:$CN$63,MATCH($D73,$CM$58:$CM$63))*$BR$58)) -> 0 | AV73: =IF($D73="",0,INDEX($CP$58:$CP$63,MATCH($D73,$CO$58:$CO$63))*$BR$58) -> 0 | AW73: =SUM(AK73:AV73) -> 0 | AX73: =IF($D73="",0,((IF(OR($R73="x",$R73="xx"),1,0))*INDEX($CR$58:$CR$63,MATCH($D73,$CQ$58:$CQ$63))*$BR$58)) -> 0 | AY73: =IF($D73="",0,((IF(OR($S73="x",$S73="xx"),1,0))*INDEX($CT$58:$CT$63,MATCH($D73,$CS$58:$CS$63))*$BR$58)) -> 0 | AZ73: =SUM(AX73:AY73) -> 0
B74: =B73+1 -> 18 | G74: =F74*D74 -> 0 | T74: =IF($L74="x",IF($D74="",0,INDEX($BE$58:$BE$63,MATCH($D74,$BD$58:$BD$63,1))),0) -> 0 | U74: =IF($I74="x",IF($D74="",0,INDEX($BG$58:$BG$63,MATCH($D74,$BF$58:$BF$63,1))),0) -> 0 | V74: =IF($J74="x",IF($D74="",0,INDEX($BI$58:$BI$63,MATCH($D74,$BH$58:$BH$63,1))),0) -> 0 | W74: =IF($K74="x",IF($D74="",0,INDEX($BK$58:$BK$63,MATCH($D74,$BJ$58:$BJ$63,1))),0) -> 0 | X74: =IF($D74="",0,IF(M74="x",$BM$60,0)) -> 0 | Y74: =IF($D74="",0,IF(N74="x",$BM$62,0)) -> 0 | Z74: =IF($O74="x",IF($D74="",0,$BL$58),0) -> 0 | AA74: =IF($P74="x",IF($D74="",0,IF($D74>4,$BL$60,0)),0) -> 0 | AB74: =IF($D74="",0,$Q74*$BL$62) -> 0 | AC74: =IF($D74="",0,(Q74+IF(OR(O74="x",44="xx"),1,0))*$BM$58) -> 0 | AD74: =G74+H74 -> 0 | AE74: =SUM(T74:AC74) -> 0 | AF74: =IF($E74="xx",(1600*$D74+$AE74),SUM(AD74:AE74))*$AF$55 -> 0 | AG74: =SUM(AD74:AF74) -> 0 | AH74: =IF($R74="x",IF($D74="",0,INDEX($BO$58:$BO$63,MATCH($D74,$BN$58:$BN$63,1))),0) -> 0 | AI74: =IF($S74="x",IF($D74="",0,INDEX($BQ$58:$BQ$63,MATCH($D74,$BP$58:$BP$63,1))),0) -> 0 | AJ74: =SUM(AH74:AI74) -> 0 | AK74: =IF($D74="",0,INDEX($BT$58:$BT$63,MATCH($D74,$BS$58:$BS$63))*$BR$58) -> 0 | AL74: =IF($D74="",0,IF(OR($I74="x",$I74="xx"),INDEX($BV$58:$BV$63,MATCH($D74,$BU$58:$BU$63))*$BR$58,0)) -> 0 | AM74: =IF($D74="",0,IF(OR($J74="x",$J74="xx"),INDEX($BX$58:$BX$63,MATCH($D74,$BW$58:$BW$63))*$BR$58,0)) -> 0 | AN74: =IF($D74="",0,IF(OR($K74="x",$K74="xx"),INDEX($BZ$58:$BZ$63,MATCH($D74,$BY$58:$BY$63))*$BR$58,0)) -> 0 | AO74: =IF($D74="",0,IF(OR($L74="x",$L74="xx"),INDEX($CB$58:$CB$63,MATCH($D74,$CA$58:$CA$63))*$BR$58,0)) -> 0 | AP74: =IF($D74="",0,IF(OR($M74="x",$M74="xx"),INDEX($CD$58:$CD$63,MATCH($D74,$CC$58:$CC$63))*$BR$58,0)) -> 0 | AQ74: =IF($D74="",0,IF(OR($N74="x",$N74="xx"),INDEX($CF$58:$CF$63,MATCH($D74,$CE$58:$CE$63))*$BR$58,0)) -> 0 | AR74: =IF($D74="",0,IF(OR($O74="x",$O74="xx"),INDEX($CH$58:$CH$63,MATCH($D74,$CG$58:$CG$63))*$BR$58,0)) -> 0 | AS74: =IF($D74="",0,IF(OR($P74="x",$P74="xx"),IF($D74>4,INDEX($CJ$58:$CJ$63,MATCH($D74,$CI$58:$CI$63))*$BR$58,0),0)) -> 0 | AT74: =IF($D74="",0,($Q74*INDEX($CL$58:$CL$63,MATCH($D74,$CK$58:$CK$63))*$BR$58)) -> 0 | AU74: =IF($D74="",0,(($Q74+IF(OR($O74="x",$O74="xx"),1,0))*INDEX($CN$58:$CN$63,MATCH($D74,$CM$58:$CM$63))*$BR$58)) -> 0 | AV74: =IF($D74="",0,INDEX($CP$58:$CP$63,MATCH($D74,$CO$58:$CO$63))*$BR$58) -> 0 | AW74: =SUM(AK74:AV74) -> 0 | AX74: =IF($D74="",0,((IF(OR($R74="x",$R74="xx"),1,0))*INDEX($CR$58:$CR$63,MATCH($D74,$CQ$58:$CQ$63))*$BR$58)) -> 0 | AY74: =IF($D74="",0,((IF(OR($S74="x",$S74="xx"),1,0))*INDEX($CT$58:$CT$63,MATCH($D74,$CS$58:$CS$63))*$BR$58)) -> 0 | AZ74: =SUM(AX74:AY74) -> 0
B75: =B74+1 -> 19 | G75: =F75*D75 -> 0 | T75: =IF($L75="x",IF($D75="",0,INDEX($BE$58:$BE$63,MATCH($D75,$BD$58:$BD$63,1))),0) -> 0 | U75: =IF($I75="x",IF($D75="",0,INDEX($BG$58:$BG$63,MATCH($D75,$BF$58:$BF$63,1))),0) -> 0 | V75: =IF($J75="x",IF($D75="",0,INDEX($BI$58:$BI$63,MATCH($D75,$BH$58:$BH$63,1))),0) -> 0 | W75: =IF($K75="x",IF($D75="",0,INDEX($BK$58:$BK$63,MATCH($D75,$BJ$58:$BJ$63,1))),0) -> 0 | X75: =IF($D75="",0,IF(M75="x",$BM$60,0)) -> 0 | Y75: =IF($D75="",0,IF(N75="x",$BM$62,0)) -> 0 | Z75: =IF($O75="x",IF($D75="",0,$BL$58),0) -> 0 | AA75: =IF($P75="x",IF($D75="",0,IF($D75>4,$BL$60,0)),0) -> 0 | AB75: =IF($D75="",0,$Q75*$BL$62) -> 0 | AC75: =IF($D75="",0,(Q75+IF(OR(O75="x",44="xx"),1,0))*$BM$58) -> 0 | AD75: =G75+H75 -> 0 | AE75: =SUM(T75:AC75) -> 0 | AF75: =IF($E75="xx",(1600*$D75+$AE75),SUM(AD75:AE75))*$AF$55 -> 0 | AG75: =SUM(AD75:AF75) -> 0 | AH75: =IF($R75="x",IF($D75="",0,INDEX($BO$58:$BO$63,MATCH($D75,$BN$58:$BN$63,1))),0) -> 0 | AI75: =IF($S75="x",IF($D75="",0,INDEX($BQ$58:$BQ$63,MATCH($D75,$BP$58:$BP$63,1))),0) -> 0 | AJ75: =SUM(AH75:AI75) -> 0 | AK75: =IF($D75="",0,INDEX($BT$58:$BT$63,MATCH($D75,$BS$58:$BS$63))*$BR$58) -> 0 | AL75: =IF($D75="",0,IF(OR($I75="x",$I75="xx"),INDEX($BV$58:$BV$63,MATCH($D75,$BU$58:$BU$63))*$BR$58,0)) -> 0 | AM75: =IF($D75="",0,IF(OR($J75="x",$J75="xx"),INDEX($BX$58:$BX$63,MATCH($D75,$BW$58:$BW$63))*$BR$58,0)) -> 0 | AN75: =IF($D75="",0,IF(OR($K75="x",$K75="xx"),INDEX($BZ$58:$BZ$63,MATCH($D75,$BY$58:$BY$63))*$BR$58,0)) -> 0 | AO75: =IF($D75="",0,IF(OR($L75="x",$L75="xx"),INDEX($CB$58:$CB$63,MATCH($D75,$CA$58:$CA$63))*$BR$58,0)) -> 0 | AP75: =IF($D75="",0,IF(OR($M75="x",$M75="xx"),INDEX($CD$58:$CD$63,MATCH($D75,$CC$58:$CC$63))*$BR$58,0)) -> 0 | AQ75: =IF($D75="",0,IF(OR($N75="x",$N75="xx"),INDEX($CF$58:$CF$63,MATCH($D75,$CE$58:$CE$63))*$BR$58,0)) -> 0 | AR75: =IF($D75="",0,IF(OR($O75="x",$O75="xx"),INDEX($CH$58:$CH$63,MATCH($D75,$CG$58:$CG$63))*$BR$58,0)) -> 0 | AS75: =IF($D75="",0,IF(OR($P75="x",$P75="xx"),IF($D75>4,INDEX($CJ$58:$CJ$63,MATCH($D75,$CI$58:$CI$63))*$BR$58,0),0)) -> 0 | AT75: =IF($D75="",0,($Q75*INDEX($CL$58:$CL$63,MATCH($D75,$CK$58:$CK$63))*$BR$58)) -> 0 | AU75: =IF($D75="",0,(($Q75+IF(OR($O75="x",$O75="xx"),1,0))*INDEX($CN$58:$CN$63,MATCH($D75,$CM$58:$CM$63))*$BR$58)) -> 0 | AV75: =IF($D75="",0,INDEX($CP$58:$CP$63,MATCH($D75,$CO$58:$CO$63))*$BR$58) -> 0 | AW75: =SUM(AK75:AV75) -> 0 | AX75: =IF($D75="",0,((IF(OR($R75="x",$R75="xx"),1,0))*INDEX($CR$58:$CR$63,MATCH($D75,$CQ$58:$CQ$63))*$BR$58)) -> 0 | AY75: =IF($D75="",0,((IF(OR($S75="x",$S75="xx"),1,0))*INDEX($CT$58:$CT$63,MATCH($D75,$CS$58:$CS$63))*$BR$58)) -> 0 | AZ75: =SUM(AX75:AY75) -> 0
... B81: =B80+1 -> 25 | G81: =F81*D81 -> 0 | T81: =IF($L81="x",IF($D81="",0,INDEX($BE$58:$BE$63,MATCH($D81,$BD$58:$BD$63,1))),0) -> 0 | U81: =IF($I81="x",IF($D81="",0,INDEX($BG$58:$BG$63,MATCH($D81,$BF$58:$BF$63,1))),0) -> 0 | V81: =IF($J81="x",IF($D81="",0,INDEX($BI$58:$BI$63,MATCH($D81,$BH$58:$BH$63,1))),0) -> 0 | W81: =IF($K81="x",IF($D81="",0,INDEX($BK$58:$BK$63,MATCH($D81,$BJ$58:$BJ$63,1))),0) -> 0 | X81: =IF($D81="",0,IF(M81="x",$BM$60,0)) -> 0 | Y81: =IF($D81="",0,IF(N81="x",$BM$62,0)) -> 0 | Z81: =IF($O81="x",IF($D81="",0,$BL$58),0) -> 0 | AA81: =IF($P81="x",IF($D81="",0,IF($D81>4,$BL$60,0)),0) -> 0 | AB81: =IF($D81="",0,$Q81*$BL$62) -> 0 | AC81: =IF($D81="",0,(Q81+IF(OR(O81="x",44="xx"),1,0))*$BM$58) -> 0 | AD81: =G81+H81 -> 0 | AE81: =SUM(T81:AC81) -> 0 | AF81: =IF($E81="xx",(1600*$D81+$AE81),SUM(AD81:AE81))*$AF$55 -> 0 | AG81: =SUM(AD81:AF81) -> 0 | AH81: =IF($R81="x",IF($D81="",0,INDEX($BO$58:$BO$63,MATCH($D81,$BN$58:$BN$63,1))),0) -> 0 | AI81: =IF($S81="x",IF($D81="",0,INDEX($BQ$58:$BQ$63,MATCH($D81,$BP$58:$BP$63,1))),0) -> 0 | AJ81: =SUM(AH81:AI81) -> 0 | AK81: =IF($D81="",0,INDEX($BT$58:$BT$63,MATCH($D81,$BS$58:$BS$63))*$BR$58) -> 0 | AL81: =IF($D81="",0,IF(OR($I81="x",$I81="xx"),INDEX($BV$58:$BV$63,MATCH($D81,$BU$58:$BU$63))*$BR$58,0)) -> 0 | AM81: =IF($D81="",0,IF(OR($J81="x",$J81="xx"),INDEX($BX$58:$BX$63,MATCH($D81,$BW$58:$BW$63))*$BR$58,0)) -> 0 | AN81: =IF($D81="",0,IF(OR($K81="x",$K81="xx"),INDEX($BZ$58:$BZ$63,MATCH($D81,$BY$58:$BY$63))*$BR$58,0)) -> 0 | AO81: =IF($D81="",0,IF(OR($L81="x",$L81="xx"),INDEX($CB$58:$CB$63,MATCH($D81,$CA$58:$CA$63))*$BR$58,0)) -> 0 | AP81: =IF($D81="",0,IF(OR($M81="x",$M81="xx"),INDEX($CD$58:$CD$63,MATCH($D81,$CC$58:$CC$63))*$BR$58,0)) -> 0 | AQ81: =IF($D81="",0,IF(OR($N81="x",$N81="xx"),INDEX($CF$58:$CF$63,MATCH($D81,$CE$58:$CE$63))*$BR$58,0)) -> 0 | AR81: =IF($D81="",0,IF(OR($O81="x",$O81="xx"),INDEX($CH$58:$CH$63,MATCH($D81,$CG$58:$CG$63))*$BR$58,0)) -> 0 | AS81: =IF($D81="",0,IF(OR($P81="x",$P81="xx"),IF($D81>4,INDEX($CJ$58:$CJ$63,MATCH($D81,$CI$58:$CI$63))*$BR$58,0),0)) -> 0 | AT81: =IF($D81="",0,($Q81*INDEX($CL$58:$CL$63,MATCH($D81,$CK$58:$CK$63))*$BR$58)) -> 0 | AU81: =IF($D81="",0,(($Q81+IF(OR($O81="x",$O81="xx"),1,0))*INDEX($CN$58:$CN$63,MATCH($D81,$CM$58:$CM$63))*$BR$58)) -> 0 | AV81: =IF($D81="",0,INDEX($CP$58:$CP$63,MATCH($D81,$CO$58:$CO$63))*$BR$58) -> 0 | AW81: =SUM(AK81:AV81) -> 0 | AX81: =IF($D81="",0,((IF(OR($R81="x",$R81="xx"),1,0))*INDEX($CR$58:$CR$63,MATCH($D81,$CQ$58:$CQ$63))*$BR$58)) -> 0 | AY81: =IF($D81="",0,((IF(OR($S81="x",$S81="xx"),1,0))*INDEX($CT$58:$CT$63,MATCH($D81,$CS$58:$CS$63))*$BR$58)) -> 0 | AZ81: =SUM(AX81:AY81) -> 0
B82: Totals | D82: =SUM(D57:D81) -> 0 | G82: =SUM(G57:G81) -> 0 | H82: =SUM(H57:H81) -> 0 | T82: =SUM(T57:T81) -> 0 | U82: =SUM(U57:U81) -> 0 | V82: =SUM(V57:V81) -> 0 | W82: =SUM(W57:W81) -> 0 | X82: =SUM(X57:X81) -> 0 | Y82: =SUM(Y57:Y81) -> 0 | Z82: =SUM(Z57:Z81) -> 0 | AA82: =SUM(AA57:AA81) -> 0 | ... AZ82: =SUM(AZ57:AZ81) -> 0
E83: vvvvvvvvvv Notes: Selecting "xx" means the owner is providing the equipment | I83: Notes: "x" implies that we need to include an estimate for this item. If the equipment provider has included the item in their package proporsal select "xx". Also use "xx" if the owner is providing but we have to install
B84: Split Systems | F84: Cost Calculator (Option) | H84: Supplier Quote (Option) | V84: DUCT | W84: Materials ----------------------------------------------------------------------------------------------------------------------------------------------------------------------------------------------------------------------------------------------------------------------------------------------------------------------------------------------------------------------------------------------------------------------------- | AM84: Misc: | AN84: 0.03 | AP84: Duct Materials------------- | AQ84: Labor----------------------------------------------------------------------------------------------------------------------------------------------------------------------------------------------------------------------------------------------------------------------------------------------------------------------------------------------------------------------------------------------------------------------------- | BE84: Duct Labor------------------ | BH84: Materials Cost | CE84: Labor Cost | DL84: Duct Labor
B85: Unit | C85: Name | D85: Cool (Tons) | E85: Owner Provided ("xx") | F85: Base Cost ($/ton) | G85: Est. Equipment Cost ($) | H85: Equipment Cost ($) | I85: Condenser Rails ("x/xx") | J85: Drain Pan ("x/xx") | K85: CU L (<100 Ft) ("x/xx") | L85: CU L (>=100 Ft) ("x/xx") | M85: CU Roll (<100 Ft) ("x/xx") | N85: CU Roll (>=100 Ft) ("x/xx") | O85: OA Damper ("x/xx") | P85: Float Switch ("x/xx") | Q85: PVC Cond. ("x/xx") | R85: CU Cond. ("x/xx") | S85: Thermostat ("x/xx") | T85: Smoke Detectors ("x/xx") | U85: Sensors (CO/Temp) (Qty) | V85: Connections ("x/xx") | W85: Condenser Rails ($) | X85: Drain Pan ($) | Y85: Copper L (<100 Ft) | Z85: Copper L (>=100 Ft) | AA85: Copper Roll (<100 Ft) | AB85: Copper Roll (>=100 Ft) | AC85: Refrigerant Charge ($) | AD85: OA Damper ($) | AE85: Float Switch ($) | AF85: PVC Cond. ($) | AG85: CU Cond. ($) | AH85: Thermostat ($) | AI85: Smoke Detectors ($) | AJ85: Sensors (CO/Temp) ($) | AK85: Stat Wire (CO/Temp) ($) | AL85: Base + Quoted Price ($) | AM85: Accessories ($) | AN85: Misc/Consumables | AO85: Total Materials | AP85: Transitions ($) | AQ85: Base Equipment ($) | AR85: Condenser Rails ($) | AS85: Drain Pan ($) | AT85: Copper ($) | AU85: OA Damper ($) | AV85: Float Switch ($) | AW85: PVC Cond. ($) | AX85: CU Cond. ($) | AY85: Thermostat ($) | AZ85: Smoke Detectors ($) | BA85: Sensors (CO/Temp) ($) | BB85: Stat Wire (CO/Temp) ($) | BC85: Startup & Testing | BD85: Labor Total ($) | BE85: Transitions ($) | BF85: Notes | BI85: Condenser Rails | BK85: Drain Pan | BM85: Copper L (<100 Ft) | BO85: Copper L (>100 Ft) | BQ85: Copper Roll (<100 Ft) | BS85: Copper Roll (>100 Ft) | BU85: Refrigerant Supplemental Charge | BX85: Fresh Air Damper | CC85: Duct Transitions (Supply & Return) | CF85: Base Unit | CH85: Condenser Rails | CJ85: Drain Pan | CL85: Copper L (< 100') | CN85: Copper L (>= 100') | CP85: Copper Roll (< 100') | CR85: Copper Roll (>= 100') | CT85: OA Damper | CV85: Float Switch | CX85: PVC Condensate | CZ85: CU Condensate | DB85: Thermostat | DD85: Smoke Detectors | DF85: Sensors | DH85: Stat Wire | DJ85: Start Up | DL85: Duct Transitions
B86: 1 | G86: =F86*D86 -> 0 | W86: =IF($I86="x",IF($D86="",0,INDEX($BJ$87:$BJ$92,MATCH($D86,$BI$87:$BI$92,1))),0) -> 0 | X86: =IF($J86="x",IF($D86="",0,INDEX($BL$87:$BL$92,MATCH($D86,$BK$87:$BK$92,1))),0) -> 0 | Y86: =IF($K86="x",IF($D86="",0,INDEX($BN$87:$BN$92,MATCH($D86,$BM$87:$BM$92,1))),0) -> 0 | Z86: =IF($L86="x",IF($D86="",0,INDEX($BP$87:$BP$92,MATCH($D86,$BO$87:$BO$92,1))),0) -> 0 | AA86: =IF($M86="x",IF($D86="",0,INDEX($BR$87:$BR$92,MATCH($D86,$BQ$87:$BQ$92,1))),0) -> 0 | AB86: =IF($N86="x",IF($D86="",0,INDEX($BT$87:$BT$92,MATCH($D86,$BS$87:$BS$92,1))),0) -> 0 | AC86: =IF(OR($K86="x",$M86="x"),IF($D86="",0,INDEX($BV$87:$BV$92,MATCH($D86,$BU$87:$BU$92,1))),0)+IF(OR($L86="x",$N86="x"),IF($D86="",0,INDEX($BW$87:$BW$92,MATCH($D86,$BU$87:$BU$92,1))),0) -> 0 | AD86: =IF($O86="x",IF($D86="",0,INDEX($BY$87:$BY$92,MATCH($D86,$BX$87:$BX$92,1))),0) -> 0 | AE86: =IF($P86="x",IF($D86="",0,$CB$87),0) -> 0 | AF86: =IF($D86="",0,IF(Q86="x",$CA$89,0)) -> 0 | AG86: =IF($D86="",0,IF(R86="x",$CA$91,0)) -> 0 | AH86: =IF($S86="x",IF($D86="",0,$BZ$87),0) -> 0 | AI86: =IF($T86="x",IF($D86="",0,IF($D86>4,$BZ$89,0)),0) -> 0 | AJ86: =IF($D86="",0,$U86*$BZ$91) -> 0 | AK86: =IF($D86="",0,(U86+IF(AH86>0,1,0))*$CA$87) -> 0 | AL86: =G86+H86 -> 0 | AM86: =SUM(W86:AK86) -> 0 | AN86: =IF($E86="xx",(1600*$D86+$AM86),SUM(AL86:AM86))*$AN$84 -> 0 | AO86: =SUM(AL86:AN86) -> 0 | AP86: =IF($V86="x",IF($D86="",0,INDEX($CD$87:$CD$92,MATCH($D86,$CC$87:$CC$92,1))),0) -> 0 | AQ86: =IF($D86="",0,INDEX($CG$87:$CG$92,MATCH($D86,$CF$87:$CF$92))*$CE$87) -> 0 | AR86: =IF($D86="",0,IF(OR($I86="x",$I86="xx"),INDEX($CI$87:$CI$92,MATCH($D86,$CH$87:$CH$92))*$CE$87,0)) -> 0 | AS86: =IF($D86="",0,IF(OR($J86="x",$J86="xx"),INDEX($CK$87:$CK$92,MATCH($D86,$CJ$87:$CJ$92))*$CE$87,0)) -> 0 | AT86: =IF($D86="",0,IF(OR($M86="x",$M86="xx"),INDEX($CQ$87:$CQ$92,MATCH($D86,$CP$87:$CP$92))*$CE$87,0))+IF($D86="",0,IF(OR($N86="x",$N86="xx"),INDEX($CS$87:$CS$92,MATCH($D86,$CR$87:$CR$92))*$CE$87,0))+IF($D86="",0,IF(OR($K86="x",$K86="xx"),INDEX($CM$87:$CM$92,MATCH($D86,$CL$87:$CL$92))*$CE$87,0))+IF($D86="",0,IF(OR($L86="x",$L86="xx"),INDEX($CO$87:$CO$92,MATCH($D86,$CN$87:$CN$92))*$CE$87,0)) -> 0 | AU86: =IF($D86="",0,IF(OR($O86="x",$O86="xx"),INDEX($CU$87:$CU$92,MATCH($D86,$CT$87:$CT$92))*$CE$87,0)) -> 0 | AV86: =IF($D86="",0,IF(OR($P86="x",$P86="xx"),INDEX($CW$87:$CW$92,MATCH($D86,$CV$87:$CV$92))*$CE$87,0)) -> 0 | AW86: =IF($D86="",0,IF(OR($Q86="x",$Q86="xx"),INDEX($CY$87:$CY$92,MATCH($D86,$CX$87:$CX$92))*$CE$87,0)) -> 0 | AX86: =IF($D86="",0,IF(OR($R86="x",$R86="xx"),INDEX($DA$87:$DA$92,MATCH($D86,$CZ$87:$CZ$92))*$CE$87,0)) -> 0 | AY86: =IF($D86="",0,IF(OR($S86="x",$S86="xx"),INDEX($DC$87:$DC$92,MATCH($D86,$DB$87:$DB$92))*$CE$87,0)) -> 0 | AZ86: =IF($D86="",0,IF(OR($T86="x",$T86="xx"),IF($D86>4,INDEX($DE$87:$DE$92,MATCH($D86,$DD$87:$DD$92))*$CE$87,0),0)) -> 0 | BA86: =IF($D86="",0,($U86*INDEX($DG$87:$DG$92,MATCH($D86,$DF$87:$DF$92))*$CE$87)) -> 0 | BB86: =IF($D86="",0,(($U86+IF(OR($S86="x",$S86="xx"),1,0))*INDEX($DI$87:$DI$92,MATCH($D86,$DH$87:$DH$92))*$CE$87)) -> 0 | BC86: =IF($D86="",0,INDEX($DK$87:$DK$92,MATCH($D86,$DJ$87:$DJ$92))*$CE$87) -> 0 | BD86: =SUM(AQ86:BC86) -> 0 | BE86: =IF($D86="",0,((IF(OR($V86="x",$V86="xx"),1,0))*INDEX($DM$87:$DM$92,MATCH($D86,$DL$87:$DL$92))*$BR$58)) -> 0 | BH86: Selection | BI86: Size | BJ86: Cost | BK86: Size | BL86: Cost | BM86: Size | BN86: Cost | BO86: Size | BP86: Cost | BQ86: Size | BR86: Cost | BS86: Size | BT86: Cost | BU86: Size | BV86: <100 | BW86: >=100 | BX86: Size | BY86: Cost | BZ86: Thermostat | CA86: Stat Wire/Unit | CB86: Float Switch | CC86: Size | CD86: Cost | CE86: Tech Rate ($/hr) | CF86: Size | CG86: Hours | CH86: Size | CI86: Hours | CJ86: Size | CK86: Hours | CL86: Size | CM86: Hours | CN86: Size | CO86: Hours | CP86: Size | CQ86: Hours | CR86: Size | CS86: Hours | CT86: Size | CU86: Hours | CV86: Size | CW86: Hours | CX86: Size | CY86: Hours | CZ86: Size | DA86: Hours | DB86: Size | DC86: Hours | DD86: Size | DE86: Hours | DF86: Size | DG86: Hours | DH86: Size | DI86: Hours | DJ86: Size | DK86: Hours | DL86: Size | DM86: Hours
B87: =B86+1 -> 2 | G87: =F87*D87 -> 0 | W87: =IF($I87="x",IF($D87="",0,INDEX($BJ$87:$BJ$92,MATCH($D87,$BI$87:$BI$92,1))),0) -> 0 | X87: =IF($J87="x",IF($D87="",0,INDEX($BL$87:$BL$92,MATCH($D87,$BK$87:$BK$92,1))),0) -> 0 | Y87: =IF($K87="x",IF($D87="",0,INDEX($BN$87:$BN$92,MATCH($D87,$BM$87:$BM$92,1))),0) -> 0 | Z87: =IF($L87="x",IF($D87="",0,INDEX($BP$87:$BP$92,MATCH($D87,$BO$87:$BO$92,1))),0) -> 0 | AA87: =IF($M87="x",IF($D87="",0,INDEX($BR$87:$BR$92,MATCH($D87,$BQ$87:$BQ$92,1))),0) -> 0 | AB87: =IF($N87="x",IF($D87="",0,INDEX($BT$87:$BT$92,MATCH($D87,$BS$87:$BS$92,1))),0) -> 0 | AC87: =IF(OR($K87="x",$M87="x"),IF($D87="",0,INDEX($BV$87:$BV$92,MATCH($D87,$BU$87:$BU$92,1))),0)+IF(OR($L87="x",$N87="x"),IF($D87="",0,INDEX($BW$87:$BW$92,MATCH($D87,$BU$87:$BU$92,1))),0) -> 0 | AD87: =IF($O87="x",IF($D87="",0,INDEX($BY$87:$BY$92,MATCH($D87,$BX$87:$BX$92,1))),0) -> 0 | AE87: =IF($P87="x",IF($D87="",0,$CB$87),0) -> 0 | AF87: =IF($D87="",0,IF(Q87="x",$CA$89,0)) -> 0 | AG87: =IF($D87="",0,IF(R87="x",$CA$91,0)) -> 0 | AH87: =IF($S87="x",IF($D87="",0,$BZ$87),0) -> 0 | AI87: =IF($T87="x",IF($D87="",0,IF($D87>4,$BZ$89,0)),0) -> 0 | AJ87: =IF($D87="",0,$U87*$BZ$91) -> 0 | AK87: =IF($D87="",0,(U87+IF(AH87>0,1,0))*$CA$87) -> 0 | AL87: =G87+H87 -> 0 | AM87: =SUM(W87:AK87) -> 0 | AN87: =IF($E87="xx",(1600*$D87+$AM87),SUM(AL87:AM87))*$AN$84 -> 0 | AO87: =SUM(AL87:AN87) -> 0 | AP87: =IF($V87="x",IF($D87="",0,INDEX($CD$87:$CD$92,MATCH($D87,$CC$87:$CC$92,1))),0) -> 0 | AQ87: =IF($D87="",0,INDEX($CG$87:$CG$92,MATCH($D87,$CF$87:$CF$92))*$CE$87) -> 0 | AR87: =IF($D87="",0,IF(OR($I87="x",$I87="xx"),INDEX($CI$87:$CI$92,MATCH($D87,$CH$87:$CH$92))*$CE$87,0)) -> 0 | AS87: =IF($D87="",0,IF(OR($J87="x",$J87="xx"),INDEX($CK$87:$CK$92,MATCH($D87,$CJ$87:$CJ$92))*$CE$87,0)) -> 0 | AT87: =IF($D87="",0,IF(OR($M87="x",$M87="xx"),INDEX($CQ$87:$CQ$92,MATCH($D87,$CP$87:$CP$92))*$CE$87,0))+IF($D87="",0,IF(OR($N87="x",$N87="xx"),INDEX($CS$87:$CS$92,MATCH($D87,$CR$87:$CR$92))*$CE$87,0))+IF($D87="",0,IF(OR($K87="x",$K87="xx"),INDEX($CM$87:$CM$92,MATCH($D87,$CL$87:$CL$92))*$CE$87,0))+IF($D87="",0,IF(OR($L87="x",$L87="xx"),INDEX($CO$87:$CO$92,MATCH($D87,$CN$87:$CN$92))*$CE$87,0)) -> 0 | AU87: =IF($D87="",0,IF(OR($O87="x",$O87="xx"),INDEX($CU$87:$CU$92,MATCH($D87,$CT$87:$CT$92))*$CE$87,0)) -> 0 | AV87: =IF($D87="",0,IF(OR($P87="x",$P87="xx"),INDEX($CW$87:$CW$92,MATCH($D87,$CV$87:$CV$92))*$CE$87,0)) -> 0 | AW87: =IF($D87="",0,IF(OR($Q87="x",$Q87="xx"),INDEX($CY$87:$CY$92,MATCH($D87,$CX$87:$CX$92))*$CE$87,0)) -> 0 | AX87: =IF($D87="",0,IF(OR($R87="x",$R87="xx"),INDEX($DA$87:$DA$92,MATCH($D87,$CZ$87:$CZ$92))*$CE$87,0)) -> 0 | AY87: =IF($D87="",0,IF(OR($S87="x",$S87="xx"),INDEX($DC$87:$DC$92,MATCH($D87,$DB$87:$DB$92))*$CE$87,0)) -> 0 | AZ87: =IF($D87="",0,IF(OR($T87="x",$T87="xx"),IF($D87>4,INDEX($DE$87:$DE$92,MATCH($D87,$DD$87:$DD$92))*$CE$87,0),0)) -> 0 | BA87: =IF($D87="",0,($U87*INDEX($DG$87:$DG$92,MATCH($D87,$DF$87:$DF$92))*$CE$87)) -> 0 | BB87: =IF($D87="",0,(($U87+IF(OR($S87="x",$S87="xx"),1,0))*INDEX($DI$87:$DI$92,MATCH($D87,$DH$87:$DH$92))*$CE$87)) -> 0 | BC87: =IF($D87="",0,INDEX($DK$87:$DK$92,MATCH($D87,$DJ$87:$DJ$92))*$CE$87) -> 0 | BD87: =SUM(AQ87:BC87) -> 0 | BE87: =IF($D87="",0,((IF(OR($V87="x",$V87="xx"),1,0))*INDEX($DM$87:$DM$92,MATCH($D87,$DL$87:$DL$92))*$BR$58)) -> 0 | BH87: x | BI87: 0 | BJ87: 350 | BK87: 0 | BL87: 70 | BM87: 0 | BN87: =BR87*2 -> 1128 | BO87: 0 | BP87: =BN87*1.5 -> 1692 | BQ87: 0 | BR87: =3.5*80+2.5*80+6*14 -> 564 | BS87: 0 | BT87: =(3.5*80+2.5*80+6*14)*1.5 -> 846 | BU87: 0 | BV87: =8*35 -> 280 | BW87: =8*35*1.5 -> 420 | BX87: 0 | BY87: 180 | BZ87: 160 | CA87: =90/2 -> 45 | CB87: 16 | CC87: 0 | CD87: 200 | CE87: 25 | CF87: 0 | CG87: 24 | CH87: 0 | CI87: 6 | CJ87: 0 | CK87: 4 | CL87: 0 | CM87: =CQ87*3 -> 24 | CN87: 0 | CO87: =CM87*1.5 -> 36 | CP87: 0 | CQ87: 8 | CR87: 0 | CS87: 12 | CT87: 0 | CU87: 6 | CV87: 0 | CW87: 1 | CX87: 0 | CY87: 5 | CZ87: 0 | DA87: 14 | DB87: 0 | DC87: 2 | DD87: 0 | DE87: 3 | DF87: 0 | DG87: 2 | DH87: 0 | DI87: 3 | DJ87: 0 | DK87: 6 | DL87: 0 | DM87: 4
B88: =B87+1 -> 3 | G88: =F88*D88 -> 0 | W88: =IF($I88="x",IF($D88="",0,INDEX($BJ$87:$BJ$92,MATCH($D88,$BI$87:$BI$92,1))),0) -> 0 | X88: =IF($J88="x",IF($D88="",0,INDEX($BL$87:$BL$92,MATCH($D88,$BK$87:$BK$92,1))),0) -> 0 | Y88: =IF($K88="x",IF($D88="",0,INDEX($BN$87:$BN$92,MATCH($D88,$BM$87:$BM$92,1))),0) -> 0 | Z88: =IF($L88="x",IF($D88="",0,INDEX($BP$87:$BP$92,MATCH($D88,$BO$87:$BO$92,1))),0) -> 0 | AA88: =IF($M88="x",IF($D88="",0,INDEX($BR$87:$BR$92,MATCH($D88,$BQ$87:$BQ$92,1))),0) -> 0 | AB88: =IF($N88="x",IF($D88="",0,INDEX($BT$87:$BT$92,MATCH($D88,$BS$87:$BS$92,1))),0) -> 0 | AC88: =IF(OR($K88="x",$M88="x"),IF($D88="",0,INDEX($BV$87:$BV$92,MATCH($D88,$BU$87:$BU$92,1))),0)+IF(OR($L88="x",$N88="x"),IF($D88="",0,INDEX($BW$87:$BW$92,MATCH($D88,$BU$87:$BU$92,1))),0) -> 0 | AD88: =IF($O88="x",IF($D88="",0,INDEX($BY$87:$BY$92,MATCH($D88,$BX$87:$BX$92,1))),0) -> 0 | AE88: =IF($P88="x",IF($D88="",0,$CB$87),0) -> 0 | AF88: =IF($D88="",0,IF(Q88="x",$CA$89,0)) -> 0 | AG88: =IF($D88="",0,IF(R88="x",$CA$91,0)) -> 0 | AH88: =IF($S88="x",IF($D88="",0,$BZ$87),0) -> 0 | AI88: =IF($T88="x",IF($D88="",0,IF($D88>4,$BZ$89,0)),0) -> 0 | AJ88: =IF($D88="",0,$U88*$BZ$91) -> 0 | AK88: =IF($D88="",0,(U88+IF(AH88>0,1,0))*$CA$87) -> 0 | AL88: =G88+H88 -> 0 | AM88: =SUM(W88:AK88) -> 0 | AN88: =IF($E88="xx",(1600*$D88+$AM88),SUM(AL88:AM88))*$AN$84 -> 0 | AO88: =SUM(AL88:AN88) -> 0 | AP88: =IF($V88="x",IF($D88="",0,INDEX($CD$87:$CD$92,MATCH($D88,$CC$87:$CC$92,1))),0) -> 0 | AQ88: =IF($D88="",0,INDEX($CG$87:$CG$92,MATCH($D88,$CF$87:$CF$92))*$CE$87) -> 0 | AR88: =IF($D88="",0,IF(OR($I88="x",$I88="xx"),INDEX($CI$87:$CI$92,MATCH($D88,$CH$87:$CH$92))*$CE$87,0)) -> 0 | AS88: =IF($D88="",0,IF(OR($J88="x",$J88="xx"),INDEX($CK$87:$CK$92,MATCH($D88,$CJ$87:$CJ$92))*$CE$87,0)) -> 0 | AT88: =IF($D88="",0,IF(OR($M88="x",$M88="xx"),INDEX($CQ$87:$CQ$92,MATCH($D88,$CP$87:$CP$92))*$CE$87,0))+IF($D88="",0,IF(OR($N88="x",$N88="xx"),INDEX($CS$87:$CS$92,MATCH($D88,$CR$87:$CR$92))*$CE$87,0))+IF($D88="",0,IF(OR($K88="x",$K88="xx"),INDEX($CM$87:$CM$92,MATCH($D88,$CL$87:$CL$92))*$CE$87,0))+IF($D88="",0,IF(OR($L88="x",$L88="xx"),INDEX($CO$87:$CO$92,MATCH($D88,$CN$87:$CN$92))*$CE$87,0)) -> 0 | AU88: =IF($D88="",0,IF(OR($O88="x",$O88="xx"),INDEX($CU$87:$CU$92,MATCH($D88,$CT$87:$CT$92))*$CE$87,0)) -> 0 | AV88: =IF($D88="",0,IF(OR($P88="x",$P88="xx"),INDEX($CW$87:$CW$92,MATCH($D88,$CV$87:$CV$92))*$CE$87,0)) -> 0 | AW88: =IF($D88="",0,IF(OR($Q88="x",$Q88="xx"),INDEX($CY$87:$CY$92,MATCH($D88,$CX$87:$CX$92))*$CE$87,0)) -> 0 | AX88: =IF($D88="",0,IF(OR($R88="x",$R88="xx"),INDEX($DA$87:$DA$92,MATCH($D88,$CZ$87:$CZ$92))*$CE$87,0)) -> 0 | AY88: =IF($D88="",0,IF(OR($S88="x",$S88="xx"),INDEX($DC$87:$DC$92,MATCH($D88,$DB$87:$DB$92))*$CE$87,0)) -> 0 | AZ88: =IF($D88="",0,IF(OR($T88="x",$T88="xx"),IF($D88>4,INDEX($DE$87:$DE$92,MATCH($D88,$DD$87:$DD$92))*$CE$87,0),0)) -> 0 | BA88: =IF($D88="",0,($U88*INDEX($DG$87:$DG$92,MATCH($D88,$DF$87:$DF$92))*$CE$87)) -> 0 | BB88: =IF($D88="",0,(($U88+IF(OR($S88="x",$S88="xx"),1,0))*INDEX($DI$87:$DI$92,MATCH($D88,$DH$87:$DH$92))*$CE$87)) -> 0 | BC88: =IF($D88="",0,INDEX($DK$87:$DK$92,MATCH($D88,$DJ$87:$DJ$92))*$CE$87) -> 0 | BD88: =SUM(AQ88:BC88) -> 0 | BE88: =IF($D88="",0,((IF(OR($V88="x",$V88="xx"),1,0))*INDEX($DM$87:$DM$92,MATCH($D88,$DL$87:$DL$92))*$BR$58)) -> 0 | BH88: xx | BI88: 5 | BJ88: 350 | BK88: 5 | BL88: 80 | BM88: 5 | BN88: =BR88*2 -> 1208 | BO88: 5 | BP88: =BN88*1.5 -> 1812 | BQ88: 5 | BR88: =4*80+2.5*80+6*14 -> 604 | BS88: 5 | BT88: =(4*80+2.5*80+6*14)*1.5 -> 906 | BU88: 5 | BV88: =8*35 -> 280 | BW88: =8*35*0.5 -> 140 | BX88: 5 | BY88: 225 | BZ88: Smoke Detector | CA88: PVC Cond | CC88: 5 | CD88: 200 | CF88: 5 | CG88: 24 | CH88: 5 | CI88: 6 | CJ88: 5 | CK88: 4 | CL88: 5 | CM88: =CQ88*3 -> 24 | CN88: 5 | CO88: =CM88*1.5 -> 36 | CP88: 5 | CQ88: 8 | CR88: 5 | CS88: 12 | CT88: 5 | CU88: 6 | CV88: 5 | CW88: 1 | CX88: 5 | CY88: 5 | CZ88: 5 | DA88: 14 | DB88: 5 | DC88: 2 | DD88: 5 | DE88: 3 | DF88: 5 | DG88: 2 | DH88: 5 | DI88: 3 | DJ88: 5 | DK88: 6 | DL88: 5 | DM88: 4
B89: =B88+1 -> 4 | G89: =F89*D89 -> 0 | W89: =IF($I89="x",IF($D89="",0,INDEX($BJ$87:$BJ$92,MATCH($D89,$BI$87:$BI$92,1))),0) -> 0 | X89: =IF($J89="x",IF($D89="",0,INDEX($BL$87:$BL$92,MATCH($D89,$BK$87:$BK$92,1))),0) -> 0 | Y89: =IF($K89="x",IF($D89="",0,INDEX($BN$87:$BN$92,MATCH($D89,$BM$87:$BM$92,1))),0) -> 0 | Z89: =IF($L89="x",IF($D89="",0,INDEX($BP$87:$BP$92,MATCH($D89,$BO$87:$BO$92,1))),0) -> 0 | AA89: =IF($M89="x",IF($D89="",0,INDEX($BR$87:$BR$92,MATCH($D89,$BQ$87:$BQ$92,1))),0) -> 0 | AB89: =IF($N89="x",IF($D89="",0,INDEX($BT$87:$BT$92,MATCH($D89,$BS$87:$BS$92,1))),0) -> 0 | AC89: =IF(OR($K89="x",$M89="x"),IF($D89="",0,INDEX($BV$87:$BV$92,MATCH($D89,$BU$87:$BU$92,1))),0)+IF(OR($L89="x",$N89="x"),IF($D89="",0,INDEX($BW$87:$BW$92,MATCH($D89,$BU$87:$BU$92,1))),0) -> 0 | AD89: =IF($O89="x",IF($D89="",0,INDEX($BY$87:$BY$92,MATCH($D89,$BX$87:$BX$92,1))),0) -> 0 | AE89: =IF($P89="x",IF($D89="",0,$CB$87),0) -> 0 | AF89: =IF($D89="",0,IF(Q89="x",$CA$89,0)) -> 0 | AG89: =IF($D89="",0,IF(R89="x",$CA$91,0)) -> 0 | AH89: =IF($S89="x",IF($D89="",0,$BZ$87),0) -> 0 | AI89: =IF($T89="x",IF($D89="",0,IF($D89>4,$BZ$89,0)),0) -> 0 | AJ89: =IF($D89="",0,$U89*$BZ$91) -> 0 | AK89: =IF($D89="",0,(U89+IF(AH89>0,1,0))*$CA$87) -> 0 | AL89: =G89+H89 -> 0 | AM89: =SUM(W89:AK89) -> 0 | AN89: =IF($E89="xx",(1600*$D89+$AM89),SUM(AL89:AM89))*$AN$84 -> 0 | AO89: =SUM(AL89:AN89) -> 0 | AP89: =IF($V89="x",IF($D89="",0,INDEX($CD$87:$CD$92,MATCH($D89,$CC$87:$CC$92,1))),0) -> 0 | AQ89: =IF($D89="",0,INDEX($CG$87:$CG$92,MATCH($D89,$CF$87:$CF$92))*$CE$87) -> 0 | AR89: =IF($D89="",0,IF(OR($I89="x",$I89="xx"),INDEX($CI$87:$CI$92,MATCH($D89,$CH$87:$CH$92))*$CE$87,0)) -> 0 | AS89: =IF($D89="",0,IF(OR($J89="x",$J89="xx"),INDEX($CK$87:$CK$92,MATCH($D89,$CJ$87:$CJ$92))*$CE$87,0)) -> 0 | AT89: =IF($D89="",0,IF(OR($M89="x",$M89="xx"),INDEX($CQ$87:$CQ$92,MATCH($D89,$CP$87:$CP$92))*$CE$87,0))+IF($D89="",0,IF(OR($N89="x",$N89="xx"),INDEX($CS$87:$CS$92,MATCH($D89,$CR$87:$CR$92))*$CE$87,0))+IF($D89="",0,IF(OR($K89="x",$K89="xx"),INDEX($CM$87:$CM$92,MATCH($D89,$CL$87:$CL$92))*$CE$87,0))+IF($D89="",0,IF(OR($L89="x",$L89="xx"),INDEX($CO$87:$CO$92,MATCH($D89,$CN$87:$CN$92))*$CE$87,0)) -> 0 | AU89: =IF($D89="",0,IF(OR($O89="x",$O89="xx"),INDEX($CU$87:$CU$92,MATCH($D89,$CT$87:$CT$92))*$CE$87,0)) -> 0 | AV89: =IF($D89="",0,IF(OR($P89="x",$P89="xx"),INDEX($CW$87:$CW$92,MATCH($D89,$CV$87:$CV$92))*$CE$87,0)) -> 0 | AW89: =IF($D89="",0,IF(OR($Q89="x",$Q89="xx"),INDEX($CY$87:$CY$92,MATCH($D89,$CX$87:$CX$92))*$CE$87,0)) -> 0 | AX89: =IF($D89="",0,IF(OR($R89="x",$R89="xx"),INDEX($DA$87:$DA$92,MATCH($D89,$CZ$87:$CZ$92))*$CE$87,0)) -> 0 | AY89: =IF($D89="",0,IF(OR($S89="x",$S89="xx"),INDEX($DC$87:$DC$92,MATCH($D89,$DB$87:$DB$92))*$CE$87,0)) -> 0 | AZ89: =IF($D89="",0,IF(OR($T89="x",$T89="xx"),IF($D89>4,INDEX($DE$87:$DE$92,MATCH($D89,$DD$87:$DD$92))*$CE$87,0),0)) -> 0 | BA89: =IF($D89="",0,($U89*INDEX($DG$87:$DG$92,MATCH($D89,$DF$87:$DF$92))*$CE$87)) -> 0 | BB89: =IF($D89="",0,(($U89+IF(OR($S89="x",$S89="xx"),1,0))*INDEX($DI$87:$DI$92,MATCH($D89,$DH$87:$DH$92))*$CE$87)) -> 0 | BC89: =IF($D89="",0,INDEX($DK$87:$DK$92,MATCH($D89,$DJ$87:$DJ$92))*$CE$87) -> 0 | BD89: =SUM(AQ89:BC89) -> 0 | BE89: =IF($D89="",0,((IF(OR($V89="x",$V89="xx"),1,0))*INDEX($DM$87:$DM$92,MATCH($D89,$DL$87:$DL$92))*$BR$58)) -> 0 | BI89: 10 | BJ89: 380 | BK89: 10 | BL89: 120 | BM89: 10 | BN89: =BR89*2 -> 1208 | BO89: 10 | BP89: =BN89*1.5 -> 1812 | BQ89: 10 | BR89: =(4*80+2.5*80+6*14) -> 604 | BS89: 10 | BT89: =((4*80+2.5*80+6*14))*1.5 -> 906 | BU89: 10 | BV89: =12*35 -> 420 | BW89: =12*35*1.5 -> 630 | BX89: 10 | BY89: 260 | BZ89: 170 | CA89: =45+9+75 -> 129 | CC89: 10 | CD89: 300 | CF89: 10 | CG89: 32 | CH89: 10 | CI89: 8 | CJ89: 10 | CK89: 5 | CL89: 10 | CM89: =CQ89*3 -> 30 | CN89: 10 | CO89: =CM89*1.5 -> 45 | CP89: 10 | CQ89: 10 | CR89: 10 | CS89: 15 | CT89: 10 | CU89: 6 | CV89: 10 | CW89: 1 | CX89: 10 | CY89: 5 | CZ89: 10 | DA89: 14 | DB89: 10 | DC89: 2 | DD89: 10 | DE89: 3 | DF89: 10 | DG89: 2 | DH89: 10 | DI89: 3 | DJ89: 10 | DK89: 6 | DL89: 10 | DM89: 6
B90: =B89+1 -> 5 | G90: =F90*D90 -> 0 | W90: =IF($I90="x",IF($D90="",0,INDEX($BJ$87:$BJ$92,MATCH($D90,$BI$87:$BI$92,1))),0) -> 0 | X90: =IF($J90="x",IF($D90="",0,INDEX($BL$87:$BL$92,MATCH($D90,$BK$87:$BK$92,1))),0) -> 0 | Y90: =IF($K90="x",IF($D90="",0,INDEX($BN$87:$BN$92,MATCH($D90,$BM$87:$BM$92,1))),0) -> 0 | Z90: =IF($L90="x",IF($D90="",0,INDEX($BP$87:$BP$92,MATCH($D90,$BO$87:$BO$92,1))),0) -> 0 | AA90: =IF($M90="x",IF($D90="",0,INDEX($BR$87:$BR$92,MATCH($D90,$BQ$87:$BQ$92,1))),0) -> 0 | AB90: =IF($N90="x",IF($D90="",0,INDEX($BT$87:$BT$92,MATCH($D90,$BS$87:$BS$92,1))),0) -> 0 | AC90: =IF(OR($K90="x",$M90="x"),IF($D90="",0,INDEX($BV$87:$BV$92,MATCH($D90,$BU$87:$BU$92,1))),0)+IF(OR($L90="x",$N90="x"),IF($D90="",0,INDEX($BW$87:$BW$92,MATCH($D90,$BU$87:$BU$92,1))),0) -> 0 | AD90: =IF($O90="x",IF($D90="",0,INDEX($BY$87:$BY$92,MATCH($D90,$BX$87:$BX$92,1))),0) -> 0 | AE90: =IF($P90="x",IF($D90="",0,$CB$87),0) -> 0 | AF90: =IF($D90="",0,IF(Q90="x",$CA$89,0)) -> 0 | AG90: =IF($D90="",0,IF(R90="x",$CA$91,0)) -> 0 | AH90: =IF($S90="x",IF($D90="",0,$BZ$87),0) -> 0 | AI90: =IF($T90="x",IF($D90="",0,IF($D90>4,$BZ$89,0)),0) -> 0 | AJ90: =IF($D90="",0,$U90*$BZ$91) -> 0 | AK90: =IF($D90="",0,(U90+IF(AH90>0,1,0))*$CA$87) -> 0 | AL90: =G90+H90 -> 0 | AM90: =SUM(W90:AK90) -> 0 | AN90: =IF($E90="xx",(1600*$D90+$AM90),SUM(AL90:AM90))*$AN$84 -> 0 | AO90: =SUM(AL90:AN90) -> 0 | AP90: =IF($V90="x",IF($D90="",0,INDEX($CD$87:$CD$92,MATCH($D90,$CC$87:$CC$92,1))),0) -> 0 | AQ90: =IF($D90="",0,INDEX($CG$87:$CG$92,MATCH($D90,$CF$87:$CF$92))*$CE$87) -> 0 | AR90: =IF($D90="",0,IF(OR($I90="x",$I90="xx"),INDEX($CI$87:$CI$92,MATCH($D90,$CH$87:$CH$92))*$CE$87,0)) -> 0 | AS90: =IF($D90="",0,IF(OR($J90="x",$J90="xx"),INDEX($CK$87:$CK$92,MATCH($D90,$CJ$87:$CJ$92))*$CE$87,0)) -> 0 | AT90: =IF($D90="",0,IF(OR($M90="x",$M90="xx"),INDEX($CQ$87:$CQ$92,MATCH($D90,$CP$87:$CP$92))*$CE$87,0))+IF($D90="",0,IF(OR($N90="x",$N90="xx"),INDEX($CS$87:$CS$92,MATCH($D90,$CR$87:$CR$92))*$CE$87,0))+IF($D90="",0,IF(OR($K90="x",$K90="xx"),INDEX($CM$87:$CM$92,MATCH($D90,$CL$87:$CL$92))*$CE$87,0))+IF($D90="",0,IF(OR($L90="x",$L90="xx"),INDEX($CO$87:$CO$92,MATCH($D90,$CN$87:$CN$92))*$CE$87,0)) -> 0 | AU90: =IF($D90="",0,IF(OR($O90="x",$O90="xx"),INDEX($CU$87:$CU$92,MATCH($D90,$CT$87:$CT$92))*$CE$87,0)) -> 0 | AV90: =IF($D90="",0,IF(OR($P90="x",$P90="xx"),INDEX($CW$87:$CW$92,MATCH($D90,$CV$87:$CV$92))*$CE$87,0)) -> 0 | AW90: =IF($D90="",0,IF(OR($Q90="x",$Q90="xx"),INDEX($CY$87:$CY$92,MATCH($D90,$CX$87:$CX$92))*$CE$87,0)) -> 0 | AX90: =IF($D90="",0,IF(OR($R90="x",$R90="xx"),INDEX($DA$87:$DA$92,MATCH($D90,$CZ$87:$CZ$92))*$CE$87,0)) -> 0 | AY90: =IF($D90="",0,IF(OR($S90="x",$S90="xx"),INDEX($DC$87:$DC$92,MATCH($D90,$DB$87:$DB$92))*$CE$87,0)) -> 0 | AZ90: =IF($D90="",0,IF(OR($T90="x",$T90="xx"),IF($D90>4,INDEX($DE$87:$DE$92,MATCH($D90,$DD$87:$DD$92))*$CE$87,0),0)) -> 0 | BA90: =IF($D90="",0,($U90*INDEX($DG$87:$DG$92,MATCH($D90,$DF$87:$DF$92))*$CE$87)) -> 0 | BB90: =IF($D90="",0,(($U90+IF(OR($S90="x",$S90="xx"),1,0))*INDEX($DI$87:$DI$92,MATCH($D90,$DH$87:$DH$92))*$CE$87)) -> 0 | BC90: =IF($D90="",0,INDEX($DK$87:$DK$92,MATCH($D90,$DJ$87:$DJ$92))*$CE$87) -> 0 | BD90: =SUM(AQ90:BC90) -> 0 | BE90: =IF($D90="",0,((IF(OR($V90="x",$V90="xx"),1,0))*INDEX($DM$87:$DM$92,MATCH($D90,$DL$87:$DL$92))*$BR$58)) -> 0 | BH90: Selection Owner Provided | BI90: 20 | BJ90: 450 | BK90: 20 | BL90: 180 | BM90: 20 | BN90: =BR90*2 -> 3216 | BO90: 20 | BP90: =BN90*1.5 -> 4824 | BQ90: 20 | BR90: =(6*80+3*80+6*14)*2 -> 1608 | BS90: 20 | BT90: =((6*80+3*80+6*14)*2)*1.5 -> 2412 | BU90: 20 | BV90: =18*35 -> 630 | BW90: =18*35*1.5 -> 945 | BX90: 20 | BY90: 400 | BZ90: Sensors | CA90: CU Cond | CC90: 20 | CD90: 400 | CF90: 20 | CG90: 40 | CH90: 20 | CI90: 16 | CJ90: 20 | CK90: 6 | CL90: 20 | CM90: =CQ90*3 -> 42 | CN90: 20 | CO90: =CM90*1.5 -> 63 | CP90: 20 | CQ90: 14 | CR90: 20 | CS90: 21 | CT90: 20 | CU90: 8 | CV90: 20 | CW90: 1 | CX90: 20 | CY90: 6 | CZ90: 20 | DA90: 16 | DB90: 20 | DC90: 2 | DD90: 20 | DE90: 3 | DF90: 20 | DG90: 2 | DH90: 20 | DI90: 3 | DJ90: 20 | DK90: 7 | DL90: 20 | DM90: 8
B91: =B90+1 -> 6 | G91: =F91*D91 -> 0 | W91: =IF($I91="x",IF($D91="",0,INDEX($BJ$87:$BJ$92,MATCH($D91,$BI$87:$BI$92,1))),0) -> 0 | X91: =IF($J91="x",IF($D91="",0,INDEX($BL$87:$BL$92,MATCH($D91,$BK$87:$BK$92,1))),0) -> 0 | Y91: =IF($K91="x",IF($D91="",0,INDEX($BN$87:$BN$92,MATCH($D91,$BM$87:$BM$92,1))),0) -> 0 | Z91: =IF($L91="x",IF($D91="",0,INDEX($BP$87:$BP$92,MATCH($D91,$BO$87:$BO$92,1))),0) -> 0 | AA91: =IF($M91="x",IF($D91="",0,INDEX($BR$87:$BR$92,MATCH($D91,$BQ$87:$BQ$92,1))),0) -> 0 | AB91: =IF($N91="x",IF($D91="",0,INDEX($BT$87:$BT$92,MATCH($D91,$BS$87:$BS$92,1))),0) -> 0 | AC91: =IF(OR($K91="x",$M91="x"),IF($D91="",0,INDEX($BV$87:$BV$92,MATCH($D91,$BU$87:$BU$92,1))),0)+IF(OR($L91="x",$N91="x"),IF($D91="",0,INDEX($BW$87:$BW$92,MATCH($D91,$BU$87:$BU$92,1))),0) -> 0 | AD91: =IF($O91="x",IF($D91="",0,INDEX($BY$87:$BY$92,MATCH($D91,$BX$87:$BX$92,1))),0) -> 0 | AE91: =IF($P91="x",IF($D91="",0,$CB$87),0) -> 0 | AF91: =IF($D91="",0,IF(Q91="x",$CA$89,0)) -> 0 | AG91: =IF($D91="",0,IF(R91="x",$CA$91,0)) -> 0 | AH91: =IF($S91="x",IF($D91="",0,$BZ$87),0) -> 0 | AI91: =IF($T91="x",IF($D91="",0,IF($D91>4,$BZ$89,0)),0) -> 0 | AJ91: =IF($D91="",0,$U91*$BZ$91) -> 0 | AK91: =IF($D91="",0,(U91+IF(AH91>0,1,0))*$CA$87) -> 0 | AL91: =G91+H91 -> 0 | AM91: =SUM(W91:AK91) -> 0 | AN91: =IF($E91="xx",(1600*$D91+$AM91),SUM(AL91:AM91))*$AN$84 -> 0 | AO91: =SUM(AL91:AN91) -> 0 | AP91: =IF($V91="x",IF($D91="",0,INDEX($CD$87:$CD$92,MATCH($D91,$CC$87:$CC$92,1))),0) -> 0 | AQ91: =IF($D91="",0,INDEX($CG$87:$CG$92,MATCH($D91,$CF$87:$CF$92))*$CE$87) -> 0 | AR91: =IF($D91="",0,IF(OR($I91="x",$I91="xx"),INDEX($CI$87:$CI$92,MATCH($D91,$CH$87:$CH$92))*$CE$87,0)) -> 0 | AS91: =IF($D91="",0,IF(OR($J91="x",$J91="xx"),INDEX($CK$87:$CK$92,MATCH($D91,$CJ$87:$CJ$92))*$CE$87,0)) -> 0 | AT91: =IF($D91="",0,IF(OR($M91="x",$M91="xx"),INDEX($CQ$87:$CQ$92,MATCH($D91,$CP$87:$CP$92))*$CE$87,0))+IF($D91="",0,IF(OR($N91="x",$N91="xx"),INDEX($CS$87:$CS$92,MATCH($D91,$CR$87:$CR$92))*$CE$87,0))+IF($D91="",0,IF(OR($K91="x",$K91="xx"),INDEX($CM$87:$CM$92,MATCH($D91,$CL$87:$CL$92))*$CE$87,0))+IF($D91="",0,IF(OR($L91="x",$L91="xx"),INDEX($CO$87:$CO$92,MATCH($D91,$CN$87:$CN$92))*$CE$87,0)) -> 0 | AU91: =IF($D91="",0,IF(OR($O91="x",$O91="xx"),INDEX($CU$87:$CU$92,MATCH($D91,$CT$87:$CT$92))*$CE$87,0)) -> 0 | AV91: =IF($D91="",0,IF(OR($P91="x",$P91="xx"),INDEX($CW$87:$CW$92,MATCH($D91,$CV$87:$CV$92))*$CE$87,0)) -> 0 | AW91: =IF($D91="",0,IF(OR($Q91="x",$Q91="xx"),INDEX($CY$87:$CY$92,MATCH($D91,$CX$87:$CX$92))*$CE$87,0)) -> 0 | AX91: =IF($D91="",0,IF(OR($R91="x",$R91="xx"),INDEX($DA$87:$DA$92,MATCH($D91,$CZ$87:$CZ$92))*$CE$87,0)) -> 0 | AY91: =IF($D91="",0,IF(OR($S91="x",$S91="xx"),INDEX($DC$87:$DC$92,MATCH($D91,$DB$87:$DB$92))*$CE$87,0)) -> 0 | AZ91: =IF($D91="",0,IF(OR($T91="x",$T91="xx"),IF($D91>4,INDEX($DE$87:$DE$92,MATCH($D91,$DD$87:$DD$92))*$CE$87,0),0)) -> 0 | BA91: =IF($D91="",0,($U91*INDEX($DG$87:$DG$92,MATCH($D91,$DF$87:$DF$92))*$CE$87)) -> 0 | BB91: =IF($D91="",0,(($U91+IF(OR($S91="x",$S91="xx"),1,0))*INDEX($DI$87:$DI$92,MATCH($D91,$DH$87:$DH$92))*$CE$87)) -> 0 | BC91: =IF($D91="",0,INDEX($DK$87:$DK$92,MATCH($D91,$DJ$87:$DJ$92))*$CE$87) -> 0 | BD91: =SUM(AQ91:BC91) -> 0 | BE91: =IF($D91="",0,((IF(OR($V91="x",$V91="xx"),1,0))*INDEX($DM$87:$DM$92,MATCH($D91,$DL$87:$DL$92))*$BR$58)) -> 0 | BH91: xx | BI91: 50 | BJ91: 1200 | BK91: 50 | BL91: 600 | BM91: 50 | BN91: =BR91*2 -> 4496 | BO91: 50 | BP91: =BN91*1.5 -> 6744 | BQ91: 50 | BR91: =(9*80+4*80+6*14)*2 -> 2248 | BS91: 50 | BT91: =((9*80+4*80+6*14)*2)*1.5 -> 3372 | BU91: 50 | BV91: =35*35 -> 1225 | BW91: =35*35*1.5 -> 1837.5 | BX91: 50 | BY91: 800 | BZ91: 125 | CA91: =(50*4+15+50)*1.5 -> 397.5 | CC91: 50 | CD91: 800 | CF91: 50 | CG91: 60 | CH91: 50 | CI91: 30 | CJ91: 50 | CK91: 9 | CL91: 50 | CM91: =CQ91*3 -> 60 | CN91: 50 | CO91: =CM91*1.5 -> 90 | CP91: 50 | CQ91: 20 | CR91: 50 | CS91: 30 | CT91: 50 | CU91: 12 | CV91: 50 | CW91: 1 | CX91: 50 | CY91: 7 | CZ91: 50 | DA91: 20 | DB91: 50 | DC91: 3 | DD91: 50 | DE91: 4 | DF91: 50 | DG91: 2 | DH91: 50 | DI91: 3 | DJ91: 50 | DK91: 9 | DL91: 50 | DM91: 12
B92: =B91+1 -> 7 | G92: =F92*D92 -> 0 | W92: =IF($I92="x",IF($D92="",0,INDEX($BJ$87:$BJ$92,MATCH($D92,$BI$87:$BI$92,1))),0) -> 0 | X92: =IF($J92="x",IF($D92="",0,INDEX($BL$87:$BL$92,MATCH($D92,$BK$87:$BK$92,1))),0) -> 0 | Y92: =IF($K92="x",IF($D92="",0,INDEX($BN$87:$BN$92,MATCH($D92,$BM$87:$BM$92,1))),0) -> 0 | Z92: =IF($L92="x",IF($D92="",0,INDEX($BP$87:$BP$92,MATCH($D92,$BO$87:$BO$92,1))),0) -> 0 | AA92: =IF($M92="x",IF($D92="",0,INDEX($BR$87:$BR$92,MATCH($D92,$BQ$87:$BQ$92,1))),0) -> 0 | AB92: =IF($N92="x",IF($D92="",0,INDEX($BT$87:$BT$92,MATCH($D92,$BS$87:$BS$92,1))),0) -> 0 | AC92: =IF(OR($K92="x",$M92="x"),IF($D92="",0,INDEX($BV$87:$BV$92,MATCH($D92,$BU$87:$BU$92,1))),0)+IF(OR($L92="x",$N92="x"),IF($D92="",0,INDEX($BW$87:$BW$92,MATCH($D92,$BU$87:$BU$92,1))),0) -> 0 | AD92: =IF($O92="x",IF($D92="",0,INDEX($BY$87:$BY$92,MATCH($D92,$BX$87:$BX$92,1))),0) -> 0 | AE92: =IF($P92="x",IF($D92="",0,$CB$87),0) -> 0 | AF92: =IF($D92="",0,IF(Q92="x",$CA$89,0)) -> 0 | AG92: =IF($D92="",0,IF(R92="x",$CA$91,0)) -> 0 | AH92: =IF($S92="x",IF($D92="",0,$BZ$87),0) -> 0 | AI92: =IF($T92="x",IF($D92="",0,IF($D92>4,$BZ$89,0)),0) -> 0 | AJ92: =IF($D92="",0,$U92*$BZ$91) -> 0 | AK92: =IF($D92="",0,(U92+IF(AH92>0,1,0))*$CA$87) -> 0 | AL92: =G92+H92 -> 0 | AM92: =SUM(W92:AK92) -> 0 | AN92: =IF($E92="xx",(1600*$D92+$AM92),SUM(AL92:AM92))*$AN$84 -> 0 | AO92: =SUM(AL92:AN92) -> 0 | AP92: =IF($V92="x",IF($D92="",0,INDEX($CD$87:$CD$92,MATCH($D92,$CC$87:$CC$92,1))),0) -> 0 | AQ92: =IF($D92="",0,INDEX($CG$87:$CG$92,MATCH($D92,$CF$87:$CF$92))*$CE$87) -> 0 | AR92: =IF($D92="",0,IF(OR($I92="x",$I92="xx"),INDEX($CI$87:$CI$92,MATCH($D92,$CH$87:$CH$92))*$CE$87,0)) -> 0 | AS92: =IF($D92="",0,IF(OR($J92="x",$J92="xx"),INDEX($CK$87:$CK$92,MATCH($D92,$CJ$87:$CJ$92))*$CE$87,0)) -> 0 | AT92: =IF($D92="",0,IF(OR($M92="x",$M92="xx"),INDEX($CQ$87:$CQ$92,MATCH($D92,$CP$87:$CP$92))*$CE$87,0))+IF($D92="",0,IF(OR($N92="x",$N92="xx"),INDEX($CS$87:$CS$92,MATCH($D92,$CR$87:$CR$92))*$CE$87,0))+IF($D92="",0,IF(OR($K92="x",$K92="xx"),INDEX($CM$87:$CM$92,MATCH($D92,$CL$87:$CL$92))*$CE$87,0))+IF($D92="",0,IF(OR($L92="x",$L92="xx"),INDEX($CO$87:$CO$92,MATCH($D92,$CN$87:$CN$92))*$CE$87,0)) -> 0 | AU92: =IF($D92="",0,IF(OR($O92="x",$O92="xx"),INDEX($CU$87:$CU$92,MATCH($D92,$CT$87:$CT$92))*$CE$87,0)) -> 0 | AV92: =IF($D92="",0,IF(OR($P92="x",$P92="xx"),INDEX($CW$87:$CW$92,MATCH($D92,$CV$87:$CV$92))*$CE$87,0)) -> 0 | AW92: =IF($D92="",0,IF(OR($Q92="x",$Q92="xx"),INDEX($CY$87:$CY$92,MATCH($D92,$CX$87:$CX$92))*$CE$87,0)) -> 0 | AX92: =IF($D92="",0,IF(OR($R92="x",$R92="xx"),INDEX($DA$87:$DA$92,MATCH($D92,$CZ$87:$CZ$92))*$CE$87,0)) -> 0 | AY92: =IF($D92="",0,IF(OR($S92="x",$S92="xx"),INDEX($DC$87:$DC$92,MATCH($D92,$DB$87:$DB$92))*$CE$87,0)) -> 0 | AZ92: =IF($D92="",0,IF(OR($T92="x",$T92="xx"),IF($D92>4,INDEX($DE$87:$DE$92,MATCH($D92,$DD$87:$DD$92))*$CE$87,0),0)) -> 0 | BA92: =IF($D92="",0,($U92*INDEX($DG$87:$DG$92,MATCH($D92,$DF$87:$DF$92))*$CE$87)) -> 0 | BB92: =IF($D92="",0,(($U92+IF(OR($S92="x",$S92="xx"),1,0))*INDEX($DI$87:$DI$92,MATCH($D92,$DH$87:$DH$92))*$CE$87)) -> 0 | BC92: =IF($D92="",0,INDEX($DK$87:$DK$92,MATCH($D92,$DJ$87:$DJ$92))*$CE$87) -> 0 | BD92: =SUM(AQ92:BC92) -> 0 | BE92: =IF($D92="",0,((IF(OR($V92="x",$V92="xx"),1,0))*INDEX($DM$87:$DM$92,MATCH($D92,$DL$87:$DL$92))*$BR$58)) -> 0 | BI92: 75 | BJ92: 4000 | BK92: 75 | BL92: 1500 | BM92: 75 | BN92: =BR92*2 -> 6096 | BO92: 75 | BP92: =BN92*1.5 -> 9144 | BQ92: 75 | BR92: =(12*80+6*80+6*14)*2 -> 3048 | BS92: 75 | BT92: =((12*80+6*80+6*14)*2)*1.5 -> 4572 | BU92: 75 | BV92: =70*35 -> 2450 | BW92: =70*35*1.5 -> 3675 | BX92: 75 | BY92: 1600 | CC92: 75 | CD92: 1600 | CF92: 75 | CG92: =CG91*2 -> 120 | CH92: 75 | CI92: 60 | CJ92: 75 | CK92: 14 | CL92: 75 | CM92: =CQ92*3 -> 120 | CN92: 75 | CO92: =CM92*1.5 -> 180 | CP92: 75 | CQ92: 40 | CR92: 75 | CS92: 60 | CT92: 75 | CU92: 16 | CV92: 75 | CW92: 1 | CX92: 75 | CY92: 9 | CZ92: 75 | DA92: 24 | DB92: 75 | DC92: 4 | DD92: 75 | DE92: 4 | DF92: 75 | DG92: 2 | DH92: 75 | DI92: 3 | DJ92: 75 | DK92: 14 | DL92: 75 | DM92: 16
B93: =B92+1 -> 8 | G93: =F93*D93 -> 0 | W93: =IF($I93="x",IF($D93="",0,INDEX($BJ$87:$BJ$92,MATCH($D93,$BI$87:$BI$92,1))),0) -> 0 | X93: =IF($J93="x",IF($D93="",0,INDEX($BL$87:$BL$92,MATCH($D93,$BK$87:$BK$92,1))),0) -> 0 | Y93: =IF($K93="x",IF($D93="",0,INDEX($BN$87:$BN$92,MATCH($D93,$BM$87:$BM$92,1))),0) -> 0 | Z93: =IF($L93="x",IF($D93="",0,INDEX($BP$87:$BP$92,MATCH($D93,$BO$87:$BO$92,1))),0) -> 0 | AA93: =IF($M93="x",IF($D93="",0,INDEX($BR$87:$BR$92,MATCH($D93,$BQ$87:$BQ$92,1))),0) -> 0 | AB93: =IF($N93="x",IF($D93="",0,INDEX($BT$87:$BT$92,MATCH($D93,$BS$87:$BS$92,1))),0) -> 0 | AC93: =IF(OR($K93="x",$M93="x"),IF($D93="",0,INDEX($BV$87:$BV$92,MATCH($D93,$BU$87:$BU$92,1))),0)+IF(OR($L93="x",$N93="x"),IF($D93="",0,INDEX($BW$87:$BW$92,MATCH($D93,$BU$87:$BU$92,1))),0) -> 0 | AD93: =IF($O93="x",IF($D93="",0,INDEX($BY$87:$BY$92,MATCH($D93,$BX$87:$BX$92,1))),0) -> 0 | AE93: =IF($P93="x",IF($D93="",0,$CB$87),0) -> 0 | AF93: =IF($D93="",0,IF(Q93="x",$CA$89,0)) -> 0 | AG93: =IF($D93="",0,IF(R93="x",$CA$91,0)) -> 0 | AH93: =IF($S93="x",IF($D93="",0,$BZ$87),0) -> 0 | AI93: =IF($T93="x",IF($D93="",0,IF($D93>4,$BZ$89,0)),0) -> 0 | AJ93: =IF($D93="",0,$U93*$BZ$91) -> 0 | AK93: =IF($D93="",0,(U93+IF(AH93>0,1,0))*$CA$87) -> 0 | AL93: =G93+H93 -> 0 | AM93: =SUM(W93:AK93) -> 0 | AN93: =IF($E93="xx",(1600*$D93+$AM93),SUM(AL93:AM93))*$AN$84 -> 0 | AO93: =SUM(AL93:AN93) -> 0 | AP93: =IF($V93="x",IF($D93="",0,INDEX($CD$87:$CD$92,MATCH($D93,$CC$87:$CC$92,1))),0) -> 0 | AQ93: =IF($D93="",0,INDEX($CG$87:$CG$92,MATCH($D93,$CF$87:$CF$92))*$CE$87) -> 0 | AR93: =IF($D93="",0,IF(OR($I93="x",$I93="xx"),INDEX($CI$87:$CI$92,MATCH($D93,$CH$87:$CH$92))*$CE$87,0)) -> 0 | AS93: =IF($D93="",0,IF(OR($J93="x",$J93="xx"),INDEX($CK$87:$CK$92,MATCH($D93,$CJ$87:$CJ$92))*$CE$87,0)) -> 0 | AT93: =IF($D93="",0,IF(OR($M93="x",$M93="xx"),INDEX($CQ$87:$CQ$92,MATCH($D93,$CP$87:$CP$92))*$CE$87,0))+IF($D93="",0,IF(OR($N93="x",$N93="xx"),INDEX($CS$87:$CS$92,MATCH($D93,$CR$87:$CR$92))*$CE$87,0))+IF($D93="",0,IF(OR($K93="x",$K93="xx"),INDEX($CM$87:$CM$92,MATCH($D93,$CL$87:$CL$92))*$CE$87,0))+IF($D93="",0,IF(OR($L93="x",$L93="xx"),INDEX($CO$87:$CO$92,MATCH($D93,$CN$87:$CN$92))*$CE$87,0)) -> 0 | AU93: =IF($D93="",0,IF(OR($O93="x",$O93="xx"),INDEX($CU$87:$CU$92,MATCH($D93,$CT$87:$CT$92))*$CE$87,0)) -> 0 | AV93: =IF($D93="",0,IF(OR($P93="x",$P93="xx"),INDEX($CW$87:$CW$92,MATCH($D93,$CV$87:$CV$92))*$CE$87,0)) -> 0 | AW93: =IF($D93="",0,IF(OR($Q93="x",$Q93="xx"),INDEX($CY$87:$CY$92,MATCH($D93,$CX$87:$CX$92))*$CE$87,0)) -> 0 | AX93: =IF($D93="",0,IF(OR($R93="x",$R93="xx"),INDEX($DA$87:$DA$92,MATCH($D93,$CZ$87:$CZ$92))*$CE$87,0)) -> 0 | AY93: =IF($D93="",0,IF(OR($S93="x",$S93="xx"),INDEX($DC$87:$DC$92,MATCH($D93,$DB$87:$DB$92))*$CE$87,0)) -> 0 | AZ93: =IF($D93="",0,IF(OR($T93="x",$T93="xx"),IF($D93>4,INDEX($DE$87:$DE$92,MATCH($D93,$DD$87:$DD$92))*$CE$87,0),0)) -> 0 | BA93: =IF($D93="",0,($U93*INDEX($DG$87:$DG$92,MATCH($D93,$DF$87:$DF$92))*$CE$87)) -> 0 | BB93: =IF($D93="",0,(($U93+IF(OR($S93="x",$S93="xx"),1,0))*INDEX($DI$87:$DI$92,MATCH($D93,$DH$87:$DH$92))*$CE$87)) -> 0 | BC93: =IF($D93="",0,INDEX($DK$87:$DK$92,MATCH($D93,$DJ$87:$DJ$92))*$CE$87) -> 0 | BD93: =SUM(AQ93:BC93) -> 0 | BE93: =IF($D93="",0,((IF(OR($V93="x",$V93="xx"),1,0))*INDEX($DM$87:$DM$92,MATCH($D93,$DL$87:$DL$92))*$BR$58)) -> 0
B94: =B93+1 -> 9 | G94: =F94*D94 -> 0 | W94: =IF($I94="x",IF($D94="",0,INDEX($BJ$87:$BJ$92,MATCH($D94,$BI$87:$BI$92,1))),0) -> 0 | X94: =IF($J94="x",IF($D94="",0,INDEX($BL$87:$BL$92,MATCH($D94,$BK$87:$BK$92,1))),0) -> 0 | Y94: =IF($K94="x",IF($D94="",0,INDEX($BN$87:$BN$92,MATCH($D94,$BM$87:$BM$92,1))),0) -> 0 | Z94: =IF($L94="x",IF($D94="",0,INDEX($BP$87:$BP$92,MATCH($D94,$BO$87:$BO$92,1))),0) -> 0 | AA94: =IF($M94="x",IF($D94="",0,INDEX($BR$87:$BR$92,MATCH($D94,$BQ$87:$BQ$92,1))),0) -> 0 | AB94: =IF($N94="x",IF($D94="",0,INDEX($BT$87:$BT$92,MATCH($D94,$BS$87:$BS$92,1))),0) -> 0 | AC94: =IF(OR($K94="x",$M94="x"),IF($D94="",0,INDEX($BV$87:$BV$92,MATCH($D94,$BU$87:$BU$92,1))),0)+IF(OR($L94="x",$N94="x"),IF($D94="",0,INDEX($BW$87:$BW$92,MATCH($D94,$BU$87:$BU$92,1))),0) -> 0 | AD94: =IF($O94="x",IF($D94="",0,INDEX($BY$87:$BY$92,MATCH($D94,$BX$87:$BX$92,1))),0) -> 0 | AE94: =IF($P94="x",IF($D94="",0,$CB$87),0) -> 0 | AF94: =IF($D94="",0,IF(Q94="x",$CA$89,0)) -> 0 | AG94: =IF($D94="",0,IF(R94="x",$CA$91,0)) -> 0 | AH94: =IF($S94="x",IF($D94="",0,$BZ$87),0) -> 0 | AI94: =IF($T94="x",IF($D94="",0,IF($D94>4,$BZ$89,0)),0) -> 0 | AJ94: =IF($D94="",0,$U94*$BZ$91) -> 0 | AK94: =IF($D94="",0,(U94+IF(AH94>0,1,0))*$CA$87) -> 0 | AL94: =G94+H94 -> 0 | AM94: =SUM(W94:AK94) -> 0 | AN94: =IF($E94="xx",(1600*$D94+$AM94),SUM(AL94:AM94))*$AN$84 -> 0 | AO94: =SUM(AL94:AN94) -> 0 | AP94: =IF($V94="x",IF($D94="",0,INDEX($CD$87:$CD$92,MATCH($D94,$CC$87:$CC$92,1))),0) -> 0 | AQ94: =IF($D94="",0,INDEX($CG$87:$CG$92,MATCH($D94,$CF$87:$CF$92))*$CE$87) -> 0 | AR94: =IF($D94="",0,IF(OR($I94="x",$I94="xx"),INDEX($CI$87:$CI$92,MATCH($D94,$CH$87:$CH$92))*$CE$87,0)) -> 0 | AS94: =IF($D94="",0,IF(OR($J94="x",$J94="xx"),INDEX($CK$87:$CK$92,MATCH($D94,$CJ$87:$CJ$92))*$CE$87,0)) -> 0 | AT94: =IF($D94="",0,IF(OR($M94="x",$M94="xx"),INDEX($CQ$87:$CQ$92,MATCH($D94,$CP$87:$CP$92))*$CE$87,0))+IF($D94="",0,IF(OR($N94="x",$N94="xx"),INDEX($CS$87:$CS$92,MATCH($D94,$CR$87:$CR$92))*$CE$87,0))+IF($D94="",0,IF(OR($K94="x",$K94="xx"),INDEX($CM$87:$CM$92,MATCH($D94,$CL$87:$CL$92))*$CE$87,0))+IF($D94="",0,IF(OR($L94="x",$L94="xx"),INDEX($CO$87:$CO$92,MATCH($D94,$CN$87:$CN$92))*$CE$87,0)) -> 0 | AU94: =IF($D94="",0,IF(OR($O94="x",$O94="xx"),INDEX($CU$87:$CU$92,MATCH($D94,$CT$87:$CT$92))*$CE$87,0)) -> 0 | AV94: =IF($D94="",0,IF(OR($P94="x",$P94="xx"),INDEX($CW$87:$CW$92,MATCH($D94,$CV$87:$CV$92))*$CE$87,0)) -> 0 | AW94: =IF($D94="",0,IF(OR($Q94="x",$Q94="xx"),INDEX($CY$87:$CY$92,MATCH($D94,$CX$87:$CX$92))*$CE$87,0)) -> 0 | AX94: =IF($D94="",0,IF(OR($R94="x",$R94="xx"),INDEX($DA$87:$DA$92,MATCH($D94,$CZ$87:$CZ$92))*$CE$87,0)) -> 0 | AY94: =IF($D94="",0,IF(OR($S94="x",$S94="xx"),INDEX($DC$87:$DC$92,MATCH($D94,$DB$87:$DB$92))*$CE$87,0)) -> 0 | AZ94: =IF($D94="",0,IF(OR($T94="x",$T94="xx"),IF($D94>4,INDEX($DE$87:$DE$92,MATCH($D94,$DD$87:$DD$92))*$CE$87,0),0)) -> 0 | BA94: =IF($D94="",0,($U94*INDEX($DG$87:$DG$92,MATCH($D94,$DF$87:$DF$92))*$CE$87)) -> 0 | BB94: =IF($D94="",0,(($U94+IF(OR($S94="x",$S94="xx"),1,0))*INDEX($DI$87:$DI$92,MATCH($D94,$DH$87:$DH$92))*$CE$87)) -> 0 | BC94: =IF($D94="",0,INDEX($DK$87:$DK$92,MATCH($D94,$DJ$87:$DJ$92))*$CE$87) -> 0 | BD94: =SUM(AQ94:BC94) -> 0 | BE94: =IF($D94="",0,((IF(OR($V94="x",$V94="xx"),1,0))*INDEX($DM$87:$DM$92,MATCH($D94,$DL$87:$DL$92))*$BR$58)) -> 0
B95: =B94+1 -> 10 | G95: =F95*D95 -> 0 | W95: =IF($I95="x",IF($D95="",0,INDEX($BJ$87:$BJ$92,MATCH($D95,$BI$87:$BI$92,1))),0) -> 0 | X95: =IF($J95="x",IF($D95="",0,INDEX($BL$87:$BL$92,MATCH($D95,$BK$87:$BK$92,1))),0) -> 0 | Y95: =IF($K95="x",IF($D95="",0,INDEX($BN$87:$BN$92,MATCH($D95,$BM$87:$BM$92,1))),0) -> 0 | Z95: =IF($L95="x",IF($D95="",0,INDEX($BP$87:$BP$92,MATCH($D95,$BO$87:$BO$92,1))),0) -> 0 | AA95: =IF($M95="x",IF($D95="",0,INDEX($BR$87:$BR$92,MATCH($D95,$BQ$87:$BQ$92,1))),0) -> 0 | AB95: =IF($N95="x",IF($D95="",0,INDEX($BT$87:$BT$92,MATCH($D95,$BS$87:$BS$92,1))),0) -> 0 | AC95: =IF(OR($K95="x",$M95="x"),IF($D95="",0,INDEX($BV$87:$BV$92,MATCH($D95,$BU$87:$BU$92,1))),0)+IF(OR($L95="x",$N95="x"),IF($D95="",0,INDEX($BW$87:$BW$92,MATCH($D95,$BU$87:$BU$92,1))),0) -> 0 | AD95: =IF($O95="x",IF($D95="",0,INDEX($BY$87:$BY$92,MATCH($D95,$BX$87:$BX$92,1))),0) -> 0 | AE95: =IF($P95="x",IF($D95="",0,$CB$87),0) -> 0 | AF95: =IF($D95="",0,IF(Q95="x",$CA$89,0)) -> 0 | AG95: =IF($D95="",0,IF(R95="x",$CA$91,0)) -> 0 | AH95: =IF($S95="x",IF($D95="",0,$BZ$87),0) -> 0 | AI95: =IF($T95="x",IF($D95="",0,IF($D95>4,$BZ$89,0)),0) -> 0 | AJ95: =IF($D95="",0,$U95*$BZ$91) -> 0 | AK95: =IF($D95="",0,(U95+IF(AH95>0,1,0))*$CA$87) -> 0 | AL95: =G95+H95 -> 0 | AM95: =SUM(W95:AK95) -> 0 | AN95: =IF($E95="xx",(1600*$D95+$AM95),SUM(AL95:AM95))*$AN$84 -> 0 | AO95: =SUM(AL95:AN95) -> 0 | AP95: =IF($V95="x",IF($D95="",0,INDEX($CD$87:$CD$92,MATCH($D95,$CC$87:$CC$92,1))),0) -> 0 | AQ95: =IF($D95="",0,INDEX($CG$87:$CG$92,MATCH($D95,$CF$87:$CF$92))*$CE$87) -> 0 | AR95: =IF($D95="",0,IF(OR($I95="x",$I95="xx"),INDEX($CI$87:$CI$92,MATCH($D95,$CH$87:$CH$92))*$CE$87,0)) -> 0 | AS95: =IF($D95="",0,IF(OR($J95="x",$J95="xx"),INDEX($CK$87:$CK$92,MATCH($D95,$CJ$87:$CJ$92))*$CE$87,0)) -> 0 | AT95: =IF($D95="",0,IF(OR($M95="x",$M95="xx"),INDEX($CQ$87:$CQ$92,MATCH($D95,$CP$87:$CP$92))*$CE$87,0))+IF($D95="",0,IF(OR($N95="x",$N95="xx"),INDEX($CS$87:$CS$92,MATCH($D95,$CR$87:$CR$92))*$CE$87,0))+IF($D95="",0,IF(OR($K95="x",$K95="xx"),INDEX($CM$87:$CM$92,MATCH($D95,$CL$87:$CL$92))*$CE$87,0))+IF($D95="",0,IF(OR($L95="x",$L95="xx"),INDEX($CO$87:$CO$92,MATCH($D95,$CN$87:$CN$92))*$CE$87,0)) -> 0 | AU95: =IF($D95="",0,IF(OR($O95="x",$O95="xx"),INDEX($CU$87:$CU$92,MATCH($D95,$CT$87:$CT$92))*$CE$87,0)) -> 0 | AV95: =IF($D95="",0,IF(OR($P95="x",$P95="xx"),INDEX($CW$87:$CW$92,MATCH($D95,$CV$87:$CV$92))*$CE$87,0)) -> 0 | AW95: =IF($D95="",0,IF(OR($Q95="x",$Q95="xx"),INDEX($CY$87:$CY$92,MATCH($D95,$CX$87:$CX$92))*$CE$87,0)) -> 0 | AX95: =IF($D95="",0,IF(OR($R95="x",$R95="xx"),INDEX($DA$87:$DA$92,MATCH($D95,$CZ$87:$CZ$92))*$CE$87,0)) -> 0 | AY95: =IF($D95="",0,IF(OR($S95="x",$S95="xx"),INDEX($DC$87:$DC$92,MATCH($D95,$DB$87:$DB$92))*$CE$87,0)) -> 0 | AZ95: =IF($D95="",0,IF(OR($T95="x",$T95="xx"),IF($D95>4,INDEX($DE$87:$DE$92,MATCH($D95,$DD$87:$DD$92))*$CE$87,0),0)) -> 0 | BA95: =IF($D95="",0,($U95*INDEX($DG$87:$DG$92,MATCH($D95,$DF$87:$DF$92))*$CE$87)) -> 0 | BB95: =IF($D95="",0,(($U95+IF(OR($S95="x",$S95="xx"),1,0))*INDEX($DI$87:$DI$92,MATCH($D95,$DH$87:$DH$92))*$CE$87)) -> 0 | BC95: =IF($D95="",0,INDEX($DK$87:$DK$92,MATCH($D95,$DJ$87:$DJ$92))*$CE$87) -> 0 | BD95: =SUM(AQ95:BC95) -> 0 | BE95: =IF($D95="",0,((IF(OR($V95="x",$V95="xx"),1,0))*INDEX($DM$87:$DM$92,MATCH($D95,$DL$87:$DL$92))*$BR$58)) -> 0
B96: =B95+1 -> 11 | G96: =F96*D96 -> 0 | W96: =IF($I96="x",IF($D96="",0,INDEX($BJ$87:$BJ$92,MATCH($D96,$BI$87:$BI$92,1))),0) -> 0 | X96: =IF($J96="x",IF($D96="",0,INDEX($BL$87:$BL$92,MATCH($D96,$BK$87:$BK$92,1))),0) -> 0 | Y96: =IF($K96="x",IF($D96="",0,INDEX($BN$87:$BN$92,MATCH($D96,$BM$87:$BM$92,1))),0) -> 0 | Z96: =IF($L96="x",IF($D96="",0,INDEX($BP$87:$BP$92,MATCH($D96,$BO$87:$BO$92,1))),0) -> 0 | AA96: =IF($M96="x",IF($D96="",0,INDEX($BR$87:$BR$92,MATCH($D96,$BQ$87:$BQ$92,1))),0) -> 0 | AB96: =IF($N96="x",IF($D96="",0,INDEX($BT$87:$BT$92,MATCH($D96,$BS$87:$BS$92,1))),0) -> 0 | AC96: =IF(OR($K96="x",$M96="x"),IF($D96="",0,INDEX($BV$87:$BV$92,MATCH($D96,$BU$87:$BU$92,1))),0)+IF(OR($L96="x",$N96="x"),IF($D96="",0,INDEX($BW$87:$BW$92,MATCH($D96,$BU$87:$BU$92,1))),0) -> 0 | AD96: =IF($O96="x",IF($D96="",0,INDEX($BY$87:$BY$92,MATCH($D96,$BX$87:$BX$92,1))),0) -> 0 | AE96: =IF($P96="x",IF($D96="",0,$CB$87),0) -> 0 | AF96: =IF($D96="",0,IF(Q96="x",$CA$89,0)) -> 0 | AG96: =IF($D96="",0,IF(R96="x",$CA$91,0)) -> 0 | AH96: =IF($S96="x",IF($D96="",0,$BZ$87),0) -> 0 | AI96: =IF($T96="x",IF($D96="",0,IF($D96>4,$BZ$89,0)),0) -> 0 | AJ96: =IF($D96="",0,$U96*$BZ$91) -> 0 | AK96: =IF($D96="",0,(U96+IF(AH96>0,1,0))*$CA$87) -> 0 | AL96: =G96+H96 -> 0 | AM96: =SUM(W96:AK96) -> 0 | AN96: =IF($E96="xx",(1600*$D96+$AM96),SUM(AL96:AM96))*$AN$84 -> 0 | AO96: =SUM(AL96:AN96) -> 0 | AP96: =IF($V96="x",IF($D96="",0,INDEX($CD$87:$CD$92,MATCH($D96,$CC$87:$CC$92,1))),0) -> 0 | AQ96: =IF($D96="",0,INDEX($CG$87:$CG$92,MATCH($D96,$CF$87:$CF$92))*$CE$87) -> 0 | AR96: =IF($D96="",0,IF(OR($I96="x",$I96="xx"),INDEX($CI$87:$CI$92,MATCH($D96,$CH$87:$CH$92))*$CE$87,0)) -> 0 | AS96: =IF($D96="",0,IF(OR($J96="x",$J96="xx"),INDEX($CK$87:$CK$92,MATCH($D96,$CJ$87:$CJ$92))*$CE$87,0)) -> 0 | AT96: =IF($D96="",0,IF(OR($M96="x",$M96="xx"),INDEX($CQ$87:$CQ$92,MATCH($D96,$CP$87:$CP$92))*$CE$87,0))+IF($D96="",0,IF(OR($N96="x",$N96="xx"),INDEX($CS$87:$CS$92,MATCH($D96,$CR$87:$CR$92))*$CE$87,0))+IF($D96="",0,IF(OR($K96="x",$K96="xx"),INDEX($CM$87:$CM$92,MATCH($D96,$CL$87:$CL$92))*$CE$87,0))+IF($D96="",0,IF(OR($L96="x",$L96="xx"),INDEX($CO$87:$CO$92,MATCH($D96,$CN$87:$CN$92))*$CE$87,0)) -> 0 | AU96: =IF($D96="",0,IF(OR($O96="x",$O96="xx"),INDEX($CU$87:$CU$92,MATCH($D96,$CT$87:$CT$92))*$CE$87,0)) -> 0 | AV96: =IF($D96="",0,IF(OR($P96="x",$P96="xx"),INDEX($CW$87:$CW$92,MATCH($D96,$CV$87:$CV$92))*$CE$87,0)) -> 0 | AW96: =IF($D96="",0,IF(OR($Q96="x",$Q96="xx"),INDEX($CY$87:$CY$92,MATCH($D96,$CX$87:$CX$92))*$CE$87,0)) -> 0 | AX96: =IF($D96="",0,IF(OR($R96="x",$R96="xx"),INDEX($DA$87:$DA$92,MATCH($D96,$CZ$87:$CZ$92))*$CE$87,0)) -> 0 | AY96: =IF($D96="",0,IF(OR($S96="x",$S96="xx"),INDEX($DC$87:$DC$92,MATCH($D96,$DB$87:$DB$92))*$CE$87,0)) -> 0 | AZ96: =IF($D96="",0,IF(OR($T96="x",$T96="xx"),IF($D96>4,INDEX($DE$87:$DE$92,MATCH($D96,$DD$87:$DD$92))*$CE$87,0),0)) -> 0 | BA96: =IF($D96="",0,($U96*INDEX($DG$87:$DG$92,MATCH($D96,$DF$87:$DF$92))*$CE$87)) -> 0 | BB96: =IF($D96="",0,(($U96+IF(OR($S96="x",$S96="xx"),1,0))*INDEX($DI$87:$DI$92,MATCH($D96,$DH$87:$DH$92))*$CE$87)) -> 0 | BC96: =IF($D96="",0,INDEX($DK$87:$DK$92,MATCH($D96,$DJ$87:$DJ$92))*$CE$87) -> 0 | BD96: =SUM(AQ96:BC96) -> 0 | BE96: =IF($D96="",0,((IF(OR($V96="x",$V96="xx"),1,0))*INDEX($DM$87:$DM$92,MATCH($D96,$DL$87:$DL$92))*$BR$58)) -> 0
B97: =B96+1 -> 12 | G97: =F97*D97 -> 0 | W97: =IF($I97="x",IF($D97="",0,INDEX($BJ$87:$BJ$92,MATCH($D97,$BI$87:$BI$92,1))),0) -> 0 | X97: =IF($J97="x",IF($D97="",0,INDEX($BL$87:$BL$92,MATCH($D97,$BK$87:$BK$92,1))),0) -> 0 | Y97: =IF($K97="x",IF($D97="",0,INDEX($BN$87:$BN$92,MATCH($D97,$BM$87:$BM$92,1))),0) -> 0 | Z97: =IF($L97="x",IF($D97="",0,INDEX($BP$87:$BP$92,MATCH($D97,$BO$87:$BO$92,1))),0) -> 0 | AA97: =IF($M97="x",IF($D97="",0,INDEX($BR$87:$BR$92,MATCH($D97,$BQ$87:$BQ$92,1))),0) -> 0 | AB97: =IF($N97="x",IF($D97="",0,INDEX($BT$87:$BT$92,MATCH($D97,$BS$87:$BS$92,1))),0) -> 0 | AC97: =IF(OR($K97="x",$M97="x"),IF($D97="",0,INDEX($BV$87:$BV$92,MATCH($D97,$BU$87:$BU$92,1))),0)+IF(OR($L97="x",$N97="x"),IF($D97="",0,INDEX($BW$87:$BW$92,MATCH($D97,$BU$87:$BU$92,1))),0) -> 0 | AD97: =IF($O97="x",IF($D97="",0,INDEX($BY$87:$BY$92,MATCH($D97,$BX$87:$BX$92,1))),0) -> 0 | AE97: =IF($P97="x",IF($D97="",0,$CB$87),0) -> 0 | AF97: =IF($D97="",0,IF(Q97="x",$CA$89,0)) -> 0 | AG97: =IF($D97="",0,IF(R97="x",$CA$91,0)) -> 0 | AH97: =IF($S97="x",IF($D97="",0,$BZ$87),0) -> 0 | AI97: =IF($T97="x",IF($D97="",0,IF($D97>4,$BZ$89,0)),0) -> 0 | AJ97: =IF($D97="",0,$U97*$BZ$91) -> 0 | AK97: =IF($D97="",0,(U97+IF(AH97>0,1,0))*$CA$87) -> 0 | AL97: =G97+H97 -> 0 | AM97: =SUM(W97:AK97) -> 0 | AN97: =IF($E97="xx",(1600*$D97+$AM97),SUM(AL97:AM97))*$AN$84 -> 0 | AO97: =SUM(AL97:AN97) -> 0 | AP97: =IF($V97="x",IF($D97="",0,INDEX($CD$87:$CD$92,MATCH($D97,$CC$87:$CC$92,1))),0) -> 0 | AQ97: =IF($D97="",0,INDEX($CG$87:$CG$92,MATCH($D97,$CF$87:$CF$92))*$CE$87) -> 0 | AR97: =IF($D97="",0,IF(OR($I97="x",$I97="xx"),INDEX($CI$87:$CI$92,MATCH($D97,$CH$87:$CH$92))*$CE$87,0)) -> 0 | AS97: =IF($D97="",0,IF(OR($J97="x",$J97="xx"),INDEX($CK$87:$CK$92,MATCH($D97,$CJ$87:$CJ$92))*$CE$87,0)) -> 0 | AT97: =IF($D97="",0,IF(OR($M97="x",$M97="xx"),INDEX($CQ$87:$CQ$92,MATCH($D97,$CP$87:$CP$92))*$CE$87,0))+IF($D97="",0,IF(OR($N97="x",$N97="xx"),INDEX($CS$87:$CS$92,MATCH($D97,$CR$87:$CR$92))*$CE$87,0))+IF($D97="",0,IF(OR($K97="x",$K97="xx"),INDEX($CM$87:$CM$92,MATCH($D97,$CL$87:$CL$92))*$CE$87,0))+IF($D97="",0,IF(OR($L97="x",$L97="xx"),INDEX($CO$87:$CO$92,MATCH($D97,$CN$87:$CN$92))*$CE$87,0)) -> 0 | AU97: =IF($D97="",0,IF(OR($O97="x",$O97="xx"),INDEX($CU$87:$CU$92,MATCH($D97,$CT$87:$CT$92))*$CE$87,0)) -> 0 | AV97: =IF($D97="",0,IF(OR($P97="x",$P97="xx"),INDEX($CW$87:$CW$92,MATCH($D97,$CV$87:$CV$92))*$CE$87,0)) -> 0 | AW97: =IF($D97="",0,IF(OR($Q97="x",$Q97="xx"),INDEX($CY$87:$CY$92,MATCH($D97,$CX$87:$CX$92))*$CE$87,0)) -> 0 | AX97: =IF($D97="",0,IF(OR($R97="x",$R97="xx"),INDEX($DA$87:$DA$92,MATCH($D97,$CZ$87:$CZ$92))*$CE$87,0)) -> 0 | AY97: =IF($D97="",0,IF(OR($S97="x",$S97="xx"),INDEX($DC$87:$DC$92,MATCH($D97,$DB$87:$DB$92))*$CE$87,0)) -> 0 | AZ97: =IF($D97="",0,IF(OR($T97="x",$T97="xx"),IF($D97>4,INDEX($DE$87:$DE$92,MATCH($D97,$DD$87:$DD$92))*$CE$87,0),0)) -> 0 | BA97: =IF($D97="",0,($U97*INDEX($DG$87:$DG$92,MATCH($D97,$DF$87:$DF$92))*$CE$87)) -> 0 | BB97: =IF($D97="",0,(($U97+IF(OR($S97="x",$S97="xx"),1,0))*INDEX($DI$87:$DI$92,MATCH($D97,$DH$87:$DH$92))*$CE$87)) -> 0 | BC97: =IF($D97="",0,INDEX($DK$87:$DK$92,MATCH($D97,$DJ$87:$DJ$92))*$CE$87) -> 0 | BD97: =SUM(AQ97:BC97) -> 0 | BE97: =IF($D97="",0,((IF(OR($V97="x",$V97="xx"),1,0))*INDEX($DM$87:$DM$92,MATCH($D97,$DL$87:$DL$92))*$BR$58)) -> 0
B98: =B97+1 -> 13 | G98: =F98*D98 -> 0 | W98: =IF($I98="x",IF($D98="",0,INDEX($BJ$87:$BJ$92,MATCH($D98,$BI$87:$BI$92,1))),0) -> 0 | X98: =IF($J98="x",IF($D98="",0,INDEX($BL$87:$BL$92,MATCH($D98,$BK$87:$BK$92,1))),0) -> 0 | Y98: =IF($K98="x",IF($D98="",0,INDEX($BN$87:$BN$92,MATCH($D98,$BM$87:$BM$92,1))),0) -> 0 | Z98: =IF($L98="x",IF($D98="",0,INDEX($BP$87:$BP$92,MATCH($D98,$BO$87:$BO$92,1))),0) -> 0 | AA98: =IF($M98="x",IF($D98="",0,INDEX($BR$87:$BR$92,MATCH($D98,$BQ$87:$BQ$92,1))),0) -> 0 | AB98: =IF($N98="x",IF($D98="",0,INDEX($BT$87:$BT$92,MATCH($D98,$BS$87:$BS$92,1))),0) -> 0 | AC98: =IF(OR($K98="x",$M98="x"),IF($D98="",0,INDEX($BV$87:$BV$92,MATCH($D98,$BU$87:$BU$92,1))),0)+IF(OR($L98="x",$N98="x"),IF($D98="",0,INDEX($BW$87:$BW$92,MATCH($D98,$BU$87:$BU$92,1))),0) -> 0 | AD98: =IF($O98="x",IF($D98="",0,INDEX($BY$87:$BY$92,MATCH($D98,$BX$87:$BX$92,1))),0) -> 0 | AE98: =IF($P98="x",IF($D98="",0,$CB$87),0) -> 0 | AF98: =IF($D98="",0,IF(Q98="x",$CA$89,0)) -> 0 | AG98: =IF($D98="",0,IF(R98="x",$CA$91,0)) -> 0 | AH98: =IF($S98="x",IF($D98="",0,$BZ$87),0) -> 0 | AI98: =IF($T98="x",IF($D98="",0,IF($D98>4,$BZ$89,0)),0) -> 0 | AJ98: =IF($D98="",0,$U98*$BZ$91) -> 0 | AK98: =IF($D98="",0,(U98+IF(AH98>0,1,0))*$CA$87) -> 0 | AL98: =G98+H98 -> 0 | AM98: =SUM(W98:AK98) -> 0 | AN98: =IF($E98="xx",(1600*$D98+$AM98),SUM(AL98:AM98))*$AN$84 -> 0 | AO98: =SUM(AL98:AN98) -> 0 | AP98: =IF($V98="x",IF($D98="",0,INDEX($CD$87:$CD$92,MATCH($D98,$CC$87:$CC$92,1))),0) -> 0 | AQ98: =IF($D98="",0,INDEX($CG$87:$CG$92,MATCH($D98,$CF$87:$CF$92))*$CE$87) -> 0 | AR98: =IF($D98="",0,IF(OR($I98="x",$I98="xx"),INDEX($CI$87:$CI$92,MATCH($D98,$CH$87:$CH$92))*$CE$87,0)) -> 0 | AS98: =IF($D98="",0,IF(OR($J98="x",$J98="xx"),INDEX($CK$87:$CK$92,MATCH($D98,$CJ$87:$CJ$92))*$CE$87,0)) -> 0 | AT98: =IF($D98="",0,IF(OR($M98="x",$M98="xx"),INDEX($CQ$87:$CQ$92,MATCH($D98,$CP$87:$CP$92))*$CE$87,0))+IF($D98="",0,IF(OR($N98="x",$N98="xx"),INDEX($CS$87:$CS$92,MATCH($D98,$CR$87:$CR$92))*$CE$87,0))+IF($D98="",0,IF(OR($K98="x",$K98="xx"),INDEX($CM$87:$CM$92,MATCH($D98,$CL$87:$CL$92))*$CE$87,0))+IF($D98="",0,IF(OR($L98="x",$L98="xx"),INDEX($CO$87:$CO$92,MATCH($D98,$CN$87:$CN$92))*$CE$87,0)) -> 0 | AU98: =IF($D98="",0,IF(OR($O98="x",$O98="xx"),INDEX($CU$87:$CU$92,MATCH($D98,$CT$87:$CT$92))*$CE$87,0)) -> 0 | AV98: =IF($D98="",0,IF(OR($P98="x",$P98="xx"),INDEX($CW$87:$CW$92,MATCH($D98,$CV$87:$CV$92))*$CE$87,0)) -> 0 | AW98: =IF($D98="",0,IF(OR($Q98="x",$Q98="xx"),INDEX($CY$87:$CY$92,MATCH($D98,$CX$87:$CX$92))*$CE$87,0)) -> 0 | AX98: =IF($D98="",0,IF(OR($R98="x",$R98="xx"),INDEX($DA$87:$DA$92,MATCH($D98,$CZ$87:$CZ$92))*$CE$87,0)) -> 0 | AY98: =IF($D98="",0,IF(OR($S98="x",$S98="xx"),INDEX($DC$87:$DC$92,MATCH($D98,$DB$87:$DB$92))*$CE$87,0)) -> 0 | AZ98: =IF($D98="",0,IF(OR($T98="x",$T98="xx"),IF($D98>4,INDEX($DE$87:$DE$92,MATCH($D98,$DD$87:$DD$92))*$CE$87,0),0)) -> 0 | BA98: =IF($D98="",0,($U98*INDEX($DG$87:$DG$92,MATCH($D98,$DF$87:$DF$92))*$CE$87)) -> 0 | BB98: =IF($D98="",0,(($U98+IF(OR($S98="x",$S98="xx"),1,0))*INDEX($DI$87:$DI$92,MATCH($D98,$DH$87:$DH$92))*$CE$87)) -> 0 | BC98: =IF($D98="",0,INDEX($DK$87:$DK$92,MATCH($D98,$DJ$87:$DJ$92))*$CE$87) -> 0 | BD98: =SUM(AQ98:BC98) -> 0 | BE98: =IF($D98="",0,((IF(OR($V98="x",$V98="xx"),1,0))*INDEX($DM$87:$DM$92,MATCH($D98,$DL$87:$DL$92))*$BR$58)) -> 0
B99: =B98+1 -> 14 | G99: =F99*D99 -> 0 | W99: =IF($I99="x",IF($D99="",0,INDEX($BJ$87:$BJ$92,MATCH($D99,$BI$87:$BI$92,1))),0) -> 0 | X99: =IF($J99="x",IF($D99="",0,INDEX($BL$87:$BL$92,MATCH($D99,$BK$87:$BK$92,1))),0) -> 0 | Y99: =IF($K99="x",IF($D99="",0,INDEX($BN$87:$BN$92,MATCH($D99,$BM$87:$BM$92,1))),0) -> 0 | Z99: =IF($L99="x",IF($D99="",0,INDEX($BP$87:$BP$92,MATCH($D99,$BO$87:$BO$92,1))),0) -> 0 | AA99: =IF($M99="x",IF($D99="",0,INDEX($BR$87:$BR$92,MATCH($D99,$BQ$87:$BQ$92,1))),0) -> 0 | AB99: =IF($N99="x",IF($D99="",0,INDEX($BT$87:$BT$92,MATCH($D99,$BS$87:$BS$92,1))),0) -> 0 | AC99: =IF(OR($K99="x",$M99="x"),IF($D99="",0,INDEX($BV$87:$BV$92,MATCH($D99,$BU$87:$BU$92,1))),0)+IF(OR($L99="x",$N99="x"),IF($D99="",0,INDEX($BW$87:$BW$92,MATCH($D99,$BU$87:$BU$92,1))),0) -> 0 | AD99: =IF($O99="x",IF($D99="",0,INDEX($BY$87:$BY$92,MATCH($D99,$BX$87:$BX$92,1))),0) -> 0 | AE99: =IF($P99="x",IF($D99="",0,$CB$87),0) -> 0 | AF99: =IF($D99="",0,IF(Q99="x",$CA$89,0)) -> 0 | AG99: =IF($D99="",0,IF(R99="x",$CA$91,0)) -> 0 | AH99: =IF($S99="x",IF($D99="",0,$BZ$87),0) -> 0 | AI99: =IF($T99="x",IF($D99="",0,IF($D99>4,$BZ$89,0)),0) -> 0 | AJ99: =IF($D99="",0,$U99*$BZ$91) -> 0 | AK99: =IF($D99="",0,(U99+IF(AH99>0,1,0))*$CA$87) -> 0 | AL99: =G99+H99 -> 0 | AM99: =SUM(W99:AK99) -> 0 | AN99: =IF($E99="xx",(1600*$D99+$AM99),SUM(AL99:AM99))*$AN$84 -> 0 | AO99: =SUM(AL99:AN99) -> 0 | AP99: =IF($V99="x",IF($D99="",0,INDEX($CD$87:$CD$92,MATCH($D99,$CC$87:$CC$92,1))),0) -> 0 | AQ99: =IF($D99="",0,INDEX($CG$87:$CG$92,MATCH($D99,$CF$87:$CF$92))*$CE$87) -> 0 | AR99: =IF($D99="",0,IF(OR($I99="x",$I99="xx"),INDEX($CI$87:$CI$92,MATCH($D99,$CH$87:$CH$92))*$CE$87,0)) -> 0 | AS99: =IF($D99="",0,IF(OR($J99="x",$J99="xx"),INDEX($CK$87:$CK$92,MATCH($D99,$CJ$87:$CJ$92))*$CE$87,0)) -> 0 | AT99: =IF($D99="",0,IF(OR($M99="x",$M99="xx"),INDEX($CQ$87:$CQ$92,MATCH($D99,$CP$87:$CP$92))*$CE$87,0))+IF($D99="",0,IF(OR($N99="x",$N99="xx"),INDEX($CS$87:$CS$92,MATCH($D99,$CR$87:$CR$92))*$CE$87,0))+IF($D99="",0,IF(OR($K99="x",$K99="xx"),INDEX($CM$87:$CM$92,MATCH($D99,$CL$87:$CL$92))*$CE$87,0))+IF($D99="",0,IF(OR($L99="x",$L99="xx"),INDEX($CO$87:$CO$92,MATCH($D99,$CN$87:$CN$92))*$CE$87,0)) -> 0 | AU99: =IF($D99="",0,IF(OR($O99="x",$O99="xx"),INDEX($CU$87:$CU$92,MATCH($D99,$CT$87:$CT$92))*$CE$87,0)) -> 0 | AV99: =IF($D99="",0,IF(OR($P99="x",$P99="xx"),INDEX($CW$87:$CW$92,MATCH($D99,$CV$87:$CV$92))*$CE$87,0)) -> 0 | AW99: =IF($D99="",0,IF(OR($Q99="x",$Q99="xx"),INDEX($CY$87:$CY$92,MATCH($D99,$CX$87:$CX$92))*$CE$87,0)) -> 0 | AX99: =IF($D99="",0,IF(OR($R99="x",$R99="xx"),INDEX($DA$87:$DA$92,MATCH($D99,$CZ$87:$CZ$92))*$CE$87,0)) -> 0 | AY99: =IF($D99="",0,IF(OR($S99="x",$S99="xx"),INDEX($DC$87:$DC$92,MATCH($D99,$DB$87:$DB$92))*$CE$87,0)) -> 0 | AZ99: =IF($D99="",0,IF(OR($T99="x",$T99="xx"),IF($D99>4,INDEX($DE$87:$DE$92,MATCH($D99,$DD$87:$DD$92))*$CE$87,0),0)) -> 0 | BA99: =IF($D99="",0,($U99*INDEX($DG$87:$DG$92,MATCH($D99,$DF$87:$DF$92))*$CE$87)) -> 0 | BB99: =IF($D99="",0,(($U99+IF(OR($S99="x",$S99="xx"),1,0))*INDEX($DI$87:$DI$92,MATCH($D99,$DH$87:$DH$92))*$CE$87)) -> 0 | BC99: =IF($D99="",0,INDEX($DK$87:$DK$92,MATCH($D99,$DJ$87:$DJ$92))*$CE$87) -> 0 | BD99: =SUM(AQ99:BC99) -> 0 | BE99: =IF($D99="",0,((IF(OR($V99="x",$V99="xx"),1,0))*INDEX($DM$87:$DM$92,MATCH($D99,$DL$87:$DL$92))*$BR$58)) -> 0
B100: =B99+1 -> 15 | G100: =F100*D100 -> 0 | W100: =IF($I100="x",IF($D100="",0,INDEX($BJ$87:$BJ$92,MATCH($D100,$BI$87:$BI$92,1))),0) -> 0 | X100: =IF($J100="x",IF($D100="",0,INDEX($BL$87:$BL$92,MATCH($D100,$BK$87:$BK$92,1))),0) -> 0 | Y100: =IF($K100="x",IF($D100="",0,INDEX($BN$87:$BN$92,MATCH($D100,$BM$87:$BM$92,1))),0) -> 0 | Z100: =IF($L100="x",IF($D100="",0,INDEX($BP$87:$BP$92,MATCH($D100,$BO$87:$BO$92,1))),0) -> 0 | AA100: =IF($M100="x",IF($D100="",0,INDEX($BR$87:$BR$92,MATCH($D100,$BQ$87:$BQ$92,1))),0) -> 0 | AB100: =IF($N100="x",IF($D100="",0,INDEX($BT$87:$BT$92,MATCH($D100,$BS$87:$BS$92,1))),0) -> 0 | AC100: =IF(OR($K100="x",$M100="x"),IF($D100="",0,INDEX($BV$87:$BV$92,MATCH($D100,$BU$87:$BU$92,1))),0)+IF(OR($L100="x",$N100="x"),IF($D100="",0,INDEX($BW$87:$BW$92,MATCH($D100,$BU$87:$BU$92,1))),0) -> 0 | AD100: =IF($O100="x",IF($D100="",0,INDEX($BY$87:$BY$92,MATCH($D100,$BX$87:$BX$92,1))),0) -> 0 | AE100: =IF($P100="x",IF($D100="",0,$CB$87),0) -> 0 | AF100: =IF($D100="",0,IF(Q100="x",$CA$89,0)) -> 0 | AG100: =IF($D100="",0,IF(R100="x",$CA$91,0)) -> 0 | AH100: =IF($S100="x",IF($D100="",0,$BZ$87),0) -> 0 | AI100: =IF($T100="x",IF($D100="",0,IF($D100>4,$BZ$89,0)),0) -> 0 | AJ100: =IF($D100="",0,$U100*$BZ$91) -> 0 | AK100: =IF($D100="",0,(U100+IF(AH100>0,1,0))*$CA$87) -> 0 | AL100: =G100+H100 -> 0 | AM100: =SUM(W100:AK100) -> 0 | AN100: =IF($E100="xx",(1600*$D100+$AM100),SUM(AL100:AM100))*$AN$84 -> 0 | AO100: =SUM(AL100:AN100) -> 0 | AP100: =IF($V100="x",IF($D100="",0,INDEX($CD$87:$CD$92,MATCH($D100,$CC$87:$CC$92,1))),0) -> 0 | AQ100: =IF($D100="",0,INDEX($CG$87:$CG$92,MATCH($D100,$CF$87:$CF$92))*$CE$87) -> 0 | AR100: =IF($D100="",0,IF(OR($I100="x",$I100="xx"),INDEX($CI$87:$CI$92,MATCH($D100,$CH$87:$CH$92))*$CE$87,0)) -> 0 | AS100: =IF($D100="",0,IF(OR($J100="x",$J100="xx"),INDEX($CK$87:$CK$92,MATCH($D100,$CJ$87:$CJ$92))*$CE$87,0)) -> 0 | AT100: =IF($D100="",0,IF(OR($M100="x",$M100="xx"),INDEX($CQ$87:$CQ$92,MATCH($D100,$CP$87:$CP$92))*$CE$87,0))+IF($D100="",0,IF(OR($N100="x",$N100="xx"),INDEX($CS$87:$CS$92,MATCH($D100,$CR$87:$CR$92))*$CE$87,0))+IF($D100="",0,IF(OR($K100="x",$K100="xx"),INDEX($CM$87:$CM$92,MATCH($D100,$CL$87:$CL$92))*$CE$87,0))+IF($D100="",0,IF(OR($L100="x",$L100="xx"),INDEX($CO$87:$CO$92,MATCH($D100,$CN$87:$CN$92))*$CE$87,0)) -> 0 | AU100: =IF($D100="",0,IF(OR($O100="x",$O100="xx"),INDEX($CU$87:$CU$92,MATCH($D100,$CT$87:$CT$92))*$CE$87,0)) -> 0 | AV100: =IF($D100="",0,IF(OR($P100="x",$P100="xx"),INDEX($CW$87:$CW$92,MATCH($D100,$CV$87:$CV$92))*$CE$87,0)) -> 0 | AW100: =IF($D100="",0,IF(OR($Q100="x",$Q100="xx"),INDEX($CY$87:$CY$92,MATCH($D100,$CX$87:$CX$92))*$CE$87,0)) -> 0 | AX100: =IF($D100="",0,IF(OR($R100="x",$R100="xx"),INDEX($DA$87:$DA$92,MATCH($D100,$CZ$87:$CZ$92))*$CE$87,0)) -> 0 | AY100: =IF($D100="",0,IF(OR($S100="x",$S100="xx"),INDEX($DC$87:$DC$92,MATCH($D100,$DB$87:$DB$92))*$CE$87,0)) -> 0 | AZ100: =IF($D100="",0,IF(OR($T100="x",$T100="xx"),IF($D100>4,INDEX($DE$87:$DE$92,MATCH($D100,$DD$87:$DD$92))*$CE$87,0),0)) -> 0 | BA100: =IF($D100="",0,($U100*INDEX($DG$87:$DG$92,MATCH($D100,$DF$87:$DF$92))*$CE$87)) -> 0 | BB100: =IF($D100="",0,(($U100+IF(OR($S100="x",$S100="xx"),1,0))*INDEX($DI$87:$DI$92,MATCH($D100,$DH$87:$DH$92))*$CE$87)) -> 0 | BC100: =IF($D100="",0,INDEX($DK$87:$DK$92,MATCH($D100,$DJ$87:$DJ$92))*$CE$87) -> 0 | BD100: =SUM(AQ100:BC100) -> 0 | BE100: =IF($D100="",0,((IF(OR($V100="x",$V100="xx"),1,0))*INDEX($DM$87:$DM$92,MATCH($D100,$DL$87:$DL$92))*$BR$58)) -> 0
B101: =B100+1 -> 16 | G101: =F101*D101 -> 0 | W101: =IF($I101="x",IF($D101="",0,INDEX($BJ$87:$BJ$92,MATCH($D101,$BI$87:$BI$92,1))),0) -> 0 | X101: =IF($J101="x",IF($D101="",0,INDEX($BL$87:$BL$92,MATCH($D101,$BK$87:$BK$92,1))),0) -> 0 | Y101: =IF($K101="x",IF($D101="",0,INDEX($BN$87:$BN$92,MATCH($D101,$BM$87:$BM$92,1))),0) -> 0 | Z101: =IF($L101="x",IF($D101="",0,INDEX($BP$87:$BP$92,MATCH($D101,$BO$87:$BO$92,1))),0) -> 0 | AA101: =IF($M101="x",IF($D101="",0,INDEX($BR$87:$BR$92,MATCH($D101,$BQ$87:$BQ$92,1))),0) -> 0 | AB101: =IF($N101="x",IF($D101="",0,INDEX($BT$87:$BT$92,MATCH($D101,$BS$87:$BS$92,1))),0) -> 0 | AC101: =IF(OR($K101="x",$M101="x"),IF($D101="",0,INDEX($BV$87:$BV$92,MATCH($D101,$BU$87:$BU$92,1))),0)+IF(OR($L101="x",$N101="x"),IF($D101="",0,INDEX($BW$87:$BW$92,MATCH($D101,$BU$87:$BU$92,1))),0) -> 0 | AD101: =IF($O101="x",IF($D101="",0,INDEX($BY$87:$BY$92,MATCH($D101,$BX$87:$BX$92,1))),0) -> 0 | AE101: =IF($P101="x",IF($D101="",0,$CB$87),0) -> 0 | AF101: =IF($D101="",0,IF(Q101="x",$CA$89,0)) -> 0 | AG101: =IF($D101="",0,IF(R101="x",$CA$91,0)) -> 0 | AH101: =IF($S101="x",IF($D101="",0,$BZ$87),0) -> 0 | AI101: =IF($T101="x",IF($D101="",0,IF($D101>4,$BZ$89,0)),0) -> 0 | AJ101: =IF($D101="",0,$U101*$BZ$91) -> 0 | AK101: =IF($D101="",0,(U101+IF(AH101>0,1,0))*$CA$87) -> 0 | AL101: =G101+H101 -> 0 | AM101: =SUM(W101:AK101) -> 0 | AN101: =IF($E101="xx",(1600*$D101+$AM101),SUM(AL101:AM101))*$AN$84 -> 0 | AO101: =SUM(AL101:AN101) -> 0 | AP101: =IF($V101="x",IF($D101="",0,INDEX($CD$87:$CD$92,MATCH($D101,$CC$87:$CC$92,1))),0) -> 0 | AQ101: =IF($D101="",0,INDEX($CG$87:$CG$92,MATCH($D101,$CF$87:$CF$92))*$CE$87) -> 0 | AR101: =IF($D101="",0,IF(OR($I101="x",$I101="xx"),INDEX($CI$87:$CI$92,MATCH($D101,$CH$87:$CH$92))*$CE$87,0)) -> 0 | AS101: =IF($D101="",0,IF(OR($J101="x",$J101="xx"),INDEX($CK$87:$CK$92,MATCH($D101,$CJ$87:$CJ$92))*$CE$87,0)) -> 0 | AT101: =IF($D101="",0,IF(OR($M101="x",$M101="xx"),INDEX($CQ$87:$CQ$92,MATCH($D101,$CP$87:$CP$92))*$CE$87,0))+IF($D101="",0,IF(OR($N101="x",$N101="xx"),INDEX($CS$87:$CS$92,MATCH($D101,$CR$87:$CR$92))*$CE$87,0))+IF($D101="",0,IF(OR($K101="x",$K101="xx"),INDEX($CM$87:$CM$92,MATCH($D101,$CL$87:$CL$92))*$CE$87,0))+IF($D101="",0,IF(OR($L101="x",$L101="xx"),INDEX($CO$87:$CO$92,MATCH($D101,$CN$87:$CN$92))*$CE$87,0)) -> 0 | AU101: =IF($D101="",0,IF(OR($O101="x",$O101="xx"),INDEX($CU$87:$CU$92,MATCH($D101,$CT$87:$CT$92))*$CE$87,0)) -> 0 | AV101: =IF($D101="",0,IF(OR($P101="x",$P101="xx"),INDEX($CW$87:$CW$92,MATCH($D101,$CV$87:$CV$92))*$CE$87,0)) -> 0 | AW101: =IF($D101="",0,IF(OR($Q101="x",$Q101="xx"),INDEX($CY$87:$CY$92,MATCH($D101,$CX$87:$CX$92))*$CE$87,0)) -> 0 | AX101: =IF($D101="",0,IF(OR($R101="x",$R101="xx"),INDEX($DA$87:$DA$92,MATCH($D101,$CZ$87:$CZ$92))*$CE$87,0)) -> 0 | AY101: =IF($D101="",0,IF(OR($S101="x",$S101="xx"),INDEX($DC$87:$DC$92,MATCH($D101,$DB$87:$DB$92))*$CE$87,0)) -> 0 | AZ101: =IF($D101="",0,IF(OR($T101="x",$T101="xx"),IF($D101>4,INDEX($DE$87:$DE$92,MATCH($D101,$DD$87:$DD$92))*$CE$87,0),0)) -> 0 | BA101: =IF($D101="",0,($U101*INDEX($DG$87:$DG$92,MATCH($D101,$DF$87:$DF$92))*$CE$87)) -> 0 | BB101: =IF($D101="",0,(($U101+IF(OR($S101="x",$S101="xx"),1,0))*INDEX($DI$87:$DI$92,MATCH($D101,$DH$87:$DH$92))*$CE$87)) -> 0 | BC101: =IF($D101="",0,INDEX($DK$87:$DK$92,MATCH($D101,$DJ$87:$DJ$92))*$CE$87) -> 0 | BD101: =SUM(AQ101:BC101) -> 0 | BE101: =IF($D101="",0,((IF(OR($V101="x",$V101="xx"),1,0))*INDEX($DM$87:$DM$92,MATCH($D101,$DL$87:$DL$92))*$BR$58)) -> 0
B102: =B101+1 -> 17 | G102: =F102*D102 -> 0 | W102: =IF($I102="x",IF($D102="",0,INDEX($BJ$87:$BJ$92,MATCH($D102,$BI$87:$BI$92,1))),0) -> 0 | X102: =IF($J102="x",IF($D102="",0,INDEX($BL$87:$BL$92,MATCH($D102,$BK$87:$BK$92,1))),0) -> 0 | Y102: =IF($K102="x",IF($D102="",0,INDEX($BN$87:$BN$92,MATCH($D102,$BM$87:$BM$92,1))),0) -> 0 | Z102: =IF($L102="x",IF($D102="",0,INDEX($BP$87:$BP$92,MATCH($D102,$BO$87:$BO$92,1))),0) -> 0 | AA102: =IF($M102="x",IF($D102="",0,INDEX($BR$87:$BR$92,MATCH($D102,$BQ$87:$BQ$92,1))),0) -> 0 | AB102: =IF($N102="x",IF($D102="",0,INDEX($BT$87:$BT$92,MATCH($D102,$BS$87:$BS$92,1))),0) -> 0 | AC102: =IF(OR($K102="x",$M102="x"),IF($D102="",0,INDEX($BV$87:$BV$92,MATCH($D102,$BU$87:$BU$92,1))),0)+IF(OR($L102="x",$N102="x"),IF($D102="",0,INDEX($BW$87:$BW$92,MATCH($D102,$BU$87:$BU$92,1))),0) -> 0 | AD102: =IF($O102="x",IF($D102="",0,INDEX($BY$87:$BY$92,MATCH($D102,$BX$87:$BX$92,1))),0) -> 0 | AE102: =IF($P102="x",IF($D102="",0,$CB$87),0) -> 0 | AF102: =IF($D102="",0,IF(Q102="x",$CA$89,0)) -> 0 | AG102: =IF($D102="",0,IF(R102="x",$CA$91,0)) -> 0 | AH102: =IF($S102="x",IF($D102="",0,$BZ$87),0) -> 0 | AI102: =IF($T102="x",IF($D102="",0,IF($D102>4,$BZ$89,0)),0) -> 0 | AJ102: =IF($D102="",0,$U102*$BZ$91) -> 0 | AK102: =IF($D102="",0,(U102+IF(AH102>0,1,0))*$CA$87) -> 0 | AL102: =G102+H102 -> 0 | AM102: =SUM(W102:AK102) -> 0 | AN102: =IF($E102="xx",(1600*$D102+$AM102),SUM(AL102:AM102))*$AN$84 -> 0 | AO102: =SUM(AL102:AN102) -> 0 | AP102: =IF($V102="x",IF($D102="",0,INDEX($CD$87:$CD$92,MATCH($D102,$CC$87:$CC$92,1))),0) -> 0 | AQ102: =IF($D102="",0,INDEX($CG$87:$CG$92,MATCH($D102,$CF$87:$CF$92))*$CE$87) -> 0 | AR102: =IF($D102="",0,IF(OR($I102="x",$I102="xx"),INDEX($CI$87:$CI$92,MATCH($D102,$CH$87:$CH$92))*$CE$87,0)) -> 0 | AS102: =IF($D102="",0,IF(OR($J102="x",$J102="xx"),INDEX($CK$87:$CK$92,MATCH($D102,$CJ$87:$CJ$92))*$CE$87,0)) -> 0 | AT102: =IF($D102="",0,IF(OR($M102="x",$M102="xx"),INDEX($CQ$87:$CQ$92,MATCH($D102,$CP$87:$CP$92))*$CE$87,0))+IF($D102="",0,IF(OR($N102="x",$N102="xx"),INDEX($CS$87:$CS$92,MATCH($D102,$CR$87:$CR$92))*$CE$87,0))+IF($D102="",0,IF(OR($K102="x",$K102="xx"),INDEX($CM$87:$CM$92,MATCH($D102,$CL$87:$CL$92))*$CE$87,0))+IF($D102="",0,IF(OR($L102="x",$L102="xx"),INDEX($CO$87:$CO$92,MATCH($D102,$CN$87:$CN$92))*$CE$87,0)) -> 0 | AU102: =IF($D102="",0,IF(OR($O102="x",$O102="xx"),INDEX($CU$87:$CU$92,MATCH($D102,$CT$87:$CT$92))*$CE$87,0)) -> 0 | AV102: =IF($D102="",0,IF(OR($P102="x",$P102="xx"),INDEX($CW$87:$CW$92,MATCH($D102,$CV$87:$CV$92))*$CE$87,0)) -> 0 | AW102: =IF($D102="",0,IF(OR($Q102="x",$Q102="xx"),INDEX($CY$87:$CY$92,MATCH($D102,$CX$87:$CX$92))*$CE$87,0)) -> 0 | AX102: =IF($D102="",0,IF(OR($R102="x",$R102="xx"),INDEX($DA$87:$DA$92,MATCH($D102,$CZ$87:$CZ$92))*$CE$87,0)) -> 0 | AY102: =IF($D102="",0,IF(OR($S102="x",$S102="xx"),INDEX($DC$87:$DC$92,MATCH($D102,$DB$87:$DB$92))*$CE$87,0)) -> 0 | AZ102: =IF($D102="",0,IF(OR($T102="x",$T102="xx"),IF($D102>4,INDEX($DE$87:$DE$92,MATCH($D102,$DD$87:$DD$92))*$CE$87,0),0)) -> 0 | BA102: =IF($D102="",0,($U102*INDEX($DG$87:$DG$92,MATCH($D102,$DF$87:$DF$92))*$CE$87)) -> 0 | BB102: =IF($D102="",0,(($U102+IF(OR($S102="x",$S102="xx"),1,0))*INDEX($DI$87:$DI$92,MATCH($D102,$DH$87:$DH$92))*$CE$87)) -> 0 | BC102: =IF($D102="",0,INDEX($DK$87:$DK$92,MATCH($D102,$DJ$87:$DJ$92))*$CE$87) -> 0 | BD102: =SUM(AQ102:BC102) -> 0 | BE102: =IF($D102="",0,((IF(OR($V102="x",$V102="xx"),1,0))*INDEX($DM$87:$DM$92,MATCH($D102,$DL$87:$DL$92))*$BR$58)) -> 0
B103: =B102+1 -> 18 | G103: =F103*D103 -> 0 | W103: =IF($I103="x",IF($D103="",0,INDEX($BJ$87:$BJ$92,MATCH($D103,$BI$87:$BI$92,1))),0) -> 0 | X103: =IF($J103="x",IF($D103="",0,INDEX($BL$87:$BL$92,MATCH($D103,$BK$87:$BK$92,1))),0) -> 0 | Y103: =IF($K103="x",IF($D103="",0,INDEX($BN$87:$BN$92,MATCH($D103,$BM$87:$BM$92,1))),0) -> 0 | Z103: =IF($L103="x",IF($D103="",0,INDEX($BP$87:$BP$92,MATCH($D103,$BO$87:$BO$92,1))),0) -> 0 | AA103: =IF($M103="x",IF($D103="",0,INDEX($BR$87:$BR$92,MATCH($D103,$BQ$87:$BQ$92,1))),0) -> 0 | AB103: =IF($N103="x",IF($D103="",0,INDEX($BT$87:$BT$92,MATCH($D103,$BS$87:$BS$92,1))),0) -> 0 | AC103: =IF(OR($K103="x",$M103="x"),IF($D103="",0,INDEX($BV$87:$BV$92,MATCH($D103,$BU$87:$BU$92,1))),0)+IF(OR($L103="x",$N103="x"),IF($D103="",0,INDEX($BW$87:$BW$92,MATCH($D103,$BU$87:$BU$92,1))),0) -> 0 | AD103: =IF($O103="x",IF($D103="",0,INDEX($BY$87:$BY$92,MATCH($D103,$BX$87:$BX$92,1))),0) -> 0 | AE103: =IF($P103="x",IF($D103="",0,$CB$87),0) -> 0 | AF103: =IF($D103="",0,IF(Q103="x",$CA$89,0)) -> 0 | AG103: =IF($D103="",0,IF(R103="x",$CA$91,0)) -> 0 | AH103: =IF($S103="x",IF($D103="",0,$BZ$87),0) -> 0 | AI103: =IF($T103="x",IF($D103="",0,IF($D103>4,$BZ$89,0)),0) -> 0 | AJ103: =IF($D103="",0,$U103*$BZ$91) -> 0 | AK103: =IF($D103="",0,(U103+IF(AH103>0,1,0))*$CA$87) -> 0 | AL103: =G103+H103 -> 0 | AM103: =SUM(W103:AK103) -> 0 | AN103: =IF($E103="xx",(1600*$D103+$AM103),SUM(AL103:AM103))*$AN$84 -> 0 | AO103: =SUM(AL103:AN103) -> 0 | AP103: =IF($V103="x",IF($D103="",0,INDEX($CD$87:$CD$92,MATCH($D103,$CC$87:$CC$92,1))),0) -> 0 | AQ103: =IF($D103="",0,INDEX($CG$87:$CG$92,MATCH($D103,$CF$87:$CF$92))*$CE$87) -> 0 | AR103: =IF($D103="",0,IF(OR($I103="x",$I103="xx"),INDEX($CI$87:$CI$92,MATCH($D103,$CH$87:$CH$92))*$CE$87,0)) -> 0 | AS103: =IF($D103="",0,IF(OR($J103="x",$J103="xx"),INDEX($CK$87:$CK$92,MATCH($D103,$CJ$87:$CJ$92))*$CE$87,0)) -> 0 | AT103: =IF($D103="",0,IF(OR($M103="x",$M103="xx"),INDEX($CQ$87:$CQ$92,MATCH($D103,$CP$87:$CP$92))*$CE$87,0))+IF($D103="",0,IF(OR($N103="x",$N103="xx"),INDEX($CS$87:$CS$92,MATCH($D103,$CR$87:$CR$92))*$CE$87,0))+IF($D103="",0,IF(OR($K103="x",$K103="xx"),INDEX($CM$87:$CM$92,MATCH($D103,$CL$87:$CL$92))*$CE$87,0))+IF($D103="",0,IF(OR($L103="x",$L103="xx"),INDEX($CO$87:$CO$92,MATCH($D103,$CN$87:$CN$92))*$CE$87,0)) -> 0 | AU103: =IF($D103="",0,IF(OR($O103="x",$O103="xx"),INDEX($CU$87:$CU$92,MATCH($D103,$CT$87:$CT$92))*$CE$87,0)) -> 0 | AV103: =IF($D103="",0,IF(OR($P103="x",$P103="xx"),INDEX($CW$87:$CW$92,MATCH($D103,$CV$87:$CV$92))*$CE$87,0)) -> 0 | AW103: =IF($D103="",0,IF(OR($Q103="x",$Q103="xx"),INDEX($CY$87:$CY$92,MATCH($D103,$CX$87:$CX$92))*$CE$87,0)) -> 0 | AX103: =IF($D103="",0,IF(OR($R103="x",$R103="xx"),INDEX($DA$87:$DA$92,MATCH($D103,$CZ$87:$CZ$92))*$CE$87,0)) -> 0 | AY103: =IF($D103="",0,IF(OR($S103="x",$S103="xx"),INDEX($DC$87:$DC$92,MATCH($D103,$DB$87:$DB$92))*$CE$87,0)) -> 0 | AZ103: =IF($D103="",0,IF(OR($T103="x",$T103="xx"),IF($D103>4,INDEX($DE$87:$DE$92,MATCH($D103,$DD$87:$DD$92))*$CE$87,0),0)) -> 0 | BA103: =IF($D103="",0,($U103*INDEX($DG$87:$DG$92,MATCH($D103,$DF$87:$DF$92))*$CE$87)) -> 0 | BB103: =IF($D103="",0,(($U103+IF(OR($S103="x",$S103="xx"),1,0))*INDEX($DI$87:$DI$92,MATCH($D103,$DH$87:$DH$92))*$CE$87)) -> 0 | BC103: =IF($D103="",0,INDEX($DK$87:$DK$92,MATCH($D103,$DJ$87:$DJ$92))*$CE$87) -> 0 | BD103: =SUM(AQ103:BC103) -> 0 | BE103: =IF($D103="",0,((IF(OR($V103="x",$V103="xx"),1,0))*INDEX($DM$87:$DM$92,MATCH($D103,$DL$87:$DL$92))*$BR$58)) -> 0
B104: =B103+1 -> 19 | G104: =F104*D104 -> 0 | W104: =IF($I104="x",IF($D104="",0,INDEX($BJ$87:$BJ$92,MATCH($D104,$BI$87:$BI$92,1))),0) -> 0 | X104: =IF($J104="x",IF($D104="",0,INDEX($BL$87:$BL$92,MATCH($D104,$BK$87:$BK$92,1))),0) -> 0 | Y104: =IF($K104="x",IF($D104="",0,INDEX($BN$87:$BN$92,MATCH($D104,$BM$87:$BM$92,1))),0) -> 0 | Z104: =IF($L104="x",IF($D104="",0,INDEX($BP$87:$BP$92,MATCH($D104,$BO$87:$BO$92,1))),0) -> 0 | AA104: =IF($M104="x",IF($D104="",0,INDEX($BR$87:$BR$92,MATCH($D104,$BQ$87:$BQ$92,1))),0) -> 0 | AB104: =IF($N104="x",IF($D104="",0,INDEX($BT$87:$BT$92,MATCH($D104,$BS$87:$BS$92,1))),0) -> 0 | AC104: =IF(OR($K104="x",$M104="x"),IF($D104="",0,INDEX($BV$87:$BV$92,MATCH($D104,$BU$87:$BU$92,1))),0)+IF(OR($L104="x",$N104="x"),IF($D104="",0,INDEX($BW$87:$BW$92,MATCH($D104,$BU$87:$BU$92,1))),0) -> 0 | AD104: =IF($O104="x",IF($D104="",0,INDEX($BY$87:$BY$92,MATCH($D104,$BX$87:$BX$92,1))),0) -> 0 | AE104: =IF($P104="x",IF($D104="",0,$CB$87),0) -> 0 | AF104: =IF($D104="",0,IF(Q104="x",$CA$89,0)) -> 0 | AG104: =IF($D104="",0,IF(R104="x",$CA$91,0)) -> 0 | AH104: =IF($S104="x",IF($D104="",0,$BZ$87),0) -> 0 | AI104: =IF($T104="x",IF($D104="",0,IF($D104>4,$BZ$89,0)),0) -> 0 | AJ104: =IF($D104="",0,$U104*$BZ$91) -> 0 | AK104: =IF($D104="",0,(U104+IF(AH104>0,1,0))*$CA$87) -> 0 | AL104: =G104+H104 -> 0 | AM104: =SUM(W104:AK104) -> 0 | AN104: =IF($E104="xx",(1600*$D104+$AM104),SUM(AL104:AM104))*$AN$84 -> 0 | AO104: =SUM(AL104:AN104) -> 0 | AP104: =IF($V104="x",IF($D104="",0,INDEX($CD$87:$CD$92,MATCH($D104,$CC$87:$CC$92,1))),0) -> 0 | AQ104: =IF($D104="",0,INDEX($CG$87:$CG$92,MATCH($D104,$CF$87:$CF$92))*$CE$87) -> 0 | AR104: =IF($D104="",0,IF(OR($I104="x",$I104="xx"),INDEX($CI$87:$CI$92,MATCH($D104,$CH$87:$CH$92))*$CE$87,0)) -> 0 | AS104: =IF($D104="",0,IF(OR($J104="x",$J104="xx"),INDEX($CK$87:$CK$92,MATCH($D104,$CJ$87:$CJ$92))*$CE$87,0)) -> 0 | AT104: =IF($D104="",0,IF(OR($M104="x",$M104="xx"),INDEX($CQ$87:$CQ$92,MATCH($D104,$CP$87:$CP$92))*$CE$87,0))+IF($D104="",0,IF(OR($N104="x",$N104="xx"),INDEX($CS$87:$CS$92,MATCH($D104,$CR$87:$CR$92))*$CE$87,0))+IF($D104="",0,IF(OR($K104="x",$K104="xx"),INDEX($CM$87:$CM$92,MATCH($D104,$CL$87:$CL$92))*$CE$87,0))+IF($D104="",0,IF(OR($L104="x",$L104="xx"),INDEX($CO$87:$CO$92,MATCH($D104,$CN$87:$CN$92))*$CE$87,0)) -> 0 | AU104: =IF($D104="",0,IF(OR($O104="x",$O104="xx"),INDEX($CU$87:$CU$92,MATCH($D104,$CT$87:$CT$92))*$CE$87,0)) -> 0 | AV104: =IF($D104="",0,IF(OR($P104="x",$P104="xx"),INDEX($CW$87:$CW$92,MATCH($D104,$CV$87:$CV$92))*$CE$87,0)) -> 0 | AW104: =IF($D104="",0,IF(OR($Q104="x",$Q104="xx"),INDEX($CY$87:$CY$92,MATCH($D104,$CX$87:$CX$92))*$CE$87,0)) -> 0 | AX104: =IF($D104="",0,IF(OR($R104="x",$R104="xx"),INDEX($DA$87:$DA$92,MATCH($D104,$CZ$87:$CZ$92))*$CE$87,0)) -> 0 | AY104: =IF($D104="",0,IF(OR($S104="x",$S104="xx"),INDEX($DC$87:$DC$92,MATCH($D104,$DB$87:$DB$92))*$CE$87,0)) -> 0 | AZ104: =IF($D104="",0,IF(OR($T104="x",$T104="xx"),IF($D104>4,INDEX($DE$87:$DE$92,MATCH($D104,$DD$87:$DD$92))*$CE$87,0),0)) -> 0 | BA104: =IF($D104="",0,($U104*INDEX($DG$87:$DG$92,MATCH($D104,$DF$87:$DF$92))*$CE$87)) -> 0 | BB104: =IF($D104="",0,(($U104+IF(OR($S104="x",$S104="xx"),1,0))*INDEX($DI$87:$DI$92,MATCH($D104,$DH$87:$DH$92))*$CE$87)) -> 0 | BC104: =IF($D104="",0,INDEX($DK$87:$DK$92,MATCH($D104,$DJ$87:$DJ$92))*$CE$87) -> 0 | BD104: =SUM(AQ104:BC104) -> 0 | BE104: =IF($D104="",0,((IF(OR($V104="x",$V104="xx"),1,0))*INDEX($DM$87:$DM$92,MATCH($D104,$DL$87:$DL$92))*$BR$58)) -> 0
... B110: =B109+1 -> 25 | G110: =F110*D110 -> 0 | W110: =IF($I110="x",IF($D110="",0,INDEX($BJ$87:$BJ$92,MATCH($D110,$BI$87:$BI$92,1))),0) -> 0 | X110: =IF($J110="x",IF($D110="",0,INDEX($BL$87:$BL$92,MATCH($D110,$BK$87:$BK$92,1))),0) -> 0 | Y110: =IF($K110="x",IF($D110="",0,INDEX($BN$87:$BN$92,MATCH($D110,$BM$87:$BM$92,1))),0) -> 0 | Z110: =IF($L110="x",IF($D110="",0,INDEX($BP$87:$BP$92,MATCH($D110,$BO$87:$BO$92,1))),0) -> 0 | AA110: =IF($M110="x",IF($D110="",0,INDEX($BR$87:$BR$92,MATCH($D110,$BQ$87:$BQ$92,1))),0) -> 0 | AB110: =IF($N110="x",IF($D110="",0,INDEX($BT$87:$BT$92,MATCH($D110,$BS$87:$BS$92,1))),0) -> 0 | AC110: =IF(OR($K110="x",$M110="x"),IF($D110="",0,INDEX($BV$87:$BV$92,MATCH($D110,$BU$87:$BU$92,1))),0)+IF(OR($L110="x",$N110="x"),IF($D110="",0,INDEX($BW$87:$BW$92,MATCH($D110,$BU$87:$BU$92,1))),0) -> 0 | AD110: =IF($O110="x",IF($D110="",0,INDEX($BY$87:$BY$92,MATCH($D110,$BX$87:$BX$92,1))),0) -> 0 | AE110: =IF($P110="x",IF($D110="",0,$CB$87),0) -> 0 | AF110: =IF($D110="",0,IF(Q110="x",$CA$89,0)) -> 0 | AG110: =IF($D110="",0,IF(R110="x",$CA$91,0)) -> 0 | AH110: =IF($S110="x",IF($D110="",0,$BZ$87),0) -> 0 | AI110: =IF($T110="x",IF($D110="",0,IF($D110>4,$BZ$89,0)),0) -> 0 | AJ110: =IF($D110="",0,$U110*$BZ$91) -> 0 | AK110: =IF($D110="",0,(U110+IF(AH110>0,1,0))*$CA$87) -> 0 | AL110: =G110+H110 -> 0 | AM110: =SUM(W110:AK110) -> 0 | AN110: =IF($E110="xx",(1600*$D110+$AM110),SUM(AL110:AM110))*$AN$84 -> 0 | AO110: =SUM(AL110:AN110) -> 0 | AP110: =IF($V110="x",IF($D110="",0,INDEX($CD$87:$CD$92,MATCH($D110,$CC$87:$CC$92,1))),0) -> 0 | AQ110: =IF($D110="",0,INDEX($CG$87:$CG$92,MATCH($D110,$CF$87:$CF$92))*$CE$87) -> 0 | AR110: =IF($D110="",0,IF(OR($I110="x",$I110="xx"),INDEX($CI$87:$CI$92,MATCH($D110,$CH$87:$CH$92))*$CE$87,0)) -> 0 | AS110: =IF($D110="",0,IF(OR($J110="x",$J110="xx"),INDEX($CK$87:$CK$92,MATCH($D110,$CJ$87:$CJ$92))*$CE$87,0)) -> 0 | AT110: =IF($D110="",0,IF(OR($M110="x",$M110="xx"),INDEX($CQ$87:$CQ$92,MATCH($D110,$CP$87:$CP$92))*$CE$87,0))+IF($D110="",0,IF(OR($N110="x",$N110="xx"),INDEX($CS$87:$CS$92,MATCH($D110,$CR$87:$CR$92))*$CE$87,0))+IF($D110="",0,IF(OR($K110="x",$K110="xx"),INDEX($CM$87:$CM$92,MATCH($D110,$CL$87:$CL$92))*$CE$87,0))+IF($D110="",0,IF(OR($L110="x",$L110="xx"),INDEX($CO$87:$CO$92,MATCH($D110,$CN$87:$CN$92))*$CE$87,0)) -> 0 | AU110: =IF($D110="",0,IF(OR($O110="x",$O110="xx"),INDEX($CU$87:$CU$92,MATCH($D110,$CT$87:$CT$92))*$CE$87,0)) -> 0 | AV110: =IF($D110="",0,IF(OR($P110="x",$P110="xx"),INDEX($CW$87:$CW$92,MATCH($D110,$CV$87:$CV$92))*$CE$87,0)) -> 0 | AW110: =IF($D110="",0,IF(OR($Q110="x",$Q110="xx"),INDEX($CY$87:$CY$92,MATCH($D110,$CX$87:$CX$92))*$CE$87,0)) -> 0 | AX110: =IF($D110="",0,IF(OR($R110="x",$R110="xx"),INDEX($DA$87:$DA$92,MATCH($D110,$CZ$87:$CZ$92))*$CE$87,0)) -> 0 | AY110: =IF($D110="",0,IF(OR($S110="x",$S110="xx"),INDEX($DC$87:$DC$92,MATCH($D110,$DB$87:$DB$92))*$CE$87,0)) -> 0 | AZ110: =IF($D110="",0,IF(OR($T110="x",$T110="xx"),IF($D110>4,INDEX($DE$87:$DE$92,MATCH($D110,$DD$87:$DD$92))*$CE$87,0),0)) -> 0 | BA110: =IF($D110="",0,($U110*INDEX($DG$87:$DG$92,MATCH($D110,$DF$87:$DF$92))*$CE$87)) -> 0 | BB110: =IF($D110="",0,(($U110+IF(OR($S110="x",$S110="xx"),1,0))*INDEX($DI$87:$DI$92,MATCH($D110,$DH$87:$DH$92))*$CE$87)) -> 0 | BC110: =IF($D110="",0,INDEX($DK$87:$DK$92,MATCH($D110,$DJ$87:$DJ$92))*$CE$87) -> 0 | BD110: =SUM(AQ110:BC110) -> 0 | BE110: =IF($D110="",0,((IF(OR($V110="x",$V110="xx"),1,0))*INDEX($DM$87:$DM$92,MATCH($D110,$DL$87:$DL$92))*$BR$58)) -> 0
B111: Totals | D111: =SUM(D86:D110) -> 0 | G111: =SUM(G86:G110) -> 0 | H111: =SUM(H86:H110) -> 0 | W111: =SUM(W86:W110) -> 0 | X111: =SUM(X86:X110) -> 0 | Y111: =SUM(Y86:Y110) -> 0 | Z111: =SUM(Z86:Z110) -> 0 | AA111: =SUM(AA86:AA110) -> 0 | AB111: =SUM(AB86:AB110) -> 0 | AC111: =SUM(AC86:AC110) -> 0 | AD111: =SUM(AD86:AD110) -> 0 | ... BE111: =SUM(BE86:BE110) -> 0
E112: vvvvvvvvvv Notes: Selecting "xx" means the owner is providing the equipment | I112: Notes: "x" implies that we need to include an estimate for this item. If the equipment provider has included the item in their package proporsal select "xx". Also use "xx" if the owner is providing but we have to install
B113: Wall Mounted Split Systems | F113: Cost Calculator (Option) | H113: Supplier Quote (Option) | P113: Materials ----------------------------------------------------------------------------------------------------------------------------------------------------------------------------------------------------------------------------------------------------------------------------------------------------------------------------------------------------------------------------------------------------------------------------- | Z113: Misc: | AA113: 0.03 | AC113: Labor----------------------------------------------------------------------------------------------------------------------------------------------------------------------------------------------------------------------------------------------------------------------------------------------------------------------------------------------------------------------------------------------------------------------------- | AO113: Materials Cost | BC113: Labor Cost
B114: Unit | C114: Name | D114: Cool (Tons) | E114: Owner Provided ("xx") | F114: Base Cost ($/ton) | G114: Est. Equipment Cost ($) | H114: Equipment Cost ($) | I114: Condenser Rails ("x/xx") | J114: Cond. Pump ("x/xx") | K114: CU (<100 Ft) ("x/xx") | L114: CU (>=100 Ft) ("x/xx") | M114: PVC Cond. ("x/xx") | N114: CU Cond. ("x/xx") | O114: Thermostat ("x/xx") | P114: Condenser Rails ($) | Q114: Cond. Pump ($) | R114: Copper (<100 Ft) | S114: Copper (>=100 Ft) | T114: Refrigerant Charge ($) | U114: PVC Cond. ($) | V114: CU Cond. ($) | W114: Thermostat ($) | X114: Stat Wire (CO/Temp) ($) | Y114: Base + Quoted Price ($) | Z114: Accessories ($) | AA114: Misc/Consumables | AB114: Total Materials | AC114: Base Equipment ($) | AD114: Condenser Rails ($) | AE114: Cond. Pump ($) | AF114: Copper ($) | AG114: PVC Cond. ($) | AH114: CU Cond. ($) | AI114: Thermostat ($) | AJ114: Stat Wire (CO/Temp) ($) | AK114: Startup & Testing | AL114: Labor Total ($) | AM114: Notes | AP114: Condenser Rails | AR114: Cond. Pump | AT114: Copper (<100 Ft) | AV114: Copper (>100 Ft) | AX114: Refrigerant Supplemental Charge | BD114: Base Unit | BF114: Condenser Rails | BH114: Cond. Pump | BJ114: Copper (< 100') | BL114: Copper (>= 100') | BN114: PVC Condensate | BP114: CU Condensate | BR114: Thermostat | BT114: Stat Wire | BV114: Start Up
B115: 1 | G115: =F115*D115 -> 0 | P115: =IF($I115="x",IF($D115="",0,INDEX($AQ$116:$AQ$121,MATCH($D115,$AP$116:$AP$121,1))),0) -> 0 | Q115: =IF($J115="x",IF($D115="",0,INDEX($AS$116:$AS$121,MATCH($D115,$AR$116:$AR$121,1))),0) -> 0 | R115: =IF($K115="x",IF($D115="",0,INDEX($AU$116:$AU$121,MATCH($D115,$AT$116:$AT$121,1))),0) -> 0 | S115: =IF($L115="x",IF($D115="",0,INDEX($AW$116:$AW$121,MATCH($D115,$AV$116:$AV$121,1))),0) -> 0 | T115: =IF($K115="x",IF($D115="",0,INDEX($AY$116:$AY$121,MATCH($D115,$AX$116:$AX$121,1))),0)+IF($L115="x",IF($D115="",0,INDEX($AZ$116:$AZ$121,MATCH($D115,$AX$116:$AX$121,1))),0) -> 0 | U115: =IF($D115="",0,IF(M115="x",$BB$118,0)) -> 0 | V115: =IF($D115="",0,IF(N115="x",$BB$120,0)) -> 0 | W115: =IF($O115="x",IF($D115="",0,$BA$116),0) -> 0 | X115: =IF($D115="",0,(IF(OR(O115="x",O115="xx"),1,0))*$BB$116) -> 0 | Y115: =G115+H115 -> 0 | Z115: =SUM(P115:X115) -> 0 | AA115: =IF($E115="xx",(1600*$D115+$Z115),SUM(Y115:Z115))*$AA$113 -> 0 | AB115: =SUM(Y115:AA115) -> 0 | AC115: =IF($D115="",0,INDEX($BE$116:$BE$121,MATCH($D115,$BD$116:$BD$121))*$BC$116) -> 0 | AD115: =IF($D115="",0,IF(OR($I115="x",$I115="xx"),INDEX($BG$116:$BG$121,MATCH($D115,$BF$116:$BF$121))*$BC$116,0)) -> 0 | AE115: =IF($D115="",0,IF(OR($J115="x",$J115="xx"),INDEX($BI$116:$BI$121,MATCH($D115,$BH$116:$BH$121))*$BC$116,0)) -> 0 | AF115: =IF($D115="",0,IF(OR($K115="x",$K115="xx"),INDEX($BK$116:$BK$121,MATCH($D115,$BJ$116:$BJ$121))*$CE$87,0))+IF($D115="",0,IF(OR($L115="x",$L115="xx"),INDEX($BM$116:$BM$121,MATCH($D115,$BL$116:$BL$121))*$CE$87,0)) -> 0 | AG115: =IF($D115="",0,IF(OR($M115="x",$M115="xx"),INDEX($BO$116:$BO$121,MATCH($D115,$BN$116:$BN$121))*$BC$116,0)) -> 0 | AH115: =IF($D115="",0,IF(OR($N115="x",$N115="xx"),INDEX($BQ$116:$BQ$121,MATCH($D115,$BP$116:$BP$121))*$BC$116,0)) -> 0 | AI115: =IF($D115="",0,IF(OR($O115="x",$O115="xx"),INDEX($BS$116:$BS$121,MATCH($D115,$BR$116:$BR$121))*$CE$87,0)) -> 0 | AJ115: =IF($D115="",0,((IF(OR($O115="x",$O115="xx"),1,0))*INDEX($BU$116:$BU$121,MATCH($D115,$BT$116:$BT$121))*$BC$116)) -> 0 | AK115: =IF($D115="",0,INDEX($BW$116:$BW$121,MATCH($D115,$BV$116:$BV$121))*$BC$116) -> 0 | AL115: =SUM(AC115:AK115) -> 0 | AO115: Selection | AP115: Size | AQ115: Cost | AR115: Size | AS115: Cost | AT115: Size | AU115: Cost | AV115: Size | AW115: Cost | AX115: Size | AY115: <100 | AZ115: >=100 | BA115: Thermostat | BB115: Stat Wire/Unit | BC115: Tech Rate ($/hr) | BD115: Size | BE115: Hours | BF115: Size | BG115: Hours | BH115: Size | BI115: Hours | BJ115: Size | BK115: Hours | BL115: Size | BM115: Hours | BN115: Size | BO115: Hours | BP115: Size | BQ115: Hours | BR115: Size | BS115: Hours | BT115: Size | BU115: Hours | BV115: Size | BW115: Hours
B116: =B115+1 -> 2 | G116: =F116*D116 -> 0 | P116: =IF($I116="x",IF($D116="",0,INDEX($AQ$116:$AQ$121,MATCH($D116,$AP$116:$AP$121,1))),0) -> 0 | Q116: =IF($J116="x",IF($D116="",0,INDEX($AS$116:$AS$121,MATCH($D116,$AR$116:$AR$121,1))),0) -> 0 | R116: =IF($K116="x",IF($D116="",0,INDEX($AU$116:$AU$121,MATCH($D116,$AT$116:$AT$121,1))),0) -> 0 | S116: =IF($L116="x",IF($D116="",0,INDEX($AW$116:$AW$121,MATCH($D116,$AV$116:$AV$121,1))),0) -> 0 | T116: =IF($K116="x",IF($D116="",0,INDEX($AY$116:$AY$121,MATCH($D116,$AX$116:$AX$121,1))),0)+IF($L116="x",IF($D116="",0,INDEX($AZ$116:$AZ$121,MATCH($D116,$AX$116:$AX$121,1))),0) -> 0 | U116: =IF($D116="",0,IF(M116="x",$BB$118,0)) -> 0 | V116: =IF($D116="",0,IF(N116="x",$BB$120,0)) -> 0 | W116: =IF($O116="x",IF($D116="",0,$BA$116),0) -> 0 | X116: =IF($D116="",0,(IF(OR(O116="x",O116="xx"),1,0))*$BB$116) -> 0 | Y116: =G116+H116 -> 0 | Z116: =SUM(P116:X116) -> 0 | AA116: =IF($E116="xx",(1600*$D116+$Z116),SUM(Y116:Z116))*$AA$113 -> 0 | AB116: =SUM(Y116:AA116) -> 0 | AC116: =IF($D116="",0,INDEX($BE$116:$BE$121,MATCH($D116,$BD$116:$BD$121))*$BC$116) -> 0 | AD116: =IF($D116="",0,IF(OR($I116="x",$I116="xx"),INDEX($BG$116:$BG$121,MATCH($D116,$BF$116:$BF$121))*$BC$116,0)) -> 0 | AE116: =IF($D116="",0,IF(OR($J116="x",$J116="xx"),INDEX($BI$116:$BI$121,MATCH($D116,$BH$116:$BH$121))*$BC$116,0)) -> 0 | AF116: =IF($D116="",0,IF(OR($K116="x",$K116="xx"),INDEX($BK$116:$BK$121,MATCH($D116,$BJ$116:$BJ$121))*$CE$87,0))+IF($D116="",0,IF(OR($L116="x",$L116="xx"),INDEX($BM$116:$BM$121,MATCH($D116,$BL$116:$BL$121))*$CE$87,0)) -> 0 | AG116: =IF($D116="",0,IF(OR($M116="x",$M116="xx"),INDEX($BO$116:$BO$121,MATCH($D116,$BN$116:$BN$121))*$BC$116,0)) -> 0 | AH116: =IF($D116="",0,IF(OR($N116="x",$N116="xx"),INDEX($BQ$116:$BQ$121,MATCH($D116,$BP$116:$BP$121))*$BC$116,0)) -> 0 | AI116: =IF($D116="",0,IF(OR($O116="x",$O116="xx"),INDEX($BS$116:$BS$121,MATCH($D116,$BR$116:$BR$121))*$CE$87,0)) -> 0 | AJ116: =IF($D116="",0,((IF(OR($O116="x",$O116="xx"),1,0))*INDEX($BU$116:$BU$121,MATCH($D116,$BT$116:$BT$121))*$BC$116)) -> 0 | AK116: =IF($D116="",0,INDEX($BW$116:$BW$121,MATCH($D116,$BV$116:$BV$121))*$BC$116) -> 0 | AL116: =SUM(AC116:AK116) -> 0 | AO116: x | AP116: 0 | AQ116: 350 | AR116: 0 | AS116: 150 | AT116: 0 | AU116: =2.5*80+2*80 -> 360 | AV116: 0 | AW116: =AU116*1.5 -> 540 | AX116: 0 | AY116: =5*35 -> 175 | AZ116: =AY116*1.5 -> 262.5 | BA116: 200 | BB116: =90/2 -> 45 | BC116: 25 | BD116: 0 | BE116: 9 | BF116: 0 | BG116: 3 | BH116: 0 | BI116: 3 | BJ116: 0 | BK116: 8 | BL116: 0 | BM116: 12 | BN116: 0 | BO116: 5 | BP116: 0 | BQ116: 14 | BR116: 0 | BS116: 1 | BT116: 0 | BU116: 2 | BV116: 0 | BW116: 6
B117: =B116+1 -> 3 | G117: =F117*D117 -> 0 | P117: =IF($I117="x",IF($D117="",0,INDEX($AQ$116:$AQ$121,MATCH($D117,$AP$116:$AP$121,1))),0) -> 0 | Q117: =IF($J117="x",IF($D117="",0,INDEX($AS$116:$AS$121,MATCH($D117,$AR$116:$AR$121,1))),0) -> 0 | R117: =IF($K117="x",IF($D117="",0,INDEX($AU$116:$AU$121,MATCH($D117,$AT$116:$AT$121,1))),0) -> 0 | S117: =IF($L117="x",IF($D117="",0,INDEX($AW$116:$AW$121,MATCH($D117,$AV$116:$AV$121,1))),0) -> 0 | T117: =IF($K117="x",IF($D117="",0,INDEX($AY$116:$AY$121,MATCH($D117,$AX$116:$AX$121,1))),0)+IF($L117="x",IF($D117="",0,INDEX($AZ$116:$AZ$121,MATCH($D117,$AX$116:$AX$121,1))),0) -> 0 | U117: =IF($D117="",0,IF(M117="x",$BB$118,0)) -> 0 | V117: =IF($D117="",0,IF(N117="x",$BB$120,0)) -> 0 | W117: =IF($O117="x",IF($D117="",0,$BA$116),0) -> 0 | X117: =IF($D117="",0,(IF(OR(O117="x",O117="xx"),1,0))*$BB$116) -> 0 | Y117: =G117+H117 -> 0 | Z117: =SUM(P117:X117) -> 0 | AA117: =IF($E117="xx",(1600*$D117+$Z117),SUM(Y117:Z117))*$AA$113 -> 0 | AB117: =SUM(Y117:AA117) -> 0 | AC117: =IF($D117="",0,INDEX($BE$116:$BE$121,MATCH($D117,$BD$116:$BD$121))*$BC$116) -> 0 | AD117: =IF($D117="",0,IF(OR($I117="x",$I117="xx"),INDEX($BG$116:$BG$121,MATCH($D117,$BF$116:$BF$121))*$BC$116,0)) -> 0 | AE117: =IF($D117="",0,IF(OR($J117="x",$J117="xx"),INDEX($BI$116:$BI$121,MATCH($D117,$BH$116:$BH$121))*$BC$116,0)) -> 0 | AF117: =IF($D117="",0,IF(OR($K117="x",$K117="xx"),INDEX($BK$116:$BK$121,MATCH($D117,$BJ$116:$BJ$121))*$CE$87,0))+IF($D117="",0,IF(OR($L117="x",$L117="xx"),INDEX($BM$116:$BM$121,MATCH($D117,$BL$116:$BL$121))*$CE$87,0)) -> 0 | AG117: =IF($D117="",0,IF(OR($M117="x",$M117="xx"),INDEX($BO$116:$BO$121,MATCH($D117,$BN$116:$BN$121))*$BC$116,0)) -> 0 | AH117: =IF($D117="",0,IF(OR($N117="x",$N117="xx"),INDEX($BQ$116:$BQ$121,MATCH($D117,$BP$116:$BP$121))*$BC$116,0)) -> 0 | AI117: =IF($D117="",0,IF(OR($O117="x",$O117="xx"),INDEX($BS$116:$BS$121,MATCH($D117,$BR$116:$BR$121))*$CE$87,0)) -> 0 | AJ117: =IF($D117="",0,((IF(OR($O117="x",$O117="xx"),1,0))*INDEX($BU$116:$BU$121,MATCH($D117,$BT$116:$BT$121))*$BC$116)) -> 0 | AK117: =IF($D117="",0,INDEX($BW$116:$BW$121,MATCH($D117,$BV$116:$BV$121))*$BC$116) -> 0 | AL117: =SUM(AC117:AK117) -> 0 | AO117: xx | AP117: 5 | AQ117: 350 | AR117: 5 | AS117: 150 | AT117: 5 | AU117: =2.5*80+2*80 -> 360 | AV117: 5 | AW117: =AU117*1.5 -> 540 | AX117: 5 | AY117: =5*35 -> 175 | AZ117: =AY117*1.5 -> 262.5 | BB117: PVC Cond | BD117: 5 | BE117: 9 | BF117: 5 | BG117: 3 | BH117: 5 | BI117: 3 | BJ117: 5 | BK117: 8 | BL117: 5 | BM117: 12 | BN117: 5 | BO117: 5 | BP117: 5 | BQ117: 14 | BR117: 5 | BS117: 1 | BT117: 5 | BU117: 2 | BV117: 5 | BW117: 6
